Workbook
Name _14_July_2025: OrderLines!$G$3:$G$925
Name Branch: Feedback!$B$2:$B$221
Name Branch: Orders!$C$2:$C$361
Name Branch: OrderLines!$H$2:$H$925
Name Breakfast: OrderLines!$L$3:$L$925
Name Category: Menu!$C$2:$C$20
Name Category: OrderLines!$E$2:$E$925
Name Combination: OrderLines!$S$2:$S$925
Name ComboFlag: OrderLines!$N$2:$N$925
Name Comment: Feedback!$D$2:$D$221
Name CustomerType: Orders!$D$2:$D$361
Name Date: Feedback!$A$2:$A$221
Name Date: WasteLog!$A$2:$A$121
Name DiscountFlag: OrderLines!$O$2:$O$925
Name DiscountPct: Orders!$G$2:$G$361
Name DiscountPct: OrderLines!$I$2:$I$925
Name FoodCost: OrderLines!$U$2:$U$925
Name GM: OrderLines!$T$2:$T$925
Name Head_Office_Café: OrderLines!$H$3:$H$925
Name id: OrderLines!$X$34:$X$40
Name item: OrderLines!$Y$34:$Y$40
Name ItemName: OrderLines!$R$2:$R$925
Name ItemName: Menu!$B$2:$B$20
Name July: OrderLines!$K$3:$K$925
Name LastRestockDate: Inventory!$E$2:$E$20
Name LeadTimeDays: Inventory!$D$2:$D$20
Name LineNetAmount: OrderLines!$J$2:$J$925
Name MonthName: OrderLines!$K$2:$K$925
Name O00001_: OrderLines!$A$3:$A$925
Name OK: OrderLines!$O$3:$O$925
Name OnHandQty: Inventory!$B$2:$B$20
Name OrderDate: Orders!$H$2:$H$361
Name OrderDate: OrderLines!$G$2:$G$925
Name OrderDateTime: Orders!$B$2:$B$361
Name OrderID: Orders!$A$2:$A$361
Name OrderID: OrderLines!$A$2:$A$925
Name PaymentType: Orders!$E$2:$E$361
Name PaymentType: OrderLines!$M$2:$M$925
Name Poha: OrderLines!$R$3:$R$925
Name Profit: OrderLines!$Q$2:$Q$925
Name Qty: WasteLog!$C$2:$C$121
Name Qty: OrderLines!$C$2:$C$925
Name Rating: Feedback!$C$2:$C$221
Name Reason: WasteLog!$D$2:$D$121
Name region: Orders!$Q$17:$Q$21
Name ReorderPoint: Inventory!$C$2:$C$20
Name sales: Orders!$R$17:$R$21
Name Shift: Orders!$F$2:$F$361
Name Shift: OrderLines!$L$2:$L$925
Name SHJ7XV: OrderLines!$B$3:$B$925
Name Single: OrderLines!$N$3:$N$925
Name SKU: Inventory!$A$2:$A$20
Name SKU: Menu!$A$2:$A$20
Name SKU: WasteLog!$B$2:$B$121
Name SKU: OrderLines!$B$2:$B$925
Name Slicer_Branch: #N/A
Name Slicer_Branch1: #N/A
Name Slicer_Branch2: #N/A
Name Slicer_Shift: #N/A
Name Slicer_Shift1: #N/A

Sheet Orders
A1: OrderID | B1: OrderDateTime | C1: Branch | D1: CustomerType | E1: PaymentType | F1: Shift | G1: DiscountPct | H1: OrderDate | I1: Has beverage | J1: LineAmount | K1: ItemList | L1: TotalCost | M1: GrossProfit | N1: combo flag | O1: discount flag | T1: Add a combo flag( based on category) on orders
A2: O00001 | B2: 45852.096 | C2: Head Office Café | D2: Visitor | E2: UPI | F2: Breakfast | G2: 0.06 | H2: =INT($B2) -> 45852 | I2: =IF(COUNTIFS([0]!OrderID,Table3[[#This Row],[OrderID]],[0]!Category,"beverage")>0,"yes","no") -> no | J2: =SUMIFS([0]!LineNetAmount,[0]!OrderID,Table3[[#This Row],[OrderID]]) -> 147.909 | K2: {=_xlfn.TEXTJOIN("+",,_xlfn._xlws.SORT(_xlfn.UNIQUE(_xlfn._xlws.FILTER([0]!Category,[0]!OrderID=Table3[[#This Row],[OrderID]]))))} -> Snack | L2: =SUMIFS([0]!FoodCost,[0]!OrderID,Table3[[#This Row],[OrderID]]) -> 77.4 | M2: =Table3[[#This Row],[LineAmount]]-Table3[[#This Row],[TotalCost]] -> 70.509 | N2: =IF(AND(COUNTIFS([0]!OrderID,Table3[[#This Row],[OrderID]],[0]!Category,"hot meal")>0,COUNTIFS([0]!OrderID,Table3[[#This Row],[OrderID]],[0]!Category,"beverage")>0),"combo","single") -> single | O2: =IF((Table3[[#This Row],[LineAmount]]/(1-Table3[[#This Row],[DiscountPct]]))*Table3[[#This Row],[DiscountPct]]>40,"High Disc","OK") -> OK | T2: if order has >= 1 hot meal >=1 bev, return combo,ow single
A3: O00002 | B3: 45862.843 | C3: Plant 2 Canteen | D3: Staff | E3: Cash | F3: Dinner | G3: 0.05 | H3: =INT($B3) -> 45862 | I3: =IF(COUNTIFS([0]!OrderID,Table3[[#This Row],[OrderID]],[0]!Category,"beverage")>0,"yes","no") -> yes | J3: =SUMIFS([0]!LineNetAmount,[0]!OrderID,Table3[[#This Row],[OrderID]]) -> 101.5455 | K3: {=_xlfn.TEXTJOIN("+",,_xlfn._xlws.SORT(_xlfn.UNIQUE(_xlfn._xlws.FILTER([0]!Category,[0]!OrderID=Table3[[#This Row],[OrderID]]))))} -> Beverage+Dessert | L3: =SUMIFS([0]!FoodCost,[0]!OrderID,Table3[[#This Row],[OrderID]]) -> 52.41 | M3: =Table3[[#This Row],[LineAmount]]-Table3[[#This Row],[TotalCost]] -> 49.1355 | N3: =IF(AND(COUNTIFS([0]!OrderID,Table3[[#This Row],[OrderID]],[0]!Category,"hot meal")>0,COUNTIFS([0]!OrderID,Table3[[#This Row],[OrderID]],[0]!Category,"beverage")>0),"combo","single") -> single | O3: =IF((Table3[[#This Row],[LineAmount]]/(1-Table3[[#This Row],[DiscountPct]]))*Table3[[#This Row],[DiscountPct]]>40,"High Disc","OK") -> OK | Q3: day
A4: O00003 | B4: 45848.661 | C4: Head Office Café | D4: Staff | E4: Card | F4: Lunch | G4: 0 | H4: =INT($B4) -> 45848 | I4: =IF(COUNTIFS([0]!OrderID,Table3[[#This Row],[OrderID]],[0]!Category,"beverage")>0,"yes","no") -> yes | J4: =SUMIFS([0]!LineNetAmount,[0]!OrderID,Table3[[#This Row],[OrderID]]) -> 668.96 | K4: {=_xlfn.TEXTJOIN("+",,_xlfn._xlws.SORT(_xlfn.UNIQUE(_xlfn._xlws.FILTER([0]!Category,[0]!OrderID=Table3[[#This Row],[OrderID]]))))} -> Beverage+Hot Meal+Snack | L4: =SUMIFS([0]!FoodCost,[0]!OrderID,Table3[[#This Row],[OrderID]]) -> 291.24 | M4: =Table3[[#This Row],[LineAmount]]-Table3[[#This Row],[TotalCost]] -> 377.72 | N4: =IF(AND(COUNTIFS([0]!OrderID,Table3[[#This Row],[OrderID]],[0]!Category,"hot meal")>0,COUNTIFS([0]!OrderID,Table3[[#This Row],[OrderID]],[0]!Category,"beverage")>0),"combo","single") -> combo | O4: =IF((Table3[[#This Row],[LineAmount]]/(1-Table3[[#This Row],[DiscountPct]]))*Table3[[#This Row],[DiscountPct]]>40,"High Disc","OK") -> OK | Q4: 1 | R4: 1
A5: O00004 | B5: 45879.164 | C5: Plant 2 Canteen | D5: Visitor | E5: Cash | F5: Breakfast | G5: 0.03 | H5: =INT($B5) -> 45879 | I5: =IF(COUNTIFS([0]!OrderID,Table3[[#This Row],[OrderID]],[0]!Category,"beverage")>0,"yes","no") -> no | J5: =SUMIFS([0]!LineNetAmount,[0]!OrderID,Table3[[#This Row],[OrderID]]) -> 477.4146 | K5: {=_xlfn.TEXTJOIN("+",,_xlfn._xlws.SORT(_xlfn.UNIQUE(_xlfn._xlws.FILTER([0]!Category,[0]!OrderID=Table3[[#This Row],[OrderID]]))))} -> Hot Meal | L5: =SUMIFS([0]!FoodCost,[0]!OrderID,Table3[[#This Row],[OrderID]]) -> 224.16 | M5: =Table3[[#This Row],[LineAmount]]-Table3[[#This Row],[TotalCost]] -> 253.2546 | N5: =IF(AND(COUNTIFS([0]!OrderID,Table3[[#This Row],[OrderID]],[0]!Category,"hot meal")>0,COUNTIFS([0]!OrderID,Table3[[#This Row],[OrderID]],[0]!Category,"beverage")>0),"combo","single") -> single | O5: =IF((Table3[[#This Row],[LineAmount]]/(1-Table3[[#This Row],[DiscountPct]]))*Table3[[#This Row],[DiscountPct]]>40,"High Disc","OK") -> OK | Q5: 2 | R5: 0 | T5: Create a disc flag per order.
A6: O00005 | B6: 45845.135 | C6: Plant 2 Canteen | D6: Visitor | E6: Card | F6: Breakfast | G6: 0.04 | H6: =INT($B6) -> 45845 | I6: =IF(COUNTIFS([0]!OrderID,Table3[[#This Row],[OrderID]],[0]!Category,"beverage")>0,"yes","no") -> yes | J6: =SUMIFS([0]!LineNetAmount,[0]!OrderID,Table3[[#This Row],[OrderID]]) -> 95.0112 | K6: {=_xlfn.TEXTJOIN("+",,_xlfn._xlws.SORT(_xlfn.UNIQUE(_xlfn._xlws.FILTER([0]!Category,[0]!OrderID=Table3[[#This Row],[OrderID]]))))} -> Beverage+Snack | L6: =SUMIFS([0]!FoodCost,[0]!OrderID,Table3[[#This Row],[OrderID]]) -> 49.7 | M6: =Table3[[#This Row],[LineAmount]]-Table3[[#This Row],[TotalCost]] -> 45.3112 | N6: =IF(AND(COUNTIFS([0]!OrderID,Table3[[#This Row],[OrderID]],[0]!Category,"hot meal")>0,COUNTIFS([0]!OrderID,Table3[[#This Row],[OrderID]],[0]!Category,"beverage")>0),"combo","single") -> single | O6: =IF((Table3[[#This Row],[LineAmount]]/(1-Table3[[#This Row],[DiscountPct]]))*Table3[[#This Row],[DiscountPct]]>40,"High Disc","OK") -> OK | Q6: 3 | R6: 1 | T6: if total order discount value > 40, "highdisc","ok"
A7: O00006 | B7: 45863.392 | C7: Plant 1 Canteen | D7: Worker | E7: UPI | F7: Breakfast | G7: 0.1 | H7: =INT($B7) -> 45863 | I7: =IF(COUNTIFS([0]!OrderID,Table3[[#This Row],[OrderID]],[0]!Category,"beverage")>0,"yes","no") -> yes | J7: =SUMIFS([0]!LineNetAmount,[0]!OrderID,Table3[[#This Row],[OrderID]]) -> 54.297 | K7: {=_xlfn.TEXTJOIN("+",,_xlfn._xlws.SORT(_xlfn.UNIQUE(_xlfn._xlws.FILTER([0]!Category,[0]!OrderID=Table3[[#This Row],[OrderID]]))))} -> Beverage | L7: =SUMIFS([0]!FoodCost,[0]!OrderID,Table3[[#This Row],[OrderID]]) -> 24 | M7: =Table3[[#This Row],[LineAmount]]-Table3[[#This Row],[TotalCost]] -> 30.297 | N7: =IF(AND(COUNTIFS([0]!OrderID,Table3[[#This Row],[OrderID]],[0]!Category,"hot meal")>0,COUNTIFS([0]!OrderID,Table3[[#This Row],[OrderID]],[0]!Category,"beverage")>0),"combo","single") -> single | O7: =IF((Table3[[#This Row],[LineAmount]]/(1-Table3[[#This Row],[DiscountPct]]))*Table3[[#This Row],[DiscountPct]]>40,"High Disc","OK") -> OK | Q7: 4 | R7: 1
A8: O00007 | B8: 45852.86 | C8: Plant 2 Canteen | D8: Worker | E8: Card | F8: Dinner | G8: 0.07 | H8: =INT($B8) -> 45852 | I8: =IF(COUNTIFS([0]!OrderID,Table3[[#This Row],[OrderID]],[0]!Category,"beverage")>0,"yes","no") -> yes | J8: =SUMIFS([0]!LineNetAmount,[0]!OrderID,Table3[[#This Row],[OrderID]]) -> 348.4152 | K8: {=_xlfn.TEXTJOIN("+",,_xlfn._xlws.SORT(_xlfn.UNIQUE(_xlfn._xlws.FILTER([0]!Category,[0]!OrderID=Table3[[#This Row],[OrderID]]))))} -> Beverage+Hot Meal | L8: =SUMIFS([0]!FoodCost,[0]!OrderID,Table3[[#This Row],[OrderID]]) -> 159.98 | M8: =Table3[[#This Row],[LineAmount]]-Table3[[#This Row],[TotalCost]] -> 188.4352 | N8: =IF(AND(COUNTIFS([0]!OrderID,Table3[[#This Row],[OrderID]],[0]!Category,"hot meal")>0,COUNTIFS([0]!OrderID,Table3[[#This Row],[OrderID]],[0]!Category,"beverage")>0),"combo","single") -> combo | O8: =IF((Table3[[#This Row],[LineAmount]]/(1-Table3[[#This Row],[DiscountPct]]))*Table3[[#This Row],[DiscountPct]]>40,"High Disc","OK") -> OK | Q8: 5 | R8: 1
A9: O00008 | B9: 45863.504 | C9: Plant 1 Canteen | D9: Staff | E9: UPI | F9: Lunch | G9: 0 | H9: =INT($B9) -> 45863 | I9: =IF(COUNTIFS([0]!OrderID,Table3[[#This Row],[OrderID]],[0]!Category,"beverage")>0,"yes","no") -> yes | J9: =SUMIFS([0]!LineNetAmount,[0]!OrderID,Table3[[#This Row],[OrderID]]) -> 223.75 | K9: {=_xlfn.TEXTJOIN("+",,_xlfn._xlws.SORT(_xlfn.UNIQUE(_xlfn._xlws.FILTER([0]!Category,[0]!OrderID=Table3[[#This Row],[OrderID]]))))} -> Beverage+Dessert | L9: =SUMIFS([0]!FoodCost,[0]!OrderID,Table3[[#This Row],[OrderID]]) -> 110.98 | M9: =Table3[[#This Row],[LineAmount]]-Table3[[#This Row],[TotalCost]] -> 112.77 | N9: =IF(AND(COUNTIFS([0]!OrderID,Table3[[#This Row],[OrderID]],[0]!Category,"hot meal")>0,COUNTIFS([0]!OrderID,Table3[[#This Row],[OrderID]],[0]!Category,"beverage")>0),"combo","single") -> single | O9: =IF((Table3[[#This Row],[LineAmount]]/(1-Table3[[#This Row],[DiscountPct]]))*Table3[[#This Row],[DiscountPct]]>40,"High Disc","OK") -> OK | Q9: 6 | R9: 1
A10: O00009 | B10: 45844.162 | C10: Head Office Café | D10: Visitor | E10: Cash | F10: Breakfast | G10: 0.07 | H10: =INT($B10) -> 45844 | I10: =IF(COUNTIFS([0]!OrderID,Table3[[#This Row],[OrderID]],[0]!Category,"beverage")>0,"yes","no") -> no | J10: =SUMIFS([0]!LineNetAmount,[0]!OrderID,Table3[[#This Row],[OrderID]]) -> 459.2898 | K10: {=_xlfn.TEXTJOIN("+",,_xlfn._xlws.SORT(_xlfn.UNIQUE(_xlfn._xlws.FILTER([0]!Category,[0]!OrderID=Table3[[#This Row],[OrderID]]))))} -> Dessert+Hot Meal+Snack | L10: =SUMIFS([0]!FoodCost,[0]!OrderID,Table3[[#This Row],[OrderID]]) -> 225.97 | M10: =Table3[[#This Row],[LineAmount]]-Table3[[#This Row],[TotalCost]] -> 233.3198 | N10: =IF(AND(COUNTIFS([0]!OrderID,Table3[[#This Row],[OrderID]],[0]!Category,"hot meal")>0,COUNTIFS([0]!OrderID,Table3[[#This Row],[OrderID]],[0]!Category,"beverage")>0),"combo","single") -> single | O10: =IF((Table3[[#This Row],[LineAmount]]/(1-Table3[[#This Row],[DiscountPct]]))*Table3[[#This Row],[DiscountPct]]>40,"High Disc","OK") -> OK | Q10: 7 | R10: 0
A11: O00010 | B11: 45862.2 | C11: Plant 1 Canteen | D11: Staff | E11: Card | F11: Breakfast | G11: 0.04 | H11: =INT($B11) -> 45862 | I11: =IF(COUNTIFS([0]!OrderID,Table3[[#This Row],[OrderID]],[0]!Category,"beverage")>0,"yes","no") -> yes | J11: =SUMIFS([0]!LineNetAmount,[0]!OrderID,Table3[[#This Row],[OrderID]]) -> 420.0768 | K11: {=_xlfn.TEXTJOIN("+",,_xlfn._xlws.SORT(_xlfn.UNIQUE(_xlfn._xlws.FILTER([0]!Category,[0]!OrderID=Table3[[#This Row],[OrderID]]))))} -> Beverage+Dessert+Hot Meal+Snack | L11: =SUMIFS([0]!FoodCost,[0]!OrderID,Table3[[#This Row],[OrderID]]) -> 204.88 | M11: =Table3[[#This Row],[LineAmount]]-Table3[[#This Row],[TotalCost]] -> 215.1968 | N11: =IF(AND(COUNTIFS([0]!OrderID,Table3[[#This Row],[OrderID]],[0]!Category,"hot meal")>0,COUNTIFS([0]!OrderID,Table3[[#This Row],[OrderID]],[0]!Category,"beverage")>0),"combo","single") -> combo | O11: =IF((Table3[[#This Row],[LineAmount]]/(1-Table3[[#This Row],[DiscountPct]]))*Table3[[#This Row],[DiscountPct]]>40,"High Disc","OK") -> OK | T11: if total order discount value = pre disc total* disc pct
A12: O00011 | B12: 45860.003 | C12: Plant 2 Canteen | D12: Worker | E12: Cash | F12: Breakfast | G12: 0.03 | H12: =INT($B12) -> 45860 | I12: =IF(COUNTIFS([0]!OrderID,Table3[[#This Row],[OrderID]],[0]!Category,"beverage")>0,"yes","no") -> yes | J12: =SUMIFS([0]!LineNetAmount,[0]!OrderID,Table3[[#This Row],[OrderID]]) -> 27.5771 | K12: {=_xlfn.TEXTJOIN("+",,_xlfn._xlws.SORT(_xlfn.UNIQUE(_xlfn._xlws.FILTER([0]!Category,[0]!OrderID=Table3[[#This Row],[OrderID]]))))} -> Beverage | L12: =SUMIFS([0]!FoodCost,[0]!OrderID,Table3[[#This Row],[OrderID]]) -> 13.89 | M12: =Table3[[#This Row],[LineAmount]]-Table3[[#This Row],[TotalCost]] -> 13.6871 | N12: =IF(AND(COUNTIFS([0]!OrderID,Table3[[#This Row],[OrderID]],[0]!Category,"hot meal")>0,COUNTIFS([0]!OrderID,Table3[[#This Row],[OrderID]],[0]!Category,"beverage")>0),"combo","single") -> single | O12: =IF((Table3[[#This Row],[LineAmount]]/(1-Table3[[#This Row],[DiscountPct]]))*Table3[[#This Row],[DiscountPct]]>40,"High Disc","OK") -> OK | W12: (p*q)*disc pct
A13: O00012 | B13: 45839.459 | C13: Plant 2 Canteen | D13: Staff | E13: Card | F13: Lunch | G13: 0.08 | H13: =INT($B13) -> 45839 | I13: =IF(COUNTIFS([0]!OrderID,Table3[[#This Row],[OrderID]],[0]!Category,"beverage")>0,"yes","no") -> no | J13: =SUMIFS([0]!LineNetAmount,[0]!OrderID,Table3[[#This Row],[OrderID]]) -> 98.118 | K13: {=_xlfn.TEXTJOIN("+",,_xlfn._xlws.SORT(_xlfn.UNIQUE(_xlfn._xlws.FILTER([0]!Category,[0]!OrderID=Table3[[#This Row],[OrderID]]))))} -> Dessert+Snack | L13: =SUMIFS([0]!FoodCost,[0]!OrderID,Table3[[#This Row],[OrderID]]) -> 47.75 | M13: =Table3[[#This Row],[LineAmount]]-Table3[[#This Row],[TotalCost]] -> 50.368 | N13: =IF(AND(COUNTIFS([0]!OrderID,Table3[[#This Row],[OrderID]],[0]!Category,"hot meal")>0,COUNTIFS([0]!OrderID,Table3[[#This Row],[OrderID]],[0]!Category,"beverage")>0),"combo","single") -> single | O13: =IF((Table3[[#This Row],[LineAmount]]/(1-Table3[[#This Row],[DiscountPct]]))*Table3[[#This Row],[DiscountPct]]>40,"High Disc","OK") -> OK
A14: O00013 | B14: 45880.32 | C14: Head Office Café | D14: Visitor | E14: UPI | F14: Breakfast | G14: 0.1 | H14: =INT($B14) -> 45880 | I14: =IF(COUNTIFS([0]!OrderID,Table3[[#This Row],[OrderID]],[0]!Category,"beverage")>0,"yes","no") -> yes | J14: =SUMIFS([0]!LineNetAmount,[0]!OrderID,Table3[[#This Row],[OrderID]]) -> 807.876 | K14: {=_xlfn.TEXTJOIN("+",,_xlfn._xlws.SORT(_xlfn.UNIQUE(_xlfn._xlws.FILTER([0]!Category,[0]!OrderID=Table3[[#This Row],[OrderID]]))))} -> Beverage+Dessert+Hot Meal | L14: =SUMIFS([0]!FoodCost,[0]!OrderID,Table3[[#This Row],[OrderID]]) -> 411.2 | M14: =Table3[[#This Row],[LineAmount]]-Table3[[#This Row],[TotalCost]] -> 396.676 | N14: =IF(AND(COUNTIFS([0]!OrderID,Table3[[#This Row],[OrderID]],[0]!Category,"hot meal")>0,COUNTIFS([0]!OrderID,Table3[[#This Row],[OrderID]],[0]!Category,"beverage")>0),"combo","single") -> combo | O14: =IF((Table3[[#This Row],[LineAmount]]/(1-Table3[[#This Row],[DiscountPct]]))*Table3[[#This Row],[DiscountPct]]>40,"High Disc","OK") -> High Disc
A15: O00014 | B15: 45854.279 | C15: Plant 1 Canteen | D15: Staff | E15: Cash | F15: Breakfast | G15: 0.1 | H15: =INT($B15) -> 45854 | I15: =IF(COUNTIFS([0]!OrderID,Table3[[#This Row],[OrderID]],[0]!Category,"beverage")>0,"yes","no") -> yes | J15: =SUMIFS([0]!LineNetAmount,[0]!OrderID,Table3[[#This Row],[OrderID]]) -> 181.476 | K15: {=_xlfn.TEXTJOIN("+",,_xlfn._xlws.SORT(_xlfn.UNIQUE(_xlfn._xlws.FILTER([0]!Category,[0]!OrderID=Table3[[#This Row],[OrderID]]))))} -> Beverage+Dessert | L15: =SUMIFS([0]!FoodCost,[0]!OrderID,Table3[[#This Row],[OrderID]]) -> 98.35 | M15: =Table3[[#This Row],[LineAmount]]-Table3[[#This Row],[TotalCost]] -> 83.126 | N15: =IF(AND(COUNTIFS([0]!OrderID,Table3[[#This Row],[OrderID]],[0]!Category,"hot meal")>0,COUNTIFS([0]!OrderID,Table3[[#This Row],[OrderID]],[0]!Category,"beverage")>0),"combo","single") -> single | O15: =IF((Table3[[#This Row],[LineAmount]]/(1-Table3[[#This Row],[DiscountPct]]))*Table3[[#This Row],[DiscountPct]]>40,"High Disc","OK") -> OK
A16: O00015 | B16: 45895.483 | C16: Head Office Café | D16: Visitor | E16: Cash | F16: Lunch | G16: 0.03 | H16: =INT($B16) -> 45895 | I16: =IF(COUNTIFS([0]!OrderID,Table3[[#This Row],[OrderID]],[0]!Category,"beverage")>0,"yes","no") -> yes | J16: =SUMIFS([0]!LineNetAmount,[0]!OrderID,Table3[[#This Row],[OrderID]]) -> 410.1839 | K16: {=_xlfn.TEXTJOIN("+",,_xlfn._xlws.SORT(_xlfn.UNIQUE(_xlfn._xlws.FILTER([0]!Category,[0]!OrderID=Table3[[#This Row],[OrderID]]))))} -> Beverage+Dessert+Hot Meal | L16: =SUMIFS([0]!FoodCost,[0]!OrderID,Table3[[#This Row],[OrderID]]) -> 186.05 | M16: =Table3[[#This Row],[LineAmount]]-Table3[[#This Row],[TotalCost]] -> 224.1339 | N16: =IF(AND(COUNTIFS([0]!OrderID,Table3[[#This Row],[OrderID]],[0]!Category,"hot meal")>0,COUNTIFS([0]!OrderID,Table3[[#This Row],[OrderID]],[0]!Category,"beverage")>0),"combo","single") -> combo | O16: =IF((Table3[[#This Row],[LineAmount]]/(1-Table3[[#This Row],[DiscountPct]]))*Table3[[#This Row],[DiscountPct]]>40,"High Disc","OK") -> OK
A17: O00016 | B17: 45844.8 | C17: Plant 1 Canteen | D17: Visitor | E17: Card | F17: Dinner | G17: 0.05 | H17: =INT($B17) -> 45844 | I17: =IF(COUNTIFS([0]!OrderID,Table3[[#This Row],[OrderID]],[0]!Category,"beverage")>0,"yes","no") -> no | J17: =SUMIFS([0]!LineNetAmount,[0]!OrderID,Table3[[#This Row],[OrderID]]) -> 486.9415 | K17: {=_xlfn.TEXTJOIN("+",,_xlfn._xlws.SORT(_xlfn.UNIQUE(_xlfn._xlws.FILTER([0]!Category,[0]!OrderID=Table3[[#This Row],[OrderID]]))))} -> Dessert+Hot Meal+Snack | L17: =SUMIFS([0]!FoodCost,[0]!OrderID,Table3[[#This Row],[OrderID]]) -> 238.57 | M17: =Table3[[#This Row],[LineAmount]]-Table3[[#This Row],[TotalCost]] -> 248.3715 | N17: =IF(AND(COUNTIFS([0]!OrderID,Table3[[#This Row],[OrderID]],[0]!Category,"hot meal")>0,COUNTIFS([0]!OrderID,Table3[[#This Row],[OrderID]],[0]!Category,"beverage")>0),"combo","single") -> single | O17: =IF((Table3[[#This Row],[LineAmount]]/(1-Table3[[#This Row],[DiscountPct]]))*Table3[[#This Row],[DiscountPct]]>40,"High Disc","OK") -> OK
A18: O00017 | B18: 45890.817 | C18: Plant 1 Canteen | D18: Worker | E18: UPI | F18: Dinner | G18: 0.07 | H18: =INT($B18) -> 45890 | I18: =IF(COUNTIFS([0]!OrderID,Table3[[#This Row],[OrderID]],[0]!Category,"beverage")>0,"yes","no") -> yes | J18: =SUMIFS([0]!LineNetAmount,[0]!OrderID,Table3[[#This Row],[OrderID]]) -> 30.6714 | K18: {=_xlfn.TEXTJOIN("+",,_xlfn._xlws.SORT(_xlfn.UNIQUE(_xlfn._xlws.FILTER([0]!Category,[0]!OrderID=Table3[[#This Row],[OrderID]]))))} -> Beverage | L18: =SUMIFS([0]!FoodCost,[0]!OrderID,Table3[[#This Row],[OrderID]]) -> 11.84 | M18: =Table3[[#This Row],[LineAmount]]-Table3[[#This Row],[TotalCost]] -> 18.8314 | N18: =IF(AND(COUNTIFS([0]!OrderID,Table3[[#This Row],[OrderID]],[0]!Category,"hot meal")>0,COUNTIFS([0]!OrderID,Table3[[#This Row],[OrderID]],[0]!Category,"beverage")>0),"combo","single") -> single | O18: =IF((Table3[[#This Row],[LineAmount]]/(1-Table3[[#This Row],[DiscountPct]]))*Table3[[#This Row],[DiscountPct]]>40,"High Disc","OK") -> OK | R18: 450 | S18: 1000g | V18: 32 | W18: 1000
A19: O00018 | B19: 45857.292 | C19: Plant 1 Canteen | D19: Visitor | E19: Cash | F19: Breakfast | G19: 0.1 | H19: =INT($B19) -> 45857 | I19: =IF(COUNTIFS([0]!OrderID,Table3[[#This Row],[OrderID]],[0]!Category,"beverage")>0,"yes","no") -> yes | J19: =SUMIFS([0]!LineNetAmount,[0]!OrderID,Table3[[#This Row],[OrderID]]) -> 164.484 | K19: {=_xlfn.TEXTJOIN("+",,_xlfn._xlws.SORT(_xlfn.UNIQUE(_xlfn._xlws.FILTER([0]!Category,[0]!OrderID=Table3[[#This Row],[OrderID]]))))} -> Beverage+Dessert | L19: =SUMIFS([0]!FoodCost,[0]!OrderID,Table3[[#This Row],[OrderID]]) -> 72.65 | M19: =Table3[[#This Row],[LineAmount]]-Table3[[#This Row],[TotalCost]] -> 91.834 | N19: =IF(AND(COUNTIFS([0]!OrderID,Table3[[#This Row],[OrderID]],[0]!Category,"hot meal")>0,COUNTIFS([0]!OrderID,Table3[[#This Row],[OrderID]],[0]!Category,"beverage")>0),"combo","single") -> single | O19: =IF((Table3[[#This Row],[LineAmount]]/(1-Table3[[#This Row],[DiscountPct]]))*Table3[[#This Row],[DiscountPct]]>40,"High Disc","OK") -> OK | R19: ? | S19: 350g | V19: ? | W19: 120
A20: O00019 | B20: 45878.453 | C20: Plant 1 Canteen | D20: Visitor | E20: Cash | F20: Breakfast | G20: 0.04 | H20: =INT($B20) -> 45878 | I20: =IF(COUNTIFS([0]!OrderID,Table3[[#This Row],[OrderID]],[0]!Category,"beverage")>0,"yes","no") -> no | J20: =SUMIFS([0]!LineNetAmount,[0]!OrderID,Table3[[#This Row],[OrderID]]) -> 701.5296 | K20: {=_xlfn.TEXTJOIN("+",,_xlfn._xlws.SORT(_xlfn.UNIQUE(_xlfn._xlws.FILTER([0]!Category,[0]!OrderID=Table3[[#This Row],[OrderID]]))))} -> Hot Meal+Snack | L20: =SUMIFS([0]!FoodCost,[0]!OrderID,Table3[[#This Row],[OrderID]]) -> 359.21 | M20: =Table3[[#This Row],[LineAmount]]-Table3[[#This Row],[TotalCost]] -> 342.3196 | N20: =IF(AND(COUNTIFS([0]!OrderID,Table3[[#This Row],[OrderID]],[0]!Category,"hot meal")>0,COUNTIFS([0]!OrderID,Table3[[#This Row],[OrderID]],[0]!Category,"beverage")>0),"combo","single") -> single | O20: =IF((Table3[[#This Row],[LineAmount]]/(1-Table3[[#This Row],[DiscountPct]]))*Table3[[#This Row],[DiscountPct]]>40,"High Disc","OK") -> OK
A21: O00020 | B21: 45847.21 | C21: Plant 2 Canteen | D21: Visitor | E21: UPI | F21: Breakfast | G21: 0.05 | H21: =INT($B21) -> 45847 | I21: =IF(COUNTIFS([0]!OrderID,Table3[[#This Row],[OrderID]],[0]!Category,"beverage")>0,"yes","no") -> yes | J21: =SUMIFS([0]!LineNetAmount,[0]!OrderID,Table3[[#This Row],[OrderID]]) -> 474.753 | K21: {=_xlfn.TEXTJOIN("+",,_xlfn._xlws.SORT(_xlfn.UNIQUE(_xlfn._xlws.FILTER([0]!Category,[0]!OrderID=Table3[[#This Row],[OrderID]]))))} -> Beverage+Dessert+Hot Meal | L21: =SUMIFS([0]!FoodCost,[0]!OrderID,Table3[[#This Row],[OrderID]]) -> 212.14 | M21: =Table3[[#This Row],[LineAmount]]-Table3[[#This Row],[TotalCost]] -> 262.613 | N21: =IF(AND(COUNTIFS([0]!OrderID,Table3[[#This Row],[OrderID]],[0]!Category,"hot meal")>0,COUNTIFS([0]!OrderID,Table3[[#This Row],[OrderID]],[0]!Category,"beverage")>0),"combo","single") -> combo | O21: =IF((Table3[[#This Row],[LineAmount]]/(1-Table3[[#This Row],[DiscountPct]]))*Table3[[#This Row],[DiscountPct]]>40,"High Disc","OK") -> OK
A22: O00021 | B22: 45869.966 | C22: Plant 2 Canteen | D22: Worker | E22: UPI | F22: Dinner | G22: 0.02 | H22: =INT($B22) -> 45869 | I22: =IF(COUNTIFS([0]!OrderID,Table3[[#This Row],[OrderID]],[0]!Category,"beverage")>0,"yes","no") -> no | J22: =SUMIFS([0]!LineNetAmount,[0]!OrderID,Table3[[#This Row],[OrderID]]) -> 291.7264 | K22: {=_xlfn.TEXTJOIN("+",,_xlfn._xlws.SORT(_xlfn.UNIQUE(_xlfn._xlws.FILTER([0]!Category,[0]!OrderID=Table3[[#This Row],[OrderID]]))))} -> Snack | L22: =SUMIFS([0]!FoodCost,[0]!OrderID,Table3[[#This Row],[OrderID]]) -> 138.13 | M22: =Table3[[#This Row],[LineAmount]]-Table3[[#This Row],[TotalCost]] -> 153.5964 | N22: =IF(AND(COUNTIFS([0]!OrderID,Table3[[#This Row],[OrderID]],[0]!Category,"hot meal")>0,COUNTIFS([0]!OrderID,Table3[[#This Row],[OrderID]],[0]!Category,"beverage")>0),"combo","single") -> single | O22: =IF((Table3[[#This Row],[LineAmount]]/(1-Table3[[#This Row],[DiscountPct]]))*Table3[[#This Row],[DiscountPct]]>40,"High Disc","OK") -> OK | R22: =450/2 -> 225
A23: O00022 | B23: 45862.424 | C23: Plant 2 Canteen | D23: Staff | E23: Cash | F23: Breakfast | G23: 0.01 | H23: =INT($B23) -> 45862 | I23: =IF(COUNTIFS([0]!OrderID,Table3[[#This Row],[OrderID]],[0]!Category,"beverage")>0,"yes","no") -> yes | J23: =SUMIFS([0]!LineNetAmount,[0]!OrderID,Table3[[#This Row],[OrderID]]) -> 364.2903 | K23: {=_xlfn.TEXTJOIN("+",,_xlfn._xlws.SORT(_xlfn.UNIQUE(_xlfn._xlws.FILTER([0]!Category,[0]!OrderID=Table3[[#This Row],[OrderID]]))))} -> Beverage+Dessert+Hot Meal | L23: =SUMIFS([0]!FoodCost,[0]!OrderID,Table3[[#This Row],[OrderID]]) -> 170.97 | M23: =Table3[[#This Row],[LineAmount]]-Table3[[#This Row],[TotalCost]] -> 193.3203 | N23: =IF(AND(COUNTIFS([0]!OrderID,Table3[[#This Row],[OrderID]],[0]!Category,"hot meal")>0,COUNTIFS([0]!OrderID,Table3[[#This Row],[OrderID]],[0]!Category,"beverage")>0),"combo","single") -> combo | O23: =IF((Table3[[#This Row],[LineAmount]]/(1-Table3[[#This Row],[DiscountPct]]))*Table3[[#This Row],[DiscountPct]]>40,"High Disc","OK") -> OK
A24: O00023 | B24: 45883.642 | C24: Plant 2 Canteen | D24: Worker | E24: Cash | F24: Lunch | G24: 0.09 | H24: =INT($B24) -> 45883 | I24: =IF(COUNTIFS([0]!OrderID,Table3[[#This Row],[OrderID]],[0]!Category,"beverage")>0,"yes","no") -> yes | J24: =SUMIFS([0]!LineNetAmount,[0]!OrderID,Table3[[#This Row],[OrderID]]) -> 242.242 | K24: {=_xlfn.TEXTJOIN("+",,_xlfn._xlws.SORT(_xlfn.UNIQUE(_xlfn._xlws.FILTER([0]!Category,[0]!OrderID=Table3[[#This Row],[OrderID]]))))} -> Beverage+Hot Meal | L24: =SUMIFS([0]!FoodCost,[0]!OrderID,Table3[[#This Row],[OrderID]]) -> 120.08 | M24: =Table3[[#This Row],[LineAmount]]-Table3[[#This Row],[TotalCost]] -> 122.162 | N24: =IF(AND(COUNTIFS([0]!OrderID,Table3[[#This Row],[OrderID]],[0]!Category,"hot meal")>0,COUNTIFS([0]!OrderID,Table3[[#This Row],[OrderID]],[0]!Category,"beverage")>0),"combo","single") -> combo | O24: =IF((Table3[[#This Row],[LineAmount]]/(1-Table3[[#This Row],[DiscountPct]]))*Table3[[#This Row],[DiscountPct]]>40,"High Disc","OK") -> OK
A25: O00024 | B25: 45893.911 | C25: Plant 1 Canteen | D25: Worker | E25: UPI | F25: Dinner | G25: 0.11 | H25: =INT($B25) -> 45893 | I25: =IF(COUNTIFS([0]!OrderID,Table3[[#This Row],[OrderID]],[0]!Category,"beverage")>0,"yes","no") -> no | J25: =SUMIFS([0]!LineNetAmount,[0]!OrderID,Table3[[#This Row],[OrderID]]) -> 390.888 | K25: {=_xlfn.TEXTJOIN("+",,_xlfn._xlws.SORT(_xlfn.UNIQUE(_xlfn._xlws.FILTER([0]!Category,[0]!OrderID=Table3[[#This Row],[OrderID]]))))} -> Hot Meal | L25: =SUMIFS([0]!FoodCost,[0]!OrderID,Table3[[#This Row],[OrderID]]) -> 242.76 | M25: =Table3[[#This Row],[LineAmount]]-Table3[[#This Row],[TotalCost]] -> 148.128 | N25: =IF(AND(COUNTIFS([0]!OrderID,Table3[[#This Row],[OrderID]],[0]!Category,"hot meal")>0,COUNTIFS([0]!OrderID,Table3[[#This Row],[OrderID]],[0]!Category,"beverage")>0),"combo","single") -> single | O25: =IF((Table3[[#This Row],[LineAmount]]/(1-Table3[[#This Row],[DiscountPct]]))*Table3[[#This Row],[DiscountPct]]>40,"High Disc","OK") -> High Disc
A26: O00025 | B26: 45888.367 | C26: Plant 2 Canteen | D26: Worker | E26: Card | F26: Breakfast | G26: 0.06 | H26: =INT($B26) -> 45888 | I26: =IF(COUNTIFS([0]!OrderID,Table3[[#This Row],[OrderID]],[0]!Category,"beverage")>0,"yes","no") -> no | J26: =SUMIFS([0]!LineNetAmount,[0]!OrderID,Table3[[#This Row],[OrderID]]) -> 47.1786 | K26: {=_xlfn.TEXTJOIN("+",,_xlfn._xlws.SORT(_xlfn.UNIQUE(_xlfn._xlws.FILTER([0]!Category,[0]!OrderID=Table3[[#This Row],[OrderID]]))))} -> Snack | L26: =SUMIFS([0]!FoodCost,[0]!OrderID,Table3[[#This Row],[OrderID]]) -> 22.61 | M26: =Table3[[#This Row],[LineAmount]]-Table3[[#This Row],[TotalCost]] -> 24.5686 | N26: =IF(AND(COUNTIFS([0]!OrderID,Table3[[#This Row],[OrderID]],[0]!Category,"hot meal")>0,COUNTIFS([0]!OrderID,Table3[[#This Row],[OrderID]],[0]!Category,"beverage")>0),"combo","single") -> single | O26: =IF((Table3[[#This Row],[LineAmount]]/(1-Table3[[#This Row],[DiscountPct]]))*Table3[[#This Row],[DiscountPct]]>40,"High Disc","OK") -> OK
A27: O00026 | B27: 45862.968 | C27: Plant 2 Canteen | D27: Staff | E27: Cash | F27: Dinner | G27: 0.1 | H27: =INT($B27) -> 45862 | I27: =IF(COUNTIFS([0]!OrderID,Table3[[#This Row],[OrderID]],[0]!Category,"beverage")>0,"yes","no") -> no | J27: =SUMIFS([0]!LineNetAmount,[0]!OrderID,Table3[[#This Row],[OrderID]]) -> 81.459 | K27: {=_xlfn.TEXTJOIN("+",,_xlfn._xlws.SORT(_xlfn.UNIQUE(_xlfn._xlws.FILTER([0]!Category,[0]!OrderID=Table3[[#This Row],[OrderID]]))))} -> Snack | L27: =SUMIFS([0]!FoodCost,[0]!OrderID,Table3[[#This Row],[OrderID]]) -> 45.35 | M27: =Table3[[#This Row],[LineAmount]]-Table3[[#This Row],[TotalCost]] -> 36.109 | N27: =IF(AND(COUNTIFS([0]!OrderID,Table3[[#This Row],[OrderID]],[0]!Category,"hot meal")>0,COUNTIFS([0]!OrderID,Table3[[#This Row],[OrderID]],[0]!Category,"beverage")>0),"combo","single") -> single | O27: =IF((Table3[[#This Row],[LineAmount]]/(1-Table3[[#This Row],[DiscountPct]]))*Table3[[#This Row],[DiscountPct]]>40,"High Disc","OK") -> OK
A28: O00027 | B28: 45891.991 | C28: Head Office Café | D28: Staff | E28: UPI | F28: Dinner | G28: 0.07 | H28: =INT($B28) -> 45891 | I28: =IF(COUNTIFS([0]!OrderID,Table3[[#This Row],[OrderID]],[0]!Category,"beverage")>0,"yes","no") -> yes | J28: =SUMIFS([0]!LineNetAmount,[0]!OrderID,Table3[[#This Row],[OrderID]]) -> 839.8458 | K28: {=_xlfn.TEXTJOIN("+",,_xlfn._xlws.SORT(_xlfn.UNIQUE(_xlfn._xlws.FILTER([0]!Category,[0]!OrderID=Table3[[#This Row],[OrderID]]))))} -> Beverage+Dessert+Hot Meal | L28: =SUMIFS([0]!FoodCost,[0]!OrderID,Table3[[#This Row],[OrderID]]) -> 406.75 | M28: =Table3[[#This Row],[LineAmount]]-Table3[[#This Row],[TotalCost]] -> 433.0958 | N28: =IF(AND(COUNTIFS([0]!OrderID,Table3[[#This Row],[OrderID]],[0]!Category,"hot meal")>0,COUNTIFS([0]!OrderID,Table3[[#This Row],[OrderID]],[0]!Category,"beverage")>0),"combo","single") -> combo | O28: =IF((Table3[[#This Row],[LineAmount]]/(1-Table3[[#This Row],[DiscountPct]]))*Table3[[#This Row],[DiscountPct]]>40,"High Disc","OK") -> High Disc
A29: O00028 | B29: 45840.01 | C29: Head Office Café | D29: Visitor | E29: Card | F29: Breakfast | G29: 0.03 | H29: =INT($B29) -> 45840 | I29: =IF(COUNTIFS([0]!OrderID,Table3[[#This Row],[OrderID]],[0]!Category,"beverage")>0,"yes","no") -> yes | J29: =SUMIFS([0]!LineNetAmount,[0]!OrderID,Table3[[#This Row],[OrderID]]) -> 382.7135 | K29: {=_xlfn.TEXTJOIN("+",,_xlfn._xlws.SORT(_xlfn.UNIQUE(_xlfn._xlws.FILTER([0]!Category,[0]!OrderID=Table3[[#This Row],[OrderID]]))))} -> Beverage+Dessert+Snack | L29: =SUMIFS([0]!FoodCost,[0]!OrderID,Table3[[#This Row],[OrderID]]) -> 172.36 | M29: =Table3[[#This Row],[LineAmount]]-Table3[[#This Row],[TotalCost]] -> 210.3535 | N29: =IF(AND(COUNTIFS([0]!OrderID,Table3[[#This Row],[OrderID]],[0]!Category,"hot meal")>0,COUNTIFS([0]!OrderID,Table3[[#This Row],[OrderID]],[0]!Category,"beverage")>0),"combo","single") -> single | O29: =IF((Table3[[#This Row],[LineAmount]]/(1-Table3[[#This Row],[DiscountPct]]))*Table3[[#This Row],[DiscountPct]]>40,"High Disc","OK") -> OK
A30: O00029 | B30: 45852.288 | C30: Plant 2 Canteen | D30: Worker | E30: Cash | F30: Breakfast | G30: 0.07 | H30: =INT($B30) -> 45852 | I30: =IF(COUNTIFS([0]!OrderID,Table3[[#This Row],[OrderID]],[0]!Category,"beverage")>0,"yes","no") -> no | J30: =SUMIFS([0]!LineNetAmount,[0]!OrderID,Table3[[#This Row],[OrderID]]) -> 140.0301 | K30: {=_xlfn.TEXTJOIN("+",,_xlfn._xlws.SORT(_xlfn.UNIQUE(_xlfn._xlws.FILTER([0]!Category,[0]!OrderID=Table3[[#This Row],[OrderID]]))))} -> Snack | L30: =SUMIFS([0]!FoodCost,[0]!OrderID,Table3[[#This Row],[OrderID]]) -> 67.83 | M30: =Table3[[#This Row],[LineAmount]]-Table3[[#This Row],[TotalCost]] -> 72.2001 | N30: =IF(AND(COUNTIFS([0]!OrderID,Table3[[#This Row],[OrderID]],[0]!Category,"hot meal")>0,COUNTIFS([0]!OrderID,Table3[[#This Row],[OrderID]],[0]!Category,"beverage")>0),"combo","single") -> single | O30: =IF((Table3[[#This Row],[LineAmount]]/(1-Table3[[#This Row],[DiscountPct]]))*Table3[[#This Row],[DiscountPct]]>40,"High Disc","OK") -> OK
A31: O00030 | B31: 45854.342 | C31: Plant 2 Canteen | D31: Staff | E31: UPI | F31: Breakfast | G31: 0.12 | H31: =INT($B31) -> 45854 | I31: =IF(COUNTIFS([0]!OrderID,Table3[[#This Row],[OrderID]],[0]!Category,"beverage")>0,"yes","no") -> yes | J31: =SUMIFS([0]!LineNetAmount,[0]!OrderID,Table3[[#This Row],[OrderID]]) -> 365.728 | K31: {=_xlfn.TEXTJOIN("+",,_xlfn._xlws.SORT(_xlfn.UNIQUE(_xlfn._xlws.FILTER([0]!Category,[0]!OrderID=Table3[[#This Row],[OrderID]]))))} -> Beverage+Hot Meal+Snack | L31: =SUMIFS([0]!FoodCost,[0]!OrderID,Table3[[#This Row],[OrderID]]) -> 197.59 | M31: =Table3[[#This Row],[LineAmount]]-Table3[[#This Row],[TotalCost]] -> 168.138 | N31: =IF(AND(COUNTIFS([0]!OrderID,Table3[[#This Row],[OrderID]],[0]!Category,"hot meal")>0,COUNTIFS([0]!OrderID,Table3[[#This Row],[OrderID]],[0]!Category,"beverage")>0),"combo","single") -> combo | O31: =IF((Table3[[#This Row],[LineAmount]]/(1-Table3[[#This Row],[DiscountPct]]))*Table3[[#This Row],[DiscountPct]]>40,"High Disc","OK") -> High Disc
A32: O00031 | B32: 45872.54 | C32: Plant 1 Canteen | D32: Visitor | E32: UPI | F32: Lunch | G32: 0.06 | H32: =INT($B32) -> 45872 | I32: =IF(COUNTIFS([0]!OrderID,Table3[[#This Row],[OrderID]],[0]!Category,"beverage")>0,"yes","no") -> no | J32: =SUMIFS([0]!LineNetAmount,[0]!OrderID,Table3[[#This Row],[OrderID]]) -> 435.972 | K32: {=_xlfn.TEXTJOIN("+",,_xlfn._xlws.SORT(_xlfn.UNIQUE(_xlfn._xlws.FILTER([0]!Category,[0]!OrderID=Table3[[#This Row],[OrderID]]))))} -> Dessert+Hot Meal | L32: =SUMIFS([0]!FoodCost,[0]!OrderID,Table3[[#This Row],[OrderID]]) -> 232.76 | M32: =Table3[[#This Row],[LineAmount]]-Table3[[#This Row],[TotalCost]] -> 203.212 | N32: =IF(AND(COUNTIFS([0]!OrderID,Table3[[#This Row],[OrderID]],[0]!Category,"hot meal")>0,COUNTIFS([0]!OrderID,Table3[[#This Row],[OrderID]],[0]!Category,"beverage")>0),"combo","single") -> single | O32: =IF((Table3[[#This Row],[LineAmount]]/(1-Table3[[#This Row],[DiscountPct]]))*Table3[[#This Row],[DiscountPct]]>40,"High Disc","OK") -> OK
A33: O00032 | B33: 45888.32 | C33: Plant 2 Canteen | D33: Staff | E33: Cash | F33: Breakfast | G33: 0.12 | H33: =INT($B33) -> 45888 | I33: =IF(COUNTIFS([0]!OrderID,Table3[[#This Row],[OrderID]],[0]!Category,"beverage")>0,"yes","no") -> yes | J33: =SUMIFS([0]!LineNetAmount,[0]!OrderID,Table3[[#This Row],[OrderID]]) -> 466.1888 | K33: {=_xlfn.TEXTJOIN("+",,_xlfn._xlws.SORT(_xlfn.UNIQUE(_xlfn._xlws.FILTER([0]!Category,[0]!OrderID=Table3[[#This Row],[OrderID]]))))} -> Beverage+Dessert+Hot Meal | L33: =SUMIFS([0]!FoodCost,[0]!OrderID,Table3[[#This Row],[OrderID]]) -> 256.44 | M33: =Table3[[#This Row],[LineAmount]]-Table3[[#This Row],[TotalCost]] -> 209.7488 | N33: =IF(AND(COUNTIFS([0]!OrderID,Table3[[#This Row],[OrderID]],[0]!Category,"hot meal")>0,COUNTIFS([0]!OrderID,Table3[[#This Row],[OrderID]],[0]!Category,"beverage")>0),"combo","single") -> combo | O33: =IF((Table3[[#This Row],[LineAmount]]/(1-Table3[[#This Row],[DiscountPct]]))*Table3[[#This Row],[DiscountPct]]>40,"High Disc","OK") -> High Disc
A34: O00033 | B34: 45880.375 | C34: Plant 2 Canteen | D34: Worker | E34: Cash | F34: Breakfast | G34: 0 | H34: =INT($B34) -> 45880 | I34: =IF(COUNTIFS([0]!OrderID,Table3[[#This Row],[OrderID]],[0]!Category,"beverage")>0,"yes","no") -> no | J34: =SUMIFS([0]!LineNetAmount,[0]!OrderID,Table3[[#This Row],[OrderID]]) -> 390.35 | K34: {=_xlfn.TEXTJOIN("+",,_xlfn._xlws.SORT(_xlfn.UNIQUE(_xlfn._xlws.FILTER([0]!Category,[0]!OrderID=Table3[[#This Row],[OrderID]]))))} -> Dessert+Snack | L34: =SUMIFS([0]!FoodCost,[0]!OrderID,Table3[[#This Row],[OrderID]]) -> 162.42 | M34: =Table3[[#This Row],[LineAmount]]-Table3[[#This Row],[TotalCost]] -> 227.93 | N34: =IF(AND(COUNTIFS([0]!OrderID,Table3[[#This Row],[OrderID]],[0]!Category,"hot meal")>0,COUNTIFS([0]!OrderID,Table3[[#This Row],[OrderID]],[0]!Category,"beverage")>0),"combo","single") -> single | O34: =IF((Table3[[#This Row],[LineAmount]]/(1-Table3[[#This Row],[DiscountPct]]))*Table3[[#This Row],[DiscountPct]]>40,"High Disc","OK") -> OK
... A361: O00360 | B361: 45878.689 | C361: Plant 2 Canteen | D361: Visitor | E361: UPI | F361: Dinner | G361: 0.04 | H361: =INT($B361) -> 45878 | I361: =IF(COUNTIFS([0]!OrderID,Table3[[#This Row],[OrderID]],[0]!Category,"beverage")>0,"yes","no") -> yes | J361: =SUMIFS([0]!LineNetAmount,[0]!OrderID,Table3[[#This Row],[OrderID]]) -> 962.1504 | K361: {=_xlfn.TEXTJOIN("+",,_xlfn._xlws.SORT(_xlfn.UNIQUE(_xlfn._xlws.FILTER([0]!Category,[0]!OrderID=Table3[[#This Row],[OrderID]]))))} -> Beverage+Hot Meal | L361: =SUMIFS([0]!FoodCost,[0]!OrderID,Table3[[#This Row],[OrderID]]) -> 466.15 | M361: =Table3[[#This Row],[LineAmount]]-Table3[[#This Row],[TotalCost]] -> 496.0004 | N361: =IF(AND(COUNTIFS([0]!OrderID,Table3[[#This Row],[OrderID]],[0]!Category,"hot meal")>0,COUNTIFS([0]!OrderID,Table3[[#This Row],[OrderID]],[0]!Category,"beverage")>0),"combo","single") -> combo | O361: =IF((Table3[[#This Row],[LineAmount]]/(1-Table3[[#This Row],[DiscountPct]]))*Table3[[#This Row],[DiscountPct]]>40,"High Disc","OK") -> High Disc

Sheet DAY 4 solution
D1: Q 2 | F1: SKU | G1: Revenue | H1: qty | L1: Q 3 | N1: Branch | O1: Total Revenue | P1: total cost | Q1: GM%
F2: HXAJI0 | G2: =SUMIFS(LineNetAmount,SKU,$F2,MonthName,"august") -> 10470.06 | H2: =SUMIFS(Qty,SKU,$F2,MonthName,"august") -> 49 | N2: Head Office Café | O2: =SUMIFS([0]!LineNetAmount,Branch,'DAY 4 solution'!$N2) -> 48982.147 | P2: {=SUMPRODUCT(([0]!Branch='DAY 4 solution'!$N2)*[0]!Qty*UnitCost)} -> 24001.28 | Q2: =(($O2-$P2)/$O2)*100 -> 50.999942
F3: HDPBHS | G3: =SUMIFS(LineNetAmount,SKU,$F3,MonthName,"august") -> 9230.7763 | H3: =SUMIFS(Qty,SKU,$F3,MonthName,"august") -> 38 | N3: Plant 2 Canteen | O3: =SUMIFS([0]!LineNetAmount,Branch,'DAY 4 solution'!$N3) -> 50416.193 | P3: {=SUMPRODUCT(([0]!Branch='DAY 4 solution'!$N3)*[0]!Qty*UnitCost)} -> 24427.5 | Q3: =(($O3-$P3)/$O3)*100 -> 51.548305
F4: HH1DNM | G4: =SUMIFS(LineNetAmount,SKU,$F4,MonthName,"august") -> 8283.3894 | H4: =SUMIFS(Qty,SKU,$F4,MonthName,"august") -> 36 | N4: Plant 1 Canteen | O4: =SUMIFS([0]!LineNetAmount,Branch,'DAY 4 solution'!$N4) -> 33249.291 | P4: {=SUMPRODUCT(([0]!Branch='DAY 4 solution'!$N4)*[0]!Qty*UnitCost)} -> 16720.52 | Q4: =(($O4-$P4)/$O4)*100 -> 49.71165
F5: HUZZPQ | G5: =SUMIFS(LineNetAmount,SKU,$F5,MonthName,"august") -> 6563.112 | H5: =SUMIFS(Qty,SKU,$F5,MonthName,"august") -> 48
F6: H3A3ZM | G6: =SUMIFS(LineNetAmount,SKU,$F6,MonthName,"august") -> 5927.801 | H6: =SUMIFS(Qty,SKU,$F6,MonthName,"august") -> 37
F7: D9T84A | G7: =SUMIFS(LineNetAmount,SKU,$F7,MonthName,"august") -> 4925.456 | H7: =SUMIFS(Qty,SKU,$F7,MonthName,"august") -> 45
F8: DH9SDB | G8: =SUMIFS(LineNetAmount,SKU,$F8,MonthName,"august") -> 3714.9715 | H8: =SUMIFS(Qty,SKU,$F8,MonthName,"august") -> 52
F9: SCKW5N | G9: =SUMIFS(LineNetAmount,SKU,$F9,MonthName,"august") -> 2910.4804 | H9: =SUMIFS(Qty,SKU,$F9,MonthName,"august") -> 44
F10: DFFYVN | G10: =SUMIFS(LineNetAmount,SKU,$F10,MonthName,"august") -> 2362.578 | H10: =SUMIFS(Qty,SKU,$F10,MonthName,"august") -> 46
F11: S5NQ4F | G11: =SUMIFS(LineNetAmount,SKU,$F11,MonthName,"august") -> 2318.778 | H11: =SUMIFS(Qty,SKU,$F11,MonthName,"august") -> 49
F12: DYTJXE | G12: =SUMIFS(LineNetAmount,SKU,$F12,MonthName,"august") -> 2202.3313 | H12: =SUMIFS([0]!Qty,SKU,'DAY 4 solution'!$F13,MonthName,"august") -> 32
F13: SHJ7XV | G13: =SUMIFS(LineNetAmount,SKU,$F13,MonthName,"august") -> 1563.5345 | H13: =SUMIFS([0]!Qty,SKU,'DAY 4 solution'!$F2,MonthName,"august") -> 49
F14: BTIQJ7 | G14: =SUMIFS(LineNetAmount,SKU,$F14,MonthName,"august") -> 1508.5048 | H14: =SUMIFS([0]!Qty,SKU,'DAY 4 solution'!$F3,MonthName,"august") -> 38
F15: SV30T9 | G15: =SUMIFS(LineNetAmount,SKU,$F15,MonthName,"august") -> 1484.1425 | H15: =SUMIFS([0]!Qty,SKU,'DAY 4 solution'!$F19,MonthName,"august") -> 45
F16: BOC6UZ | G16: =SUMIFS(LineNetAmount,SKU,$F16,MonthName,"august") -> 1432.6512 | H16: =SUMIFS([0]!Qty,SKU,'DAY 4 solution'!$F5,MonthName,"august") -> 48
F17: SZBIKC | G17: =SUMIFS(LineNetAmount,SKU,$F17,MonthName,"august") -> 1155.5016 | H17: =SUMIFS([0]!Qty,SKU,'DAY 4 solution'!$F7,MonthName,"august") -> 45
F18: B0T0PV | G18: =SUMIFS(LineNetAmount,SKU,$F18,MonthName,"august") -> 1151.6993 | H18: =SUMIFS([0]!Qty,SKU,'DAY 4 solution'!$F10,MonthName,"august") -> 46
F19: BXO6QJ | G19: =SUMIFS(LineNetAmount,SKU,$F19,MonthName,"august") -> 854.8761 | H19: =SUMIFS([0]!Qty,SKU,'DAY 4 solution'!$F11,MonthName,"august") -> 49
F20: BHL1C3 | G20: =SUMIFS(LineNetAmount,SKU,$F20,MonthName,"august") -> 647.796 | H20: =SUMIFS([0]!Qty,SKU,'DAY 4 solution'!$F12,MonthName,"august") -> 41
A23: Q 1
A24: MonthName | B24: (All)
A26: Row Labels | B26: Total Revenue | C26: % contribution
A27: Beverage | B27: 10321.758 | C27: 0.077813364
A28: Head Office Café | B28: 3489.8727 | C28: 0.33810835
A29: Plant 1 Canteen | B29: 2895.3357 | C29: 0.28050799
A30: Plant 2 Canteen | B30: 3936.5499 | C30: 0.38138365
A31: Dessert | B31: 24556.193 | C31: 0.18512349
A32: Head Office Café | B32: 9544.0172 | C32: 0.3886603
A33: Plant 1 Canteen | B33: 6497.6642 | C33: 0.26460389
A34: Plant 2 Canteen | B34: 8514.5112 | C34: 0.3467358
A35: Hot Meal | B35: 79136.671 | C35: 0.59659317
A36: Head Office Café | B36: 30604.808 | C36: 0.38673358
A37: Plant 1 Canteen | B37: 17407.726 | C37: 0.21997041
A38: Plant 2 Canteen | B38: 31124.138 | C38: 0.39329602
... A43: Grand Total | B43: 132647.63 | C43: 1

Sheet DAY 5 solution
A1: Date | B1: Revenue | C1: Avg Feedback Rating | D1: Avg Waste Cost | E1: Waste Cost
A2: {=_xlfn._xlws.SORT(_xlfn.UNIQUE([0]!OrderDate))} -> 45839 | B2: =SUMIFS([0]!LineNetAmount,OrderDate,'DAY 5 solution'!$A2) -> 198.822 | C2: =IFERROR(AVERAGEIFS([0]!Rating,Feedback!Date,'DAY 5 solution'!$A2),0) -> 3.8571429 | E2: {=SUMPRODUCT(([0]!Date='DAY 5 solution'!$A2)*WasteLog!Qty*WasteLog!$E$2:$E$121)} -> 0
A3: 45840 | B3: =SUMIFS([0]!LineNetAmount,OrderDate,'DAY 5 solution'!$A3) -> 3202.85 | C3: =IFERROR(AVERAGEIFS([0]!Rating,Feedback!Date,'DAY 5 solution'!$A3),0) -> 3.6 | E3: {=SUMPRODUCT(([0]!Date='DAY 5 solution'!$A3)*WasteLog!Qty*WasteLog!$E$2:$E$121)} -> 369.92
A4: 45841 | B4: =SUMIFS([0]!LineNetAmount,OrderDate,'DAY 5 solution'!$A4) -> 1027.7541 | C4: =IFERROR(AVERAGEIFS([0]!Rating,Feedback!Date,'DAY 5 solution'!$A4),0) -> 4 | E4: {=SUMPRODUCT(([0]!Date='DAY 5 solution'!$A4)*WasteLog!Qty*WasteLog!$E$2:$E$121)} -> 0
A5: 45842 | B5: =SUMIFS([0]!LineNetAmount,OrderDate,'DAY 5 solution'!$A5) -> 1622.0684 | C5: =IFERROR(AVERAGEIFS([0]!Rating,Feedback!Date,'DAY 5 solution'!$A5),0) -> 4.5 | E5: {=SUMPRODUCT(([0]!Date='DAY 5 solution'!$A5)*WasteLog!Qty*WasteLog!$E$2:$E$121)} -> 80.92
A6: 45843 | B6: =SUMIFS([0]!LineNetAmount,OrderDate,'DAY 5 solution'!$A6) -> 626.2479 | C6: =IFERROR(AVERAGEIFS([0]!Rating,Feedback!Date,'DAY 5 solution'!$A6),0) -> 4 | E6: {=SUMPRODUCT(([0]!Date='DAY 5 solution'!$A6)*WasteLog!Qty*WasteLog!$E$2:$E$121)} -> 253.64
A7: 45844 | B7: =SUMIFS([0]!LineNetAmount,OrderDate,'DAY 5 solution'!$A7) -> 2758.1276 | C7: =IFERROR(AVERAGEIFS([0]!Rating,Feedback!Date,'DAY 5 solution'!$A7),0) -> 3.5 | E7: {=SUMPRODUCT(([0]!Date='DAY 5 solution'!$A7)*WasteLog!Qty*WasteLog!$E$2:$E$121)} -> 543.5
A8: 45845 | B8: =SUMIFS([0]!LineNetAmount,OrderDate,'DAY 5 solution'!$A8) -> 1619.6286 | C8: =IFERROR(AVERAGEIFS([0]!Rating,Feedback!Date,'DAY 5 solution'!$A8),0) -> 4.75 | E8: {=SUMPRODUCT(([0]!Date='DAY 5 solution'!$A8)*WasteLog!Qty*WasteLog!$E$2:$E$121)} -> 74.07
A9: 45846 | B9: =SUMIFS([0]!LineNetAmount,OrderDate,'DAY 5 solution'!$A9) -> 425.1991 | C9: =IFERROR(AVERAGEIFS([0]!Rating,Feedback!Date,'DAY 5 solution'!$A9),0) -> 4 | E9: {=SUMPRODUCT(([0]!Date='DAY 5 solution'!$A9)*WasteLog!Qty*WasteLog!$E$2:$E$121)} -> 141.28
A10: 45847 | B10: =SUMIFS([0]!LineNetAmount,OrderDate,'DAY 5 solution'!$A10) -> 2706.5737 | C10: =IFERROR(AVERAGEIFS([0]!Rating,Feedback!Date,'DAY 5 solution'!$A10),0) -> 3.1666667 | E10: {=SUMPRODUCT(([0]!Date='DAY 5 solution'!$A10)*WasteLog!Qty*WasteLog!$E$2:$E$121)} -> 111.78
A11: 45848 | B11: =SUMIFS([0]!LineNetAmount,OrderDate,'DAY 5 solution'!$A11) -> 3654.4446 | C11: =IFERROR(AVERAGEIFS([0]!Rating,Feedback!Date,'DAY 5 solution'!$A11),0) -> 4 | E11: {=SUMPRODUCT(([0]!Date='DAY 5 solution'!$A11)*WasteLog!Qty*WasteLog!$E$2:$E$121)} -> 8
A12: 45849 | B12: =SUMIFS([0]!LineNetAmount,OrderDate,'DAY 5 solution'!$A12) -> 3744.4975 | C12: =IFERROR(AVERAGEIFS([0]!Rating,Feedback!Date,'DAY 5 solution'!$A12),0) -> 3.5 | E12: {=SUMPRODUCT(([0]!Date='DAY 5 solution'!$A12)*WasteLog!Qty*WasteLog!$E$2:$E$121)} -> 390.62
A13: 45850 | B13: =SUMIFS([0]!LineNetAmount,OrderDate,'DAY 5 solution'!$A13) -> 3559.4395 | C13: =IFERROR(AVERAGEIFS([0]!Rating,Feedback!Date,'DAY 5 solution'!$A13),0) -> 4 | E13: {=SUMPRODUCT(([0]!Date='DAY 5 solution'!$A13)*WasteLog!Qty*WasteLog!$E$2:$E$121)} -> 143.24
A14: 45851 | B14: =SUMIFS([0]!LineNetAmount,OrderDate,'DAY 5 solution'!$A14) -> 2567.5368 | C14: =IFERROR(AVERAGEIFS([0]!Rating,Feedback!Date,'DAY 5 solution'!$A14),0) -> 3.8 | E14: {=SUMPRODUCT(([0]!Date='DAY 5 solution'!$A14)*WasteLog!Qty*WasteLog!$E$2:$E$121)} -> 0
... A61: 45898 | B61: =SUMIFS([0]!LineNetAmount,OrderDate,'DAY 5 solution'!$A61) -> 1445.0394 | C61: =IFERROR(AVERAGEIFS([0]!Rating,Feedback!Date,'DAY 5 solution'!$A61),0) -> 0 | E61: {=SUMPRODUCT(([0]!Date='DAY 5 solution'!$A61)*WasteLog!Qty*WasteLog!$E$2:$E$121)} -> 0

Sheet DAY 6 solution
B1: SKU | C1: SELECT ANY | D1: VALUE | J1: {=_xlfn.UNIQUE([0]!SKU)} -> SHJ7XV
B2: DH9SDB | C2: UNITcost | D2: =INDEX(orderlinesTABLE[],MATCH(B2,[0]!SKU,0),MATCH('DAY 6 solution'!C2,orderlinesTABLE[#Headers],0)) -> 38.23 | J2: BTIQJ7
J3: DH9SDB
J4: BOC6UZ
J5: H3A3ZM
J6: SZBIKC
J7: HH1DNM
J8: SCKW5N
J9: B0T0PV
J10: BXO6QJ
J11: BHL1C3
J12: DYTJXE
J13: DFFYVN
J14: D9T84A
... J19: S5NQ4F

Sheet OrderLines
A1: OrderID | B1: SKU | C1: Qty | D1: UnitPrice | E1: Category | F1: UnitCost | G1: OrderDate | H1: Branch | I1: DiscountPct | J1: LineNetAmount | K1: MonthName | L1: Shift | M1: PaymentType | N1: ComboFlag | O1: DiscountFlag | P1: totalCOST | Q1: Profit | R1: ItemName | S1: Combination | T1: GM% | U1: FoodCost | W1: DAY 2 SOLUTIONS
A2: O00001 | B2: SHJ7XV | C2: 3 | D2: =VLOOKUP($B2,Menu!$A$1:$F$20,MATCH($D$1,Menu!$A$1:$F$1,0),0) -> 52.45 | E2: =VLOOKUP($B2,Menu!$A$1:$F$20,MATCH(OrderLines!E$1,Menu!$A$1:$F$1,0),0) -> Snack | F2: =VLOOKUP($B2,Menu!$A$1:$F$20,MATCH(OrderLines!F$1,Menu!$A$1:$F$1,0),0) -> 25.8 | G2: =VLOOKUP($A2,Orders!$A$1:$H$361,MATCH($G$1,Orders!$A$1:$H$1,0),0) -> 45852 | H2: =VLOOKUP($A2,Orders!$A$1:$H$361,MATCH(OrderLines!$H$1,Orders!$A$1:$H$1,0),0) -> Head Office Café | I2: =VLOOKUP($A2,Orders!$A$1:$H$361,MATCH(OrderLines!$I$1,Orders!$A$1:$H$1,0),0) -> 0.06 | J2: =$C2*$D2*(1-$I2) -> 147.909 | K2: =TEXT($G2,"mmmm") -> July | L2: =VLOOKUP(OrderLines!$A2,Orders!$A$1:$H$361,MATCH(OrderLines!$L$1,Orders!$A$1:$H$1,0),0) -> Breakfast | M2: =VLOOKUP($A2,Orders!$A$1:$H$361,MATCH(OrderLines!$M$1,Orders!$A$1:$H$1,0),0) -> UPI | N2: =IF(AND(COUNTIFS(OrderID,$A2,Category,"hot meal")>=1,COUNTIFS(OrderID,$A2,Category,"beverage")>=1),"Combo","Single") -> Single | O2: {=IF((SUMPRODUCT((OrderID=OrderLines!$A2)*Qty*UnitPrice*DiscountPct))>40,"HighDisc","OK")} -> OK | P2: =(orderlinesTABLE[[#This Row],[UnitCost]]*orderlinesTABLE[[#This Row],[Qty]]) -> 77.4 | Q2: =(orderlinesTABLE[[#This Row],[LineNetAmount]]-orderlinesTABLE[[#This Row],[totalCOST]]) -> 70.509 | R2: =VLOOKUP($B2,Menu!$A$1:$F$20,MATCH(OrderLines!R$1,Menu!$A$1:$F$1,0),0) -> Poha | S2: {=_xlfn.TEXTJOIN("+",TRUE,_xlfn._xlws.FILTER(orderlinesTABLE[ItemName],OrderID=orderlinesTABLE[[#This Row],[OrderID]]))} -> Poha | T2: =orderlinesTABLE[[#This Row],[Profit]]/orderlinesTABLE[[#This Row],[LineNetAmount]] -> 0.47670527 | U2: =(orderlinesTABLE[[#This Row],[Qty]]*orderlinesTABLE[[#This Row],[UnitCost]]) -> 77.4
A3: O00002 | B3: BTIQJ7 | C3: 1 | D3: =VLOOKUP($B3,Menu!$A$1:$F$20,MATCH($D$1,Menu!$A$1:$F$1,0),0) -> 30.34 | E3: =VLOOKUP($B3,Menu!$A$1:$F$20,MATCH(OrderLines!E$1,Menu!$A$1:$F$1,0),0) -> Beverage | F3: =VLOOKUP($B3,Menu!$A$1:$F$20,MATCH(OrderLines!F$1,Menu!$A$1:$F$1,0),0) -> 14.18 | G3: =VLOOKUP($A3,Orders!$A$1:$H$361,MATCH($G$1,Orders!$A$1:$H$1,0),0) -> 45862 | H3: =VLOOKUP($A3,Orders!$A$1:$H$361,MATCH(OrderLines!$H$1,Orders!$A$1:$H$1,0),0) -> Plant 2 Canteen | I3: =VLOOKUP($A3,Orders!$A$1:$H$361,MATCH(OrderLines!$I$1,Orders!$A$1:$H$1,0),0) -> 0.05 | J3: =$C3*$D3*(1-$I3) -> 28.823 | K3: =TEXT($G3,"mmmm") -> July | L3: =VLOOKUP(OrderLines!$A3,Orders!$A$1:$H$361,MATCH(OrderLines!$L$1,Orders!$A$1:$H$1,0),0) -> Dinner | M3: =VLOOKUP($A3,Orders!$A$1:$H$361,MATCH(OrderLines!$M$1,Orders!$A$1:$H$1,0),0) -> Cash | N3: =IF(AND(COUNTIFS(OrderID,$A3,Category,"hot meal")>=1,COUNTIFS(OrderID,$A3,Category,"beverage")>=1),"Combo","Single") -> Single | O3: {=IF((SUMPRODUCT((OrderID=OrderLines!$A3)*Qty*UnitPrice*DiscountPct))>40,"HighDisc","OK")} -> OK | P3: =(orderlinesTABLE[[#This Row],[UnitCost]]*orderlinesTABLE[[#This Row],[Qty]]) -> 14.18 | Q3: =(orderlinesTABLE[[#This Row],[LineNetAmount]]-orderlinesTABLE[[#This Row],[totalCOST]]) -> 14.643 | R3: =VLOOKUP($B3,Menu!$A$1:$F$20,MATCH(OrderLines!R$1,Menu!$A$1:$F$1,0),0) -> Tea | S3: {=_xlfn.TEXTJOIN("+",TRUE,_xlfn._xlws.FILTER(orderlinesTABLE[ItemName],OrderID=orderlinesTABLE[[#This Row],[OrderID]]))} -> Tea+Gulab Jamun (2 pc) | T3: =orderlinesTABLE[[#This Row],[Profit]]/orderlinesTABLE[[#This Row],[LineNetAmount]] -> 0.50803178 | U3: =(orderlinesTABLE[[#This Row],[Qty]]*orderlinesTABLE[[#This Row],[UnitCost]]) -> 14.18
A4: O00002 | B4: DH9SDB | C4: 1 | D4: =VLOOKUP($B4,Menu!$A$1:$F$20,MATCH($D$1,Menu!$A$1:$F$1,0),0) -> 76.55 | E4: =VLOOKUP($B4,Menu!$A$1:$F$20,MATCH(OrderLines!E$1,Menu!$A$1:$F$1,0),0) -> Dessert | F4: =VLOOKUP($B4,Menu!$A$1:$F$20,MATCH(OrderLines!F$1,Menu!$A$1:$F$1,0),0) -> 38.23 | G4: =VLOOKUP($A4,Orders!$A$1:$H$361,MATCH($G$1,Orders!$A$1:$H$1,0),0) -> 45862 | H4: =VLOOKUP($A4,Orders!$A$1:$H$361,MATCH(OrderLines!$H$1,Orders!$A$1:$H$1,0),0) -> Plant 2 Canteen | I4: =VLOOKUP($A4,Orders!$A$1:$H$361,MATCH(OrderLines!$I$1,Orders!$A$1:$H$1,0),0) -> 0.05 | J4: =$C4*$D4*(1-$I4) -> 72.7225 | K4: =TEXT($G4,"mmmm") -> July | L4: =VLOOKUP(OrderLines!$A4,Orders!$A$1:$H$361,MATCH(OrderLines!$L$1,Orders!$A$1:$H$1,0),0) -> Dinner | M4: =VLOOKUP($A4,Orders!$A$1:$H$361,MATCH(OrderLines!$M$1,Orders!$A$1:$H$1,0),0) -> Cash | N4: =IF(AND(COUNTIFS(OrderID,$A4,Category,"hot meal")>=1,COUNTIFS(OrderID,$A4,Category,"beverage")>=1),"Combo","Single") -> Single | O4: {=IF((SUMPRODUCT((OrderID=OrderLines!$A4)*Qty*UnitPrice*DiscountPct))>40,"HighDisc","OK")} -> OK | P4: =(orderlinesTABLE[[#This Row],[UnitCost]]*orderlinesTABLE[[#This Row],[Qty]]) -> 38.23 | Q4: =(orderlinesTABLE[[#This Row],[LineNetAmount]]-orderlinesTABLE[[#This Row],[totalCOST]]) -> 34.4925 | R4: =VLOOKUP($B4,Menu!$A$1:$F$20,MATCH(OrderLines!R$1,Menu!$A$1:$F$1,0),0) -> Gulab Jamun (2 pc) | S4: {=_xlfn.TEXTJOIN("+",TRUE,_xlfn._xlws.FILTER(orderlinesTABLE[ItemName],OrderID=orderlinesTABLE[[#This Row],[OrderID]]))} -> Tea+Gulab Jamun (2 pc) | T4: =orderlinesTABLE[[#This Row],[Profit]]/orderlinesTABLE[[#This Row],[LineNetAmount]] -> 0.474303 | U4: =(orderlinesTABLE[[#This Row],[Qty]]*orderlinesTABLE[[#This Row],[UnitCost]]) -> 38.23 | Y4: Sum of LineNetAmount
A5: O00003 | B5: BOC6UZ | C5: 2 | D5: =VLOOKUP($B5,Menu!$A$1:$F$20,MATCH($D$1,Menu!$A$1:$F$1,0),0) -> 32.98 | E5: =VLOOKUP($B5,Menu!$A$1:$F$20,MATCH(OrderLines!E$1,Menu!$A$1:$F$1,0),0) -> Beverage | F5: =VLOOKUP($B5,Menu!$A$1:$F$20,MATCH(OrderLines!F$1,Menu!$A$1:$F$1,0),0) -> 11.84 | G5: =VLOOKUP($A5,Orders!$A$1:$H$361,MATCH($G$1,Orders!$A$1:$H$1,0),0) -> 45848 | H5: =VLOOKUP($A5,Orders!$A$1:$H$361,MATCH(OrderLines!$H$1,Orders!$A$1:$H$1,0),0) -> Head Office Café | I5: =VLOOKUP($A5,Orders!$A$1:$H$361,MATCH(OrderLines!$I$1,Orders!$A$1:$H$1,0),0) -> 0 | J5: =$C5*$D5*(1-$I5) -> 65.96 | K5: =TEXT($G5,"mmmm") -> July | L5: =VLOOKUP(OrderLines!$A5,Orders!$A$1:$H$361,MATCH(OrderLines!$L$1,Orders!$A$1:$H$1,0),0) -> Lunch | M5: =VLOOKUP($A5,Orders!$A$1:$H$361,MATCH(OrderLines!$M$1,Orders!$A$1:$H$1,0),0) -> Card | N5: =IF(AND(COUNTIFS(OrderID,$A5,Category,"hot meal")>=1,COUNTIFS(OrderID,$A5,Category,"beverage")>=1),"Combo","Single") -> Combo | O5: {=IF((SUMPRODUCT((OrderID=OrderLines!$A5)*Qty*UnitPrice*DiscountPct))>40,"HighDisc","OK")} -> OK | P5: =(orderlinesTABLE[[#This Row],[UnitCost]]*orderlinesTABLE[[#This Row],[Qty]]) -> 23.68 | Q5: =(orderlinesTABLE[[#This Row],[LineNetAmount]]-orderlinesTABLE[[#This Row],[totalCOST]]) -> 42.28 | R5: =VLOOKUP($B5,Menu!$A$1:$F$20,MATCH(OrderLines!R$1,Menu!$A$1:$F$1,0),0) -> Masala Chaas | S5: {=_xlfn.TEXTJOIN("+",TRUE,_xlfn._xlws.FILTER(orderlinesTABLE[ItemName],OrderID=orderlinesTABLE[[#This Row],[OrderID]]))} -> Masala Chaas+Poha+Paneer Butter Masala + Naan+Paneer Roll | T5: =orderlinesTABLE[[#This Row],[Profit]]/orderlinesTABLE[[#This Row],[LineNetAmount]] -> 0.64099454 | U5: =(orderlinesTABLE[[#This Row],[Qty]]*orderlinesTABLE[[#This Row],[UnitCost]]) -> 23.68 | Y5: 132647.63
A6: O00003 | B6: SHJ7XV | C6: 1 | D6: =VLOOKUP($B6,Menu!$A$1:$F$20,MATCH($D$1,Menu!$A$1:$F$1,0),0) -> 52.45 | E6: =VLOOKUP($B6,Menu!$A$1:$F$20,MATCH(OrderLines!E$1,Menu!$A$1:$F$1,0),0) -> Snack | F6: =VLOOKUP($B6,Menu!$A$1:$F$20,MATCH(OrderLines!F$1,Menu!$A$1:$F$1,0),0) -> 25.8 | G6: =VLOOKUP($A6,Orders!$A$1:$H$361,MATCH($G$1,Orders!$A$1:$H$1,0),0) -> 45848 | H6: =VLOOKUP($A6,Orders!$A$1:$H$361,MATCH(OrderLines!$H$1,Orders!$A$1:$H$1,0),0) -> Head Office Café | I6: =VLOOKUP($A6,Orders!$A$1:$H$361,MATCH(OrderLines!$I$1,Orders!$A$1:$H$1,0),0) -> 0 | J6: =$C6*$D6*(1-$I6) -> 52.45 | K6: =TEXT($G6,"mmmm") -> July | L6: =VLOOKUP(OrderLines!$A6,Orders!$A$1:$H$361,MATCH(OrderLines!$L$1,Orders!$A$1:$H$1,0),0) -> Lunch | M6: =VLOOKUP($A6,Orders!$A$1:$H$361,MATCH(OrderLines!$M$1,Orders!$A$1:$H$1,0),0) -> Card | N6: =IF(AND(COUNTIFS(OrderID,$A6,Category,"hot meal")>=1,COUNTIFS(OrderID,$A6,Category,"beverage")>=1),"Combo","Single") -> Combo | O6: {=IF((SUMPRODUCT((OrderID=OrderLines!$A6)*Qty*UnitPrice*DiscountPct))>40,"HighDisc","OK")} -> OK | P6: =(orderlinesTABLE[[#This Row],[UnitCost]]*orderlinesTABLE[[#This Row],[Qty]]) -> 25.8 | Q6: =(orderlinesTABLE[[#This Row],[LineNetAmount]]-orderlinesTABLE[[#This Row],[totalCOST]]) -> 26.65 | R6: =VLOOKUP($B6,Menu!$A$1:$F$20,MATCH(OrderLines!R$1,Menu!$A$1:$F$1,0),0) -> Poha | S6: {=_xlfn.TEXTJOIN("+",TRUE,_xlfn._xlws.FILTER(orderlinesTABLE[ItemName],OrderID=orderlinesTABLE[[#This Row],[OrderID]]))} -> Masala Chaas+Poha+Paneer Butter Masala + Naan+Paneer Roll | T6: =orderlinesTABLE[[#This Row],[Profit]]/orderlinesTABLE[[#This Row],[LineNetAmount]] -> 0.50810296 | U6: =(orderlinesTABLE[[#This Row],[Qty]]*orderlinesTABLE[[#This Row],[UnitCost]]) -> 25.8
A7: O00003 | B7: H3A3ZM | C7: 3 | D7: =VLOOKUP($B7,Menu!$A$1:$F$20,MATCH($D$1,Menu!$A$1:$F$1,0),0) -> 170.83 | E7: =VLOOKUP($B7,Menu!$A$1:$F$20,MATCH(OrderLines!E$1,Menu!$A$1:$F$1,0),0) -> Hot Meal | F7: =VLOOKUP($B7,Menu!$A$1:$F$20,MATCH(OrderLines!F$1,Menu!$A$1:$F$1,0),0) -> 74.07 | G7: =VLOOKUP($A7,Orders!$A$1:$H$361,MATCH($G$1,Orders!$A$1:$H$1,0),0) -> 45848 | H7: =VLOOKUP($A7,Orders!$A$1:$H$361,MATCH(OrderLines!$H$1,Orders!$A$1:$H$1,0),0) -> Head Office Café | I7: =VLOOKUP($A7,Orders!$A$1:$H$361,MATCH(OrderLines!$I$1,Orders!$A$1:$H$1,0),0) -> 0 | J7: =$C7*$D7*(1-$I7) -> 512.49 | K7: =TEXT($G7,"mmmm") -> July | L7: =VLOOKUP(OrderLines!$A7,Orders!$A$1:$H$361,MATCH(OrderLines!$L$1,Orders!$A$1:$H$1,0),0) -> Lunch | M7: =VLOOKUP($A7,Orders!$A$1:$H$361,MATCH(OrderLines!$M$1,Orders!$A$1:$H$1,0),0) -> Card | N7: =IF(AND(COUNTIFS(OrderID,$A7,Category,"hot meal")>=1,COUNTIFS(OrderID,$A7,Category,"beverage")>=1),"Combo","Single") -> Combo | O7: {=IF((SUMPRODUCT((OrderID=OrderLines!$A7)*Qty*UnitPrice*DiscountPct))>40,"HighDisc","OK")} -> OK | P7: =(orderlinesTABLE[[#This Row],[UnitCost]]*orderlinesTABLE[[#This Row],[Qty]]) -> 222.21 | Q7: =(orderlinesTABLE[[#This Row],[LineNetAmount]]-orderlinesTABLE[[#This Row],[totalCOST]]) -> 290.28 | R7: =VLOOKUP($B7,Menu!$A$1:$F$20,MATCH(OrderLines!R$1,Menu!$A$1:$F$1,0),0) -> Paneer Butter Masala + Naan | S7: {=_xlfn.TEXTJOIN("+",TRUE,_xlfn._xlws.FILTER(orderlinesTABLE[ItemName],OrderID=orderlinesTABLE[[#This Row],[OrderID]]))} -> Masala Chaas+Poha+Paneer Butter Masala + Naan+Paneer Roll | T7: =orderlinesTABLE[[#This Row],[Profit]]/orderlinesTABLE[[#This Row],[LineNetAmount]] -> 0.56641105 | U7: =(orderlinesTABLE[[#This Row],[Qty]]*orderlinesTABLE[[#This Row],[UnitCost]]) -> 222.21
A8: O00003 | B8: SZBIKC | C8: 1 | D8: =VLOOKUP($B8,Menu!$A$1:$F$20,MATCH($D$1,Menu!$A$1:$F$1,0),0) -> 38.06 | E8: =VLOOKUP($B8,Menu!$A$1:$F$20,MATCH(OrderLines!E$1,Menu!$A$1:$F$1,0),0) -> Snack | F8: =VLOOKUP($B8,Menu!$A$1:$F$20,MATCH(OrderLines!F$1,Menu!$A$1:$F$1,0),0) -> 19.55 | G8: =VLOOKUP($A8,Orders!$A$1:$H$361,MATCH($G$1,Orders!$A$1:$H$1,0),0) -> 45848 | H8: =VLOOKUP($A8,Orders!$A$1:$H$361,MATCH(OrderLines!$H$1,Orders!$A$1:$H$1,0),0) -> Head Office Café | I8: =VLOOKUP($A8,Orders!$A$1:$H$361,MATCH(OrderLines!$I$1,Orders!$A$1:$H$1,0),0) -> 0 | J8: =$C8*$D8*(1-$I8) -> 38.06 | K8: =TEXT($G8,"mmmm") -> July | L8: =VLOOKUP(OrderLines!$A8,Orders!$A$1:$H$361,MATCH(OrderLines!$L$1,Orders!$A$1:$H$1,0),0) -> Lunch | M8: =VLOOKUP($A8,Orders!$A$1:$H$361,MATCH(OrderLines!$M$1,Orders!$A$1:$H$1,0),0) -> Card | N8: =IF(AND(COUNTIFS(OrderID,$A8,Category,"hot meal")>=1,COUNTIFS(OrderID,$A8,Category,"beverage")>=1),"Combo","Single") -> Combo | O8: {=IF((SUMPRODUCT((OrderID=OrderLines!$A8)*Qty*UnitPrice*DiscountPct))>40,"HighDisc","OK")} -> OK | P8: =(orderlinesTABLE[[#This Row],[UnitCost]]*orderlinesTABLE[[#This Row],[Qty]]) -> 19.55 | Q8: =(orderlinesTABLE[[#This Row],[LineNetAmount]]-orderlinesTABLE[[#This Row],[totalCOST]]) -> 18.51 | R8: =VLOOKUP($B8,Menu!$A$1:$F$20,MATCH(OrderLines!R$1,Menu!$A$1:$F$1,0),0) -> Paneer Roll | S8: {=_xlfn.TEXTJOIN("+",TRUE,_xlfn._xlws.FILTER(orderlinesTABLE[ItemName],OrderID=orderlinesTABLE[[#This Row],[OrderID]]))} -> Masala Chaas+Poha+Paneer Butter Masala + Naan+Paneer Roll | T8: =orderlinesTABLE[[#This Row],[Profit]]/orderlinesTABLE[[#This Row],[LineNetAmount]] -> 0.48633736 | U8: =(orderlinesTABLE[[#This Row],[Qty]]*orderlinesTABLE[[#This Row],[UnitCost]]) -> 19.55
A9: O00004 | B9: HH1DNM | C9: 2 | D9: =VLOOKUP($B9,Menu!$A$1:$F$20,MATCH($D$1,Menu!$A$1:$F$1,0),0) -> 246.09 | E9: =VLOOKUP($B9,Menu!$A$1:$F$20,MATCH(OrderLines!E$1,Menu!$A$1:$F$1,0),0) -> Hot Meal | F9: =VLOOKUP($B9,Menu!$A$1:$F$20,MATCH(OrderLines!F$1,Menu!$A$1:$F$1,0),0) -> 112.08 | G9: =VLOOKUP($A9,Orders!$A$1:$H$361,MATCH($G$1,Orders!$A$1:$H$1,0),0) -> 45879 | H9: =VLOOKUP($A9,Orders!$A$1:$H$361,MATCH(OrderLines!$H$1,Orders!$A$1:$H$1,0),0) -> Plant 2 Canteen | I9: =VLOOKUP($A9,Orders!$A$1:$H$361,MATCH(OrderLines!$I$1,Orders!$A$1:$H$1,0),0) -> 0.03 | J9: =$C9*$D9*(1-$I9) -> 477.4146 | K9: =TEXT($G9,"mmmm") -> August | L9: =VLOOKUP(OrderLines!$A9,Orders!$A$1:$H$361,MATCH(OrderLines!$L$1,Orders!$A$1:$H$1,0),0) -> Breakfast | M9: =VLOOKUP($A9,Orders!$A$1:$H$361,MATCH(OrderLines!$M$1,Orders!$A$1:$H$1,0),0) -> Cash | N9: =IF(AND(COUNTIFS(OrderID,$A9,Category,"hot meal")>=1,COUNTIFS(OrderID,$A9,Category,"beverage")>=1),"Combo","Single") -> Single | O9: {=IF((SUMPRODUCT((OrderID=OrderLines!$A9)*Qty*UnitPrice*DiscountPct))>40,"HighDisc","OK")} -> OK | P9: =(orderlinesTABLE[[#This Row],[UnitCost]]*orderlinesTABLE[[#This Row],[Qty]]) -> 224.16 | Q9: =(orderlinesTABLE[[#This Row],[LineNetAmount]]-orderlinesTABLE[[#This Row],[totalCOST]]) -> 253.2546 | R9: =VLOOKUP($B9,Menu!$A$1:$F$20,MATCH(OrderLines!R$1,Menu!$A$1:$F$1,0),0) -> Egg Curry + Rice | S9: {=_xlfn.TEXTJOIN("+",TRUE,_xlfn._xlws.FILTER(orderlinesTABLE[ItemName],OrderID=orderlinesTABLE[[#This Row],[OrderID]]))} -> Egg Curry + Rice | T9: =orderlinesTABLE[[#This Row],[Profit]]/orderlinesTABLE[[#This Row],[LineNetAmount]] -> 0.530471 | U9: =(orderlinesTABLE[[#This Row],[Qty]]*orderlinesTABLE[[#This Row],[UnitCost]]) -> 224.16
A10: O00005 | B10: SCKW5N | C10: 1 | D10: =VLOOKUP($B10,Menu!$A$1:$F$20,MATCH($D$1,Menu!$A$1:$F$1,0),0) -> 70.54 | E10: =VLOOKUP($B10,Menu!$A$1:$F$20,MATCH(OrderLines!E$1,Menu!$A$1:$F$1,0),0) -> Snack | F10: =VLOOKUP($B10,Menu!$A$1:$F$20,MATCH(OrderLines!F$1,Menu!$A$1:$F$1,0),0) -> 35.81 | G10: =VLOOKUP($A10,Orders!$A$1:$H$361,MATCH($G$1,Orders!$A$1:$H$1,0),0) -> 45845 | H10: =VLOOKUP($A10,Orders!$A$1:$H$361,MATCH(OrderLines!$H$1,Orders!$A$1:$H$1,0),0) -> Plant 2 Canteen | I10: =VLOOKUP($A10,Orders!$A$1:$H$361,MATCH(OrderLines!$I$1,Orders!$A$1:$H$1,0),0) -> 0.04 | J10: =$C10*$D10*(1-$I10) -> 67.7184 | K10: =TEXT($G10,"mmmm") -> July | L10: =VLOOKUP(OrderLines!$A10,Orders!$A$1:$H$361,MATCH(OrderLines!$L$1,Orders!$A$1:$H$1,0),0) -> Breakfast | M10: =VLOOKUP($A10,Orders!$A$1:$H$361,MATCH(OrderLines!$M$1,Orders!$A$1:$H$1,0),0) -> Card | N10: =IF(AND(COUNTIFS(OrderID,$A10,Category,"hot meal")>=1,COUNTIFS(OrderID,$A10,Category,"beverage")>=1),"Combo","Single") -> Single | O10: {=IF((SUMPRODUCT((OrderID=OrderLines!$A10)*Qty*UnitPrice*DiscountPct))>40,"HighDisc","OK")} -> OK | P10: =(orderlinesTABLE[[#This Row],[UnitCost]]*orderlinesTABLE[[#This Row],[Qty]]) -> 35.81 | Q10: =(orderlinesTABLE[[#This Row],[LineNetAmount]]-orderlinesTABLE[[#This Row],[totalCOST]]) -> 31.9084 | R10: =VLOOKUP($B10,Menu!$A$1:$F$20,MATCH(OrderLines!R$1,Menu!$A$1:$F$1,0),0) -> Veg Sandwich | S10: {=_xlfn.TEXTJOIN("+",TRUE,_xlfn._xlws.FILTER(orderlinesTABLE[ItemName],OrderID=orderlinesTABLE[[#This Row],[OrderID]]))} -> Veg Sandwich+Bottled Water | T10: =orderlinesTABLE[[#This Row],[Profit]]/orderlinesTABLE[[#This Row],[LineNetAmount]] -> 0.47119247 | U10: =(orderlinesTABLE[[#This Row],[Qty]]*orderlinesTABLE[[#This Row],[UnitCost]]) -> 35.81 | W10: Q2> | Y10: Row Labels | Z10: Sum of LineNetAmount | AA10: Sum of LineNetAmount2
A11: O00005 | B11: B0T0PV | C11: 1 | D11: =VLOOKUP($B11,Menu!$A$1:$F$20,MATCH($D$1,Menu!$A$1:$F$1,0),0) -> 28.43 | E11: =VLOOKUP($B11,Menu!$A$1:$F$20,MATCH(OrderLines!E$1,Menu!$A$1:$F$1,0),0) -> Beverage | F11: =VLOOKUP($B11,Menu!$A$1:$F$20,MATCH(OrderLines!F$1,Menu!$A$1:$F$1,0),0) -> 13.89 | G11: =VLOOKUP($A11,Orders!$A$1:$H$361,MATCH($G$1,Orders!$A$1:$H$1,0),0) -> 45845 | H11: =VLOOKUP($A11,Orders!$A$1:$H$361,MATCH(OrderLines!$H$1,Orders!$A$1:$H$1,0),0) -> Plant 2 Canteen | I11: =VLOOKUP($A11,Orders!$A$1:$H$361,MATCH(OrderLines!$I$1,Orders!$A$1:$H$1,0),0) -> 0.04 | J11: =$C11*$D11*(1-$I11) -> 27.2928 | K11: =TEXT($G11,"mmmm") -> July | L11: =VLOOKUP(OrderLines!$A11,Orders!$A$1:$H$361,MATCH(OrderLines!$L$1,Orders!$A$1:$H$1,0),0) -> Breakfast | M11: =VLOOKUP($A11,Orders!$A$1:$H$361,MATCH(OrderLines!$M$1,Orders!$A$1:$H$1,0),0) -> Card | N11: =IF(AND(COUNTIFS(OrderID,$A11,Category,"hot meal")>=1,COUNTIFS(OrderID,$A11,Category,"beverage")>=1),"Combo","Single") -> Single | O11: {=IF((SUMPRODUCT((OrderID=OrderLines!$A11)*Qty*UnitPrice*DiscountPct))>40,"HighDisc","OK")} -> OK | P11: =(orderlinesTABLE[[#This Row],[UnitCost]]*orderlinesTABLE[[#This Row],[Qty]]) -> 13.89 | Q11: =(orderlinesTABLE[[#This Row],[LineNetAmount]]-orderlinesTABLE[[#This Row],[totalCOST]]) -> 13.4028 | R11: =VLOOKUP($B11,Menu!$A$1:$F$20,MATCH(OrderLines!R$1,Menu!$A$1:$F$1,0),0) -> Bottled Water | S11: {=_xlfn.TEXTJOIN("+",TRUE,_xlfn._xlws.FILTER(orderlinesTABLE[ItemName],OrderID=orderlinesTABLE[[#This Row],[OrderID]]))} -> Veg Sandwich+Bottled Water | T11: =orderlinesTABLE[[#This Row],[Profit]]/orderlinesTABLE[[#This Row],[LineNetAmount]] -> 0.49107457 | U11: =(orderlinesTABLE[[#This Row],[Qty]]*orderlinesTABLE[[#This Row],[UnitCost]]) -> 13.89 | Y11: July | Z11: 63939.191
A12: O00006 | B12: BXO6QJ | C12: 3 | D12: =VLOOKUP($B12,Menu!$A$1:$F$20,MATCH($D$1,Menu!$A$1:$F$1,0),0) -> 20.11 | E12: =VLOOKUP($B12,Menu!$A$1:$F$20,MATCH(OrderLines!E$1,Menu!$A$1:$F$1,0),0) -> Beverage | F12: =VLOOKUP($B12,Menu!$A$1:$F$20,MATCH(OrderLines!F$1,Menu!$A$1:$F$1,0),0) -> 8 | G12: =VLOOKUP($A12,Orders!$A$1:$H$361,MATCH($G$1,Orders!$A$1:$H$1,0),0) -> 45863 | H12: =VLOOKUP($A12,Orders!$A$1:$H$361,MATCH(OrderLines!$H$1,Orders!$A$1:$H$1,0),0) -> Plant 1 Canteen | I12: =VLOOKUP($A12,Orders!$A$1:$H$361,MATCH(OrderLines!$I$1,Orders!$A$1:$H$1,0),0) -> 0.1 | J12: =$C12*$D12*(1-$I12) -> 54.297 | K12: =TEXT($G12,"mmmm") -> July | L12: =VLOOKUP(OrderLines!$A12,Orders!$A$1:$H$361,MATCH(OrderLines!$L$1,Orders!$A$1:$H$1,0),0) -> Breakfast | M12: =VLOOKUP($A12,Orders!$A$1:$H$361,MATCH(OrderLines!$M$1,Orders!$A$1:$H$1,0),0) -> UPI | N12: =IF(AND(COUNTIFS(OrderID,$A12,Category,"hot meal")>=1,COUNTIFS(OrderID,$A12,Category,"beverage")>=1),"Combo","Single") -> Single | O12: {=IF((SUMPRODUCT((OrderID=OrderLines!$A12)*Qty*UnitPrice*DiscountPct))>40,"HighDisc","OK")} -> OK | P12: =(orderlinesTABLE[[#This Row],[UnitCost]]*orderlinesTABLE[[#This Row],[Qty]]) -> 24 | Q12: =(orderlinesTABLE[[#This Row],[LineNetAmount]]-orderlinesTABLE[[#This Row],[totalCOST]]) -> 30.297 | R12: =VLOOKUP($B12,Menu!$A$1:$F$20,MATCH(OrderLines!R$1,Menu!$A$1:$F$1,0),0) -> Nimbu Pani | S12: {=_xlfn.TEXTJOIN("+",TRUE,_xlfn._xlws.FILTER(orderlinesTABLE[ItemName],OrderID=orderlinesTABLE[[#This Row],[OrderID]]))} -> Nimbu Pani | T12: =orderlinesTABLE[[#This Row],[Profit]]/orderlinesTABLE[[#This Row],[LineNetAmount]] -> 0.55798663 | U12: =(orderlinesTABLE[[#This Row],[Qty]]*orderlinesTABLE[[#This Row],[UnitCost]]) -> 24 | Y12: August | Z12: 68708.44 | AA12: 0.07459039
A13: O00007 | B13: BOC6UZ | C13: 1 | D13: =VLOOKUP($B13,Menu!$A$1:$F$20,MATCH($D$1,Menu!$A$1:$F$1,0),0) -> 32.98 | E13: =VLOOKUP($B13,Menu!$A$1:$F$20,MATCH(OrderLines!E$1,Menu!$A$1:$F$1,0),0) -> Beverage | F13: =VLOOKUP($B13,Menu!$A$1:$F$20,MATCH(OrderLines!F$1,Menu!$A$1:$F$1,0),0) -> 11.84 | G13: =VLOOKUP($A13,Orders!$A$1:$H$361,MATCH($G$1,Orders!$A$1:$H$1,0),0) -> 45852 | H13: =VLOOKUP($A13,Orders!$A$1:$H$361,MATCH(OrderLines!$H$1,Orders!$A$1:$H$1,0),0) -> Plant 2 Canteen | I13: =VLOOKUP($A13,Orders!$A$1:$H$361,MATCH(OrderLines!$I$1,Orders!$A$1:$H$1,0),0) -> 0.07 | J13: =$C13*$D13*(1-$I13) -> 30.6714 | K13: =TEXT($G13,"mmmm") -> July | L13: =VLOOKUP(OrderLines!$A13,Orders!$A$1:$H$361,MATCH(OrderLines!$L$1,Orders!$A$1:$H$1,0),0) -> Dinner | M13: =VLOOKUP($A13,Orders!$A$1:$H$361,MATCH(OrderLines!$M$1,Orders!$A$1:$H$1,0),0) -> Card | N13: =IF(AND(COUNTIFS(OrderID,$A13,Category,"hot meal")>=1,COUNTIFS(OrderID,$A13,Category,"beverage")>=1),"Combo","Single") -> Combo | O13: {=IF((SUMPRODUCT((OrderID=OrderLines!$A13)*Qty*UnitPrice*DiscountPct))>40,"HighDisc","OK")} -> OK | P13: =(orderlinesTABLE[[#This Row],[UnitCost]]*orderlinesTABLE[[#This Row],[Qty]]) -> 11.84 | Q13: =(orderlinesTABLE[[#This Row],[LineNetAmount]]-orderlinesTABLE[[#This Row],[totalCOST]]) -> 18.8314 | R13: =VLOOKUP($B13,Menu!$A$1:$F$20,MATCH(OrderLines!R$1,Menu!$A$1:$F$1,0),0) -> Masala Chaas | S13: {=_xlfn.TEXTJOIN("+",TRUE,_xlfn._xlws.FILTER(orderlinesTABLE[ItemName],OrderID=orderlinesTABLE[[#This Row],[OrderID]]))} -> Masala Chaas+Paneer Butter Masala + Naan | T13: =orderlinesTABLE[[#This Row],[Profit]]/orderlinesTABLE[[#This Row],[LineNetAmount]] -> 0.61397263 | U13: =(orderlinesTABLE[[#This Row],[Qty]]*orderlinesTABLE[[#This Row],[UnitCost]]) -> 11.84 | Y13: Grand Total | Z13: 132647.63
A14: O00007 | B14: H3A3ZM | C14: 2 | D14: =VLOOKUP($B14,Menu!$A$1:$F$20,MATCH($D$1,Menu!$A$1:$F$1,0),0) -> 170.83 | E14: =VLOOKUP($B14,Menu!$A$1:$F$20,MATCH(OrderLines!E$1,Menu!$A$1:$F$1,0),0) -> Hot Meal | F14: =VLOOKUP($B14,Menu!$A$1:$F$20,MATCH(OrderLines!F$1,Menu!$A$1:$F$1,0),0) -> 74.07 | G14: =VLOOKUP($A14,Orders!$A$1:$H$361,MATCH($G$1,Orders!$A$1:$H$1,0),0) -> 45852 | H14: =VLOOKUP($A14,Orders!$A$1:$H$361,MATCH(OrderLines!$H$1,Orders!$A$1:$H$1,0),0) -> Plant 2 Canteen | I14: =VLOOKUP($A14,Orders!$A$1:$H$361,MATCH(OrderLines!$I$1,Orders!$A$1:$H$1,0),0) -> 0.07 | J14: =$C14*$D14*(1-$I14) -> 317.7438 | K14: =TEXT($G14,"mmmm") -> July | L14: =VLOOKUP(OrderLines!$A14,Orders!$A$1:$H$361,MATCH(OrderLines!$L$1,Orders!$A$1:$H$1,0),0) -> Dinner | M14: =VLOOKUP($A14,Orders!$A$1:$H$361,MATCH(OrderLines!$M$1,Orders!$A$1:$H$1,0),0) -> Card | N14: =IF(AND(COUNTIFS(OrderID,$A14,Category,"hot meal")>=1,COUNTIFS(OrderID,$A14,Category,"beverage")>=1),"Combo","Single") -> Combo | O14: {=IF((SUMPRODUCT((OrderID=OrderLines!$A14)*Qty*UnitPrice*DiscountPct))>40,"HighDisc","OK")} -> OK | P14: =(orderlinesTABLE[[#This Row],[UnitCost]]*orderlinesTABLE[[#This Row],[Qty]]) -> 148.14 | Q14: =(orderlinesTABLE[[#This Row],[LineNetAmount]]-orderlinesTABLE[[#This Row],[totalCOST]]) -> 169.6038 | R14: =VLOOKUP($B14,Menu!$A$1:$F$20,MATCH(OrderLines!R$1,Menu!$A$1:$F$1,0),0) -> Paneer Butter Masala + Naan | S14: {=_xlfn.TEXTJOIN("+",TRUE,_xlfn._xlws.FILTER(orderlinesTABLE[ItemName],OrderID=orderlinesTABLE[[#This Row],[OrderID]]))} -> Masala Chaas+Paneer Butter Masala + Naan | T14: =orderlinesTABLE[[#This Row],[Profit]]/orderlinesTABLE[[#This Row],[LineNetAmount]] -> 0.53377532 | U14: =(orderlinesTABLE[[#This Row],[Qty]]*orderlinesTABLE[[#This Row],[UnitCost]]) -> 148.14
A15: O00008 | B15: BHL1C3 | C15: 1 | D15: =VLOOKUP($B15,Menu!$A$1:$F$20,MATCH($D$1,Menu!$A$1:$F$1,0),0) -> 22.2 | E15: =VLOOKUP($B15,Menu!$A$1:$F$20,MATCH(OrderLines!E$1,Menu!$A$1:$F$1,0),0) -> Beverage | F15: =VLOOKUP($B15,Menu!$A$1:$F$20,MATCH(OrderLines!F$1,Menu!$A$1:$F$1,0),0) -> 9.38 | G15: =VLOOKUP($A15,Orders!$A$1:$H$361,MATCH($G$1,Orders!$A$1:$H$1,0),0) -> 45863 | H15: =VLOOKUP($A15,Orders!$A$1:$H$361,MATCH(OrderLines!$H$1,Orders!$A$1:$H$1,0),0) -> Plant 1 Canteen | I15: =VLOOKUP($A15,Orders!$A$1:$H$361,MATCH(OrderLines!$I$1,Orders!$A$1:$H$1,0),0) -> 0 | J15: =$C15*$D15*(1-$I15) -> 22.2 | K15: =TEXT($G15,"mmmm") -> July | L15: =VLOOKUP(OrderLines!$A15,Orders!$A$1:$H$361,MATCH(OrderLines!$L$1,Orders!$A$1:$H$1,0),0) -> Lunch | M15: =VLOOKUP($A15,Orders!$A$1:$H$361,MATCH(OrderLines!$M$1,Orders!$A$1:$H$1,0),0) -> UPI | N15: =IF(AND(COUNTIFS(OrderID,$A15,Category,"hot meal")>=1,COUNTIFS(OrderID,$A15,Category,"beverage")>=1),"Combo","Single") -> Single | O15: {=IF((SUMPRODUCT((OrderID=OrderLines!$A15)*Qty*UnitPrice*DiscountPct))>40,"HighDisc","OK")} -> OK | P15: =(orderlinesTABLE[[#This Row],[UnitCost]]*orderlinesTABLE[[#This Row],[Qty]]) -> 9.38 | Q15: =(orderlinesTABLE[[#This Row],[LineNetAmount]]-orderlinesTABLE[[#This Row],[totalCOST]]) -> 12.82 | R15: =VLOOKUP($B15,Menu!$A$1:$F$20,MATCH(OrderLines!R$1,Menu!$A$1:$F$1,0),0) -> Coffee | S15: {=_xlfn.TEXTJOIN("+",TRUE,_xlfn._xlws.FILTER(orderlinesTABLE[ItemName],OrderID=orderlinesTABLE[[#This Row],[OrderID]]))} -> Coffee+Fruit Cup+Tea | T15: =orderlinesTABLE[[#This Row],[Profit]]/orderlinesTABLE[[#This Row],[LineNetAmount]] -> 0.57747748 | U15: =(orderlinesTABLE[[#This Row],[Qty]]*orderlinesTABLE[[#This Row],[UnitCost]]) -> 9.38
A16: O00008 | B16: DYTJXE | C16: 3 | D16: =VLOOKUP($B16,Menu!$A$1:$F$20,MATCH($D$1,Menu!$A$1:$F$1,0),0) -> 57.07 | E16: =VLOOKUP($B16,Menu!$A$1:$F$20,MATCH(OrderLines!E$1,Menu!$A$1:$F$1,0),0) -> Dessert | F16: =VLOOKUP($B16,Menu!$A$1:$F$20,MATCH(OrderLines!F$1,Menu!$A$1:$F$1,0),0) -> 29.14 | G16: =VLOOKUP($A16,Orders!$A$1:$H$361,MATCH($G$1,Orders!$A$1:$H$1,0),0) -> 45863 | H16: =VLOOKUP($A16,Orders!$A$1:$H$361,MATCH(OrderLines!$H$1,Orders!$A$1:$H$1,0),0) -> Plant 1 Canteen | I16: =VLOOKUP($A16,Orders!$A$1:$H$361,MATCH(OrderLines!$I$1,Orders!$A$1:$H$1,0),0) -> 0 | J16: =$C16*$D16*(1-$I16) -> 171.21 | K16: =TEXT($G16,"mmmm") -> July | L16: =VLOOKUP(OrderLines!$A16,Orders!$A$1:$H$361,MATCH(OrderLines!$L$1,Orders!$A$1:$H$1,0),0) -> Lunch | M16: =VLOOKUP($A16,Orders!$A$1:$H$361,MATCH(OrderLines!$M$1,Orders!$A$1:$H$1,0),0) -> UPI | N16: =IF(AND(COUNTIFS(OrderID,$A16,Category,"hot meal")>=1,COUNTIFS(OrderID,$A16,Category,"beverage")>=1),"Combo","Single") -> Single | O16: {=IF((SUMPRODUCT((OrderID=OrderLines!$A16)*Qty*UnitPrice*DiscountPct))>40,"HighDisc","OK")} -> OK | P16: =(orderlinesTABLE[[#This Row],[UnitCost]]*orderlinesTABLE[[#This Row],[Qty]]) -> 87.42 | Q16: =(orderlinesTABLE[[#This Row],[LineNetAmount]]-orderlinesTABLE[[#This Row],[totalCOST]]) -> 83.79 | R16: =VLOOKUP($B16,Menu!$A$1:$F$20,MATCH(OrderLines!R$1,Menu!$A$1:$F$1,0),0) -> Fruit Cup | S16: {=_xlfn.TEXTJOIN("+",TRUE,_xlfn._xlws.FILTER(orderlinesTABLE[ItemName],OrderID=orderlinesTABLE[[#This Row],[OrderID]]))} -> Coffee+Fruit Cup+Tea | T16: =orderlinesTABLE[[#This Row],[Profit]]/orderlinesTABLE[[#This Row],[LineNetAmount]] -> 0.48939898 | U16: =(orderlinesTABLE[[#This Row],[Qty]]*orderlinesTABLE[[#This Row],[UnitCost]]) -> 87.42 | X16: WRONG WAY | Y16: =(GETPIVOTDATA("LineNetAmount",$Y$10,"MonthName","August")-GETPIVOTDATA("LineNetAmount",$Y$10,"MonthName","July"))/GETPIVOTDATA("LineNetAmount",$Y$10,"MonthName","July")*100 -> 7.459039 | Z16: mom%
A17: O00008 | B17: BTIQJ7 | C17: 1 | D17: =VLOOKUP($B17,Menu!$A$1:$F$20,MATCH($D$1,Menu!$A$1:$F$1,0),0) -> 30.34 | E17: =VLOOKUP($B17,Menu!$A$1:$F$20,MATCH(OrderLines!E$1,Menu!$A$1:$F$1,0),0) -> Beverage | F17: =VLOOKUP($B17,Menu!$A$1:$F$20,MATCH(OrderLines!F$1,Menu!$A$1:$F$1,0),0) -> 14.18 | G17: =VLOOKUP($A17,Orders!$A$1:$H$361,MATCH($G$1,Orders!$A$1:$H$1,0),0) -> 45863 | H17: =VLOOKUP($A17,Orders!$A$1:$H$361,MATCH(OrderLines!$H$1,Orders!$A$1:$H$1,0),0) -> Plant 1 Canteen | I17: =VLOOKUP($A17,Orders!$A$1:$H$361,MATCH(OrderLines!$I$1,Orders!$A$1:$H$1,0),0) -> 0 | J17: =$C17*$D17*(1-$I17) -> 30.34 | K17: =TEXT($G17,"mmmm") -> July | L17: =VLOOKUP(OrderLines!$A17,Orders!$A$1:$H$361,MATCH(OrderLines!$L$1,Orders!$A$1:$H$1,0),0) -> Lunch | M17: =VLOOKUP($A17,Orders!$A$1:$H$361,MATCH(OrderLines!$M$1,Orders!$A$1:$H$1,0),0) -> UPI | N17: =IF(AND(COUNTIFS(OrderID,$A17,Category,"hot meal")>=1,COUNTIFS(OrderID,$A17,Category,"beverage")>=1),"Combo","Single") -> Single | O17: {=IF((SUMPRODUCT((OrderID=OrderLines!$A17)*Qty*UnitPrice*DiscountPct))>40,"HighDisc","OK")} -> OK | P17: =(orderlinesTABLE[[#This Row],[UnitCost]]*orderlinesTABLE[[#This Row],[Qty]]) -> 14.18 | Q17: =(orderlinesTABLE[[#This Row],[LineNetAmount]]-orderlinesTABLE[[#This Row],[totalCOST]]) -> 16.16 | R17: =VLOOKUP($B17,Menu!$A$1:$F$20,MATCH(OrderLines!R$1,Menu!$A$1:$F$1,0),0) -> Tea | S17: {=_xlfn.TEXTJOIN("+",TRUE,_xlfn._xlws.FILTER(orderlinesTABLE[ItemName],OrderID=orderlinesTABLE[[#This Row],[OrderID]]))} -> Coffee+Fruit Cup+Tea | T17: =orderlinesTABLE[[#This Row],[Profit]]/orderlinesTABLE[[#This Row],[LineNetAmount]] -> 0.53263019 | U17: =(orderlinesTABLE[[#This Row],[Qty]]*orderlinesTABLE[[#This Row],[UnitCost]]) -> 14.18
A18: O00009 | B18: H3A3ZM | C18: 2 | D18: =VLOOKUP($B18,Menu!$A$1:$F$20,MATCH($D$1,Menu!$A$1:$F$1,0),0) -> 170.83 | E18: =VLOOKUP($B18,Menu!$A$1:$F$20,MATCH(OrderLines!E$1,Menu!$A$1:$F$1,0),0) -> Hot Meal | F18: =VLOOKUP($B18,Menu!$A$1:$F$20,MATCH(OrderLines!F$1,Menu!$A$1:$F$1,0),0) -> 74.07 | G18: =VLOOKUP($A18,Orders!$A$1:$H$361,MATCH($G$1,Orders!$A$1:$H$1,0),0) -> 45844 | H18: =VLOOKUP($A18,Orders!$A$1:$H$361,MATCH(OrderLines!$H$1,Orders!$A$1:$H$1,0),0) -> Head Office Café | I18: =VLOOKUP($A18,Orders!$A$1:$H$361,MATCH(OrderLines!$I$1,Orders!$A$1:$H$1,0),0) -> 0.07 | J18: =$C18*$D18*(1-$I18) -> 317.7438 | K18: =TEXT($G18,"mmmm") -> July | L18: =VLOOKUP(OrderLines!$A18,Orders!$A$1:$H$361,MATCH(OrderLines!$L$1,Orders!$A$1:$H$1,0),0) -> Breakfast | M18: =VLOOKUP($A18,Orders!$A$1:$H$361,MATCH(OrderLines!$M$1,Orders!$A$1:$H$1,0),0) -> Cash | N18: =IF(AND(COUNTIFS(OrderID,$A18,Category,"hot meal")>=1,COUNTIFS(OrderID,$A18,Category,"beverage")>=1),"Combo","Single") -> Single | O18: {=IF((SUMPRODUCT((OrderID=OrderLines!$A18)*Qty*UnitPrice*DiscountPct))>40,"HighDisc","OK")} -> OK | P18: =(orderlinesTABLE[[#This Row],[UnitCost]]*orderlinesTABLE[[#This Row],[Qty]]) -> 148.14 | Q18: =(orderlinesTABLE[[#This Row],[LineNetAmount]]-orderlinesTABLE[[#This Row],[totalCOST]]) -> 169.6038 | R18: =VLOOKUP($B18,Menu!$A$1:$F$20,MATCH(OrderLines!R$1,Menu!$A$1:$F$1,0),0) -> Paneer Butter Masala + Naan | S18: {=_xlfn.TEXTJOIN("+",TRUE,_xlfn._xlws.FILTER(orderlinesTABLE[ItemName],OrderID=orderlinesTABLE[[#This Row],[OrderID]]))} -> Paneer Butter Masala + Naan+Fruit Cup+Paneer Roll | T18: =orderlinesTABLE[[#This Row],[Profit]]/orderlinesTABLE[[#This Row],[LineNetAmount]] -> 0.53377532 | U18: =(orderlinesTABLE[[#This Row],[Qty]]*orderlinesTABLE[[#This Row],[UnitCost]]) -> 148.14
A19: O00009 | B19: DYTJXE | C19: 2 | D19: =VLOOKUP($B19,Menu!$A$1:$F$20,MATCH($D$1,Menu!$A$1:$F$1,0),0) -> 57.07 | E19: =VLOOKUP($B19,Menu!$A$1:$F$20,MATCH(OrderLines!E$1,Menu!$A$1:$F$1,0),0) -> Dessert | F19: =VLOOKUP($B19,Menu!$A$1:$F$20,MATCH(OrderLines!F$1,Menu!$A$1:$F$1,0),0) -> 29.14 | G19: =VLOOKUP($A19,Orders!$A$1:$H$361,MATCH($G$1,Orders!$A$1:$H$1,0),0) -> 45844 | H19: =VLOOKUP($A19,Orders!$A$1:$H$361,MATCH(OrderLines!$H$1,Orders!$A$1:$H$1,0),0) -> Head Office Café | I19: =VLOOKUP($A19,Orders!$A$1:$H$361,MATCH(OrderLines!$I$1,Orders!$A$1:$H$1,0),0) -> 0.07 | J19: =$C19*$D19*(1-$I19) -> 106.1502 | K19: =TEXT($G19,"mmmm") -> July | L19: =VLOOKUP(OrderLines!$A19,Orders!$A$1:$H$361,MATCH(OrderLines!$L$1,Orders!$A$1:$H$1,0),0) -> Breakfast | M19: =VLOOKUP($A19,Orders!$A$1:$H$361,MATCH(OrderLines!$M$1,Orders!$A$1:$H$1,0),0) -> Cash | N19: =IF(AND(COUNTIFS(OrderID,$A19,Category,"hot meal")>=1,COUNTIFS(OrderID,$A19,Category,"beverage")>=1),"Combo","Single") -> Single | O19: {=IF((SUMPRODUCT((OrderID=OrderLines!$A19)*Qty*UnitPrice*DiscountPct))>40,"HighDisc","OK")} -> OK | P19: =(orderlinesTABLE[[#This Row],[UnitCost]]*orderlinesTABLE[[#This Row],[Qty]]) -> 58.28 | Q19: =(orderlinesTABLE[[#This Row],[LineNetAmount]]-orderlinesTABLE[[#This Row],[totalCOST]]) -> 47.8702 | R19: =VLOOKUP($B19,Menu!$A$1:$F$20,MATCH(OrderLines!R$1,Menu!$A$1:$F$1,0),0) -> Fruit Cup | S19: {=_xlfn.TEXTJOIN("+",TRUE,_xlfn._xlws.FILTER(orderlinesTABLE[ItemName],OrderID=orderlinesTABLE[[#This Row],[OrderID]]))} -> Paneer Butter Masala + Naan+Fruit Cup+Paneer Roll | T19: =orderlinesTABLE[[#This Row],[Profit]]/orderlinesTABLE[[#This Row],[LineNetAmount]] -> 0.45096665 | U19: =(orderlinesTABLE[[#This Row],[Qty]]*orderlinesTABLE[[#This Row],[UnitCost]]) -> 58.28
A20: O00009 | B20: SZBIKC | C20: 1 | D20: =VLOOKUP($B20,Menu!$A$1:$F$20,MATCH($D$1,Menu!$A$1:$F$1,0),0) -> 38.06 | E20: =VLOOKUP($B20,Menu!$A$1:$F$20,MATCH(OrderLines!E$1,Menu!$A$1:$F$1,0),0) -> Snack | F20: =VLOOKUP($B20,Menu!$A$1:$F$20,MATCH(OrderLines!F$1,Menu!$A$1:$F$1,0),0) -> 19.55 | G20: =VLOOKUP($A20,Orders!$A$1:$H$361,MATCH($G$1,Orders!$A$1:$H$1,0),0) -> 45844 | H20: =VLOOKUP($A20,Orders!$A$1:$H$361,MATCH(OrderLines!$H$1,Orders!$A$1:$H$1,0),0) -> Head Office Café | I20: =VLOOKUP($A20,Orders!$A$1:$H$361,MATCH(OrderLines!$I$1,Orders!$A$1:$H$1,0),0) -> 0.07 | J20: =$C20*$D20*(1-$I20) -> 35.3958 | K20: =TEXT($G20,"mmmm") -> July | L20: =VLOOKUP(OrderLines!$A20,Orders!$A$1:$H$361,MATCH(OrderLines!$L$1,Orders!$A$1:$H$1,0),0) -> Breakfast | M20: =VLOOKUP($A20,Orders!$A$1:$H$361,MATCH(OrderLines!$M$1,Orders!$A$1:$H$1,0),0) -> Cash | N20: =IF(AND(COUNTIFS(OrderID,$A20,Category,"hot meal")>=1,COUNTIFS(OrderID,$A20,Category,"beverage")>=1),"Combo","Single") -> Single | O20: {=IF((SUMPRODUCT((OrderID=OrderLines!$A20)*Qty*UnitPrice*DiscountPct))>40,"HighDisc","OK")} -> OK | P20: =(orderlinesTABLE[[#This Row],[UnitCost]]*orderlinesTABLE[[#This Row],[Qty]]) -> 19.55 | Q20: =(orderlinesTABLE[[#This Row],[LineNetAmount]]-orderlinesTABLE[[#This Row],[totalCOST]]) -> 15.8458 | R20: =VLOOKUP($B20,Menu!$A$1:$F$20,MATCH(OrderLines!R$1,Menu!$A$1:$F$1,0),0) -> Paneer Roll | S20: {=_xlfn.TEXTJOIN("+",TRUE,_xlfn._xlws.FILTER(orderlinesTABLE[ItemName],OrderID=orderlinesTABLE[[#This Row],[OrderID]]))} -> Paneer Butter Masala + Naan+Fruit Cup+Paneer Roll | T20: =orderlinesTABLE[[#This Row],[Profit]]/orderlinesTABLE[[#This Row],[LineNetAmount]] -> 0.44767458 | U20: =(orderlinesTABLE[[#This Row],[Qty]]*orderlinesTABLE[[#This Row],[UnitCost]]) -> 19.55
A21: O00010 | B21: BHL1C3 | C21: 2 | D21: =VLOOKUP($B21,Menu!$A$1:$F$20,MATCH($D$1,Menu!$A$1:$F$1,0),0) -> 22.2 | E21: =VLOOKUP($B21,Menu!$A$1:$F$20,MATCH(OrderLines!E$1,Menu!$A$1:$F$1,0),0) -> Beverage | F21: =VLOOKUP($B21,Menu!$A$1:$F$20,MATCH(OrderLines!F$1,Menu!$A$1:$F$1,0),0) -> 9.38 | G21: =VLOOKUP($A21,Orders!$A$1:$H$361,MATCH($G$1,Orders!$A$1:$H$1,0),0) -> 45862 | H21: =VLOOKUP($A21,Orders!$A$1:$H$361,MATCH(OrderLines!$H$1,Orders!$A$1:$H$1,0),0) -> Plant 1 Canteen | I21: =VLOOKUP($A21,Orders!$A$1:$H$361,MATCH(OrderLines!$I$1,Orders!$A$1:$H$1,0),0) -> 0.04 | J21: =$C21*$D21*(1-$I21) -> 42.624 | K21: =TEXT($G21,"mmmm") -> July | L21: =VLOOKUP(OrderLines!$A21,Orders!$A$1:$H$361,MATCH(OrderLines!$L$1,Orders!$A$1:$H$1,0),0) -> Breakfast | M21: =VLOOKUP($A21,Orders!$A$1:$H$361,MATCH(OrderLines!$M$1,Orders!$A$1:$H$1,0),0) -> Card | N21: =IF(AND(COUNTIFS(OrderID,$A21,Category,"hot meal")>=1,COUNTIFS(OrderID,$A21,Category,"beverage")>=1),"Combo","Single") -> Combo | O21: {=IF((SUMPRODUCT((OrderID=OrderLines!$A21)*Qty*UnitPrice*DiscountPct))>40,"HighDisc","OK")} -> OK | P21: =(orderlinesTABLE[[#This Row],[UnitCost]]*orderlinesTABLE[[#This Row],[Qty]]) -> 18.76 | Q21: =(orderlinesTABLE[[#This Row],[LineNetAmount]]-orderlinesTABLE[[#This Row],[totalCOST]]) -> 23.864 | R21: =VLOOKUP($B21,Menu!$A$1:$F$20,MATCH(OrderLines!R$1,Menu!$A$1:$F$1,0),0) -> Coffee | S21: {=_xlfn.TEXTJOIN("+",TRUE,_xlfn._xlws.FILTER(orderlinesTABLE[ItemName],OrderID=orderlinesTABLE[[#This Row],[OrderID]]))} -> Coffee+Egg Curry + Rice+Veg Sandwich+Gulab Jamun (2 pc) | T21: =orderlinesTABLE[[#This Row],[Profit]]/orderlinesTABLE[[#This Row],[LineNetAmount]] -> 0.55987237 | U21: =(orderlinesTABLE[[#This Row],[Qty]]*orderlinesTABLE[[#This Row],[UnitCost]]) -> 18.76
A22: O00010 | B22: HH1DNM | C22: 1 | D22: =VLOOKUP($B22,Menu!$A$1:$F$20,MATCH($D$1,Menu!$A$1:$F$1,0),0) -> 246.09 | E22: =VLOOKUP($B22,Menu!$A$1:$F$20,MATCH(OrderLines!E$1,Menu!$A$1:$F$1,0),0) -> Hot Meal | F22: =VLOOKUP($B22,Menu!$A$1:$F$20,MATCH(OrderLines!F$1,Menu!$A$1:$F$1,0),0) -> 112.08 | G22: =VLOOKUP($A22,Orders!$A$1:$H$361,MATCH($G$1,Orders!$A$1:$H$1,0),0) -> 45862 | H22: =VLOOKUP($A22,Orders!$A$1:$H$361,MATCH(OrderLines!$H$1,Orders!$A$1:$H$1,0),0) -> Plant 1 Canteen | I22: =VLOOKUP($A22,Orders!$A$1:$H$361,MATCH(OrderLines!$I$1,Orders!$A$1:$H$1,0),0) -> 0.04 | J22: =$C22*$D22*(1-$I22) -> 236.2464 | K22: =TEXT($G22,"mmmm") -> July | L22: =VLOOKUP(OrderLines!$A22,Orders!$A$1:$H$361,MATCH(OrderLines!$L$1,Orders!$A$1:$H$1,0),0) -> Breakfast | M22: =VLOOKUP($A22,Orders!$A$1:$H$361,MATCH(OrderLines!$M$1,Orders!$A$1:$H$1,0),0) -> Card | N22: =IF(AND(COUNTIFS(OrderID,$A22,Category,"hot meal")>=1,COUNTIFS(OrderID,$A22,Category,"beverage")>=1),"Combo","Single") -> Combo | O22: {=IF((SUMPRODUCT((OrderID=OrderLines!$A22)*Qty*UnitPrice*DiscountPct))>40,"HighDisc","OK")} -> OK | P22: =(orderlinesTABLE[[#This Row],[UnitCost]]*orderlinesTABLE[[#This Row],[Qty]]) -> 112.08 | Q22: =(orderlinesTABLE[[#This Row],[LineNetAmount]]-orderlinesTABLE[[#This Row],[totalCOST]]) -> 124.1664 | R22: =VLOOKUP($B22,Menu!$A$1:$F$20,MATCH(OrderLines!R$1,Menu!$A$1:$F$1,0),0) -> Egg Curry + Rice | S22: {=_xlfn.TEXTJOIN("+",TRUE,_xlfn._xlws.FILTER(orderlinesTABLE[ItemName],OrderID=orderlinesTABLE[[#This Row],[OrderID]]))} -> Coffee+Egg Curry + Rice+Veg Sandwich+Gulab Jamun (2 pc) | T22: =orderlinesTABLE[[#This Row],[Profit]]/orderlinesTABLE[[#This Row],[LineNetAmount]] -> 0.52558007 | U22: =(orderlinesTABLE[[#This Row],[Qty]]*orderlinesTABLE[[#This Row],[UnitCost]]) -> 112.08
A23: O00010 | B23: SCKW5N | C23: 1 | D23: =VLOOKUP($B23,Menu!$A$1:$F$20,MATCH($D$1,Menu!$A$1:$F$1,0),0) -> 70.54 | E23: =VLOOKUP($B23,Menu!$A$1:$F$20,MATCH(OrderLines!E$1,Menu!$A$1:$F$1,0),0) -> Snack | F23: =VLOOKUP($B23,Menu!$A$1:$F$20,MATCH(OrderLines!F$1,Menu!$A$1:$F$1,0),0) -> 35.81 | G23: =VLOOKUP($A23,Orders!$A$1:$H$361,MATCH($G$1,Orders!$A$1:$H$1,0),0) -> 45862 | H23: =VLOOKUP($A23,Orders!$A$1:$H$361,MATCH(OrderLines!$H$1,Orders!$A$1:$H$1,0),0) -> Plant 1 Canteen | I23: =VLOOKUP($A23,Orders!$A$1:$H$361,MATCH(OrderLines!$I$1,Orders!$A$1:$H$1,0),0) -> 0.04 | J23: =$C23*$D23*(1-$I23) -> 67.7184 | K23: =TEXT($G23,"mmmm") -> July | L23: =VLOOKUP(OrderLines!$A23,Orders!$A$1:$H$361,MATCH(OrderLines!$L$1,Orders!$A$1:$H$1,0),0) -> Breakfast | M23: =VLOOKUP($A23,Orders!$A$1:$H$361,MATCH(OrderLines!$M$1,Orders!$A$1:$H$1,0),0) -> Card | N23: =IF(AND(COUNTIFS(OrderID,$A23,Category,"hot meal")>=1,COUNTIFS(OrderID,$A23,Category,"beverage")>=1),"Combo","Single") -> Combo | O23: {=IF((SUMPRODUCT((OrderID=OrderLines!$A23)*Qty*UnitPrice*DiscountPct))>40,"HighDisc","OK")} -> OK | P23: =(orderlinesTABLE[[#This Row],[UnitCost]]*orderlinesTABLE[[#This Row],[Qty]]) -> 35.81 | Q23: =(orderlinesTABLE[[#This Row],[LineNetAmount]]-orderlinesTABLE[[#This Row],[totalCOST]]) -> 31.9084 | R23: =VLOOKUP($B23,Menu!$A$1:$F$20,MATCH(OrderLines!R$1,Menu!$A$1:$F$1,0),0) -> Veg Sandwich | S23: {=_xlfn.TEXTJOIN("+",TRUE,_xlfn._xlws.FILTER(orderlinesTABLE[ItemName],OrderID=orderlinesTABLE[[#This Row],[OrderID]]))} -> Coffee+Egg Curry + Rice+Veg Sandwich+Gulab Jamun (2 pc) | T23: =orderlinesTABLE[[#This Row],[Profit]]/orderlinesTABLE[[#This Row],[LineNetAmount]] -> 0.47119247 | U23: =(orderlinesTABLE[[#This Row],[Qty]]*orderlinesTABLE[[#This Row],[UnitCost]]) -> 35.81 | W23: Q4> | Y23: count orders with any beverage item and paid via upi,counted by order
A24: O00010 | B24: DH9SDB | C24: 1 | D24: =VLOOKUP($B24,Menu!$A$1:$F$20,MATCH($D$1,Menu!$A$1:$F$1,0),0) -> 76.55 | E24: =VLOOKUP($B24,Menu!$A$1:$F$20,MATCH(OrderLines!E$1,Menu!$A$1:$F$1,0),0) -> Dessert | F24: =VLOOKUP($B24,Menu!$A$1:$F$20,MATCH(OrderLines!F$1,Menu!$A$1:$F$1,0),0) -> 38.23 | G24: =VLOOKUP($A24,Orders!$A$1:$H$361,MATCH($G$1,Orders!$A$1:$H$1,0),0) -> 45862 | H24: =VLOOKUP($A24,Orders!$A$1:$H$361,MATCH(OrderLines!$H$1,Orders!$A$1:$H$1,0),0) -> Plant 1 Canteen | I24: =VLOOKUP($A24,Orders!$A$1:$H$361,MATCH(OrderLines!$I$1,Orders!$A$1:$H$1,0),0) -> 0.04 | J24: =$C24*$D24*(1-$I24) -> 73.488 | K24: =TEXT($G24,"mmmm") -> July | L24: =VLOOKUP(OrderLines!$A24,Orders!$A$1:$H$361,MATCH(OrderLines!$L$1,Orders!$A$1:$H$1,0),0) -> Breakfast | M24: =VLOOKUP($A24,Orders!$A$1:$H$361,MATCH(OrderLines!$M$1,Orders!$A$1:$H$1,0),0) -> Card | N24: =IF(AND(COUNTIFS(OrderID,$A24,Category,"hot meal")>=1,COUNTIFS(OrderID,$A24,Category,"beverage")>=1),"Combo","Single") -> Combo | O24: {=IF((SUMPRODUCT((OrderID=OrderLines!$A24)*Qty*UnitPrice*DiscountPct))>40,"HighDisc","OK")} -> OK | P24: =(orderlinesTABLE[[#This Row],[UnitCost]]*orderlinesTABLE[[#This Row],[Qty]]) -> 38.23 | Q24: =(orderlinesTABLE[[#This Row],[LineNetAmount]]-orderlinesTABLE[[#This Row],[totalCOST]]) -> 35.258 | R24: =VLOOKUP($B24,Menu!$A$1:$F$20,MATCH(OrderLines!R$1,Menu!$A$1:$F$1,0),0) -> Gulab Jamun (2 pc) | S24: {=_xlfn.TEXTJOIN("+",TRUE,_xlfn._xlws.FILTER(orderlinesTABLE[ItemName],OrderID=orderlinesTABLE[[#This Row],[OrderID]]))} -> Coffee+Egg Curry + Rice+Veg Sandwich+Gulab Jamun (2 pc) | T24: =orderlinesTABLE[[#This Row],[Profit]]/orderlinesTABLE[[#This Row],[LineNetAmount]] -> 0.47977901 | U24: =(orderlinesTABLE[[#This Row],[Qty]]*orderlinesTABLE[[#This Row],[UnitCost]]) -> 38.23
A25: O00011 | B25: B0T0PV | C25: 1 | D25: =VLOOKUP($B25,Menu!$A$1:$F$20,MATCH($D$1,Menu!$A$1:$F$1,0),0) -> 28.43 | E25: =VLOOKUP($B25,Menu!$A$1:$F$20,MATCH(OrderLines!E$1,Menu!$A$1:$F$1,0),0) -> Beverage | F25: =VLOOKUP($B25,Menu!$A$1:$F$20,MATCH(OrderLines!F$1,Menu!$A$1:$F$1,0),0) -> 13.89 | G25: =VLOOKUP($A25,Orders!$A$1:$H$361,MATCH($G$1,Orders!$A$1:$H$1,0),0) -> 45860 | H25: =VLOOKUP($A25,Orders!$A$1:$H$361,MATCH(OrderLines!$H$1,Orders!$A$1:$H$1,0),0) -> Plant 2 Canteen | I25: =VLOOKUP($A25,Orders!$A$1:$H$361,MATCH(OrderLines!$I$1,Orders!$A$1:$H$1,0),0) -> 0.03 | J25: =$C25*$D25*(1-$I25) -> 27.5771 | K25: =TEXT($G25,"mmmm") -> July | L25: =VLOOKUP(OrderLines!$A25,Orders!$A$1:$H$361,MATCH(OrderLines!$L$1,Orders!$A$1:$H$1,0),0) -> Breakfast | M25: =VLOOKUP($A25,Orders!$A$1:$H$361,MATCH(OrderLines!$M$1,Orders!$A$1:$H$1,0),0) -> Cash | N25: =IF(AND(COUNTIFS(OrderID,$A25,Category,"hot meal")>=1,COUNTIFS(OrderID,$A25,Category,"beverage")>=1),"Combo","Single") -> Single | O25: {=IF((SUMPRODUCT((OrderID=OrderLines!$A25)*Qty*UnitPrice*DiscountPct))>40,"HighDisc","OK")} -> OK | P25: =(orderlinesTABLE[[#This Row],[UnitCost]]*orderlinesTABLE[[#This Row],[Qty]]) -> 13.89 | Q25: =(orderlinesTABLE[[#This Row],[LineNetAmount]]-orderlinesTABLE[[#This Row],[totalCOST]]) -> 13.6871 | R25: =VLOOKUP($B25,Menu!$A$1:$F$20,MATCH(OrderLines!R$1,Menu!$A$1:$F$1,0),0) -> Bottled Water | S25: {=_xlfn.TEXTJOIN("+",TRUE,_xlfn._xlws.FILTER(orderlinesTABLE[ItemName],OrderID=orderlinesTABLE[[#This Row],[OrderID]]))} -> Bottled Water | T25: =orderlinesTABLE[[#This Row],[Profit]]/orderlinesTABLE[[#This Row],[LineNetAmount]] -> 0.49632122 | U25: =(orderlinesTABLE[[#This Row],[Qty]]*orderlinesTABLE[[#This Row],[UnitCost]]) -> 13.89 | X25: WRONG WAY | Y25: {=COUNTA(_xlfn.UNIQUE(_xlfn._xlws.FILTER(OrderID,(Category="beverage")*(PaymentType="upi"))))} -> 70
A26: O00012 | B26: DFFYVN | C26: 1 | D26: =VLOOKUP($B26,Menu!$A$1:$F$20,MATCH($D$1,Menu!$A$1:$F$1,0),0) -> 54.2 | E26: =VLOOKUP($B26,Menu!$A$1:$F$20,MATCH(OrderLines!E$1,Menu!$A$1:$F$1,0),0) -> Dessert | F26: =VLOOKUP($B26,Menu!$A$1:$F$20,MATCH(OrderLines!F$1,Menu!$A$1:$F$1,0),0) -> 21.95 | G26: =VLOOKUP($A26,Orders!$A$1:$H$361,MATCH($G$1,Orders!$A$1:$H$1,0),0) -> 45839 | H26: =VLOOKUP($A26,Orders!$A$1:$H$361,MATCH(OrderLines!$H$1,Orders!$A$1:$H$1,0),0) -> Plant 2 Canteen | I26: =VLOOKUP($A26,Orders!$A$1:$H$361,MATCH(OrderLines!$I$1,Orders!$A$1:$H$1,0),0) -> 0.08 | J26: =$C26*$D26*(1-$I26) -> 49.864 | K26: =TEXT($G26,"mmmm") -> July | L26: =VLOOKUP(OrderLines!$A26,Orders!$A$1:$H$361,MATCH(OrderLines!$L$1,Orders!$A$1:$H$1,0),0) -> Lunch | M26: =VLOOKUP($A26,Orders!$A$1:$H$361,MATCH(OrderLines!$M$1,Orders!$A$1:$H$1,0),0) -> Card | N26: =IF(AND(COUNTIFS(OrderID,$A26,Category,"hot meal")>=1,COUNTIFS(OrderID,$A26,Category,"beverage")>=1),"Combo","Single") -> Single | O26: {=IF((SUMPRODUCT((OrderID=OrderLines!$A26)*Qty*UnitPrice*DiscountPct))>40,"HighDisc","OK")} -> OK | P26: =(orderlinesTABLE[[#This Row],[UnitCost]]*orderlinesTABLE[[#This Row],[Qty]]) -> 21.95 | Q26: =(orderlinesTABLE[[#This Row],[LineNetAmount]]-orderlinesTABLE[[#This Row],[totalCOST]]) -> 27.914 | R26: =VLOOKUP($B26,Menu!$A$1:$F$20,MATCH(OrderLines!R$1,Menu!$A$1:$F$1,0),0) -> Kheer Cup | S26: {=_xlfn.TEXTJOIN("+",TRUE,_xlfn._xlws.FILTER(orderlinesTABLE[ItemName],OrderID=orderlinesTABLE[[#This Row],[OrderID]]))} -> Kheer Cup+Poha | T26: =orderlinesTABLE[[#This Row],[Profit]]/orderlinesTABLE[[#This Row],[LineNetAmount]] -> 0.55980266 | U26: =(orderlinesTABLE[[#This Row],[Qty]]*orderlinesTABLE[[#This Row],[UnitCost]]) -> 21.95
A27: O00012 | B27: SHJ7XV | C27: 1 | D27: =VLOOKUP($B27,Menu!$A$1:$F$20,MATCH($D$1,Menu!$A$1:$F$1,0),0) -> 52.45 | E27: =VLOOKUP($B27,Menu!$A$1:$F$20,MATCH(OrderLines!E$1,Menu!$A$1:$F$1,0),0) -> Snack | F27: =VLOOKUP($B27,Menu!$A$1:$F$20,MATCH(OrderLines!F$1,Menu!$A$1:$F$1,0),0) -> 25.8 | G27: =VLOOKUP($A27,Orders!$A$1:$H$361,MATCH($G$1,Orders!$A$1:$H$1,0),0) -> 45839 | H27: =VLOOKUP($A27,Orders!$A$1:$H$361,MATCH(OrderLines!$H$1,Orders!$A$1:$H$1,0),0) -> Plant 2 Canteen | I27: =VLOOKUP($A27,Orders!$A$1:$H$361,MATCH(OrderLines!$I$1,Orders!$A$1:$H$1,0),0) -> 0.08 | J27: =$C27*$D27*(1-$I27) -> 48.254 | K27: =TEXT($G27,"mmmm") -> July | L27: =VLOOKUP(OrderLines!$A27,Orders!$A$1:$H$361,MATCH(OrderLines!$L$1,Orders!$A$1:$H$1,0),0) -> Lunch | M27: =VLOOKUP($A27,Orders!$A$1:$H$361,MATCH(OrderLines!$M$1,Orders!$A$1:$H$1,0),0) -> Card | N27: =IF(AND(COUNTIFS(OrderID,$A27,Category,"hot meal")>=1,COUNTIFS(OrderID,$A27,Category,"beverage")>=1),"Combo","Single") -> Single | O27: {=IF((SUMPRODUCT((OrderID=OrderLines!$A27)*Qty*UnitPrice*DiscountPct))>40,"HighDisc","OK")} -> OK | P27: =(orderlinesTABLE[[#This Row],[UnitCost]]*orderlinesTABLE[[#This Row],[Qty]]) -> 25.8 | Q27: =(orderlinesTABLE[[#This Row],[LineNetAmount]]-orderlinesTABLE[[#This Row],[totalCOST]]) -> 22.454 | R27: =VLOOKUP($B27,Menu!$A$1:$F$20,MATCH(OrderLines!R$1,Menu!$A$1:$F$1,0),0) -> Poha | S27: {=_xlfn.TEXTJOIN("+",TRUE,_xlfn._xlws.FILTER(orderlinesTABLE[ItemName],OrderID=orderlinesTABLE[[#This Row],[OrderID]]))} -> Kheer Cup+Poha | T27: =orderlinesTABLE[[#This Row],[Profit]]/orderlinesTABLE[[#This Row],[LineNetAmount]] -> 0.4653293 | U27: =(orderlinesTABLE[[#This Row],[Qty]]*orderlinesTABLE[[#This Row],[UnitCost]]) -> 25.8
A28: O00013 | B28: DH9SDB | C28: 3 | D28: =VLOOKUP($B28,Menu!$A$1:$F$20,MATCH($D$1,Menu!$A$1:$F$1,0),0) -> 76.55 | E28: =VLOOKUP($B28,Menu!$A$1:$F$20,MATCH(OrderLines!E$1,Menu!$A$1:$F$1,0),0) -> Dessert | F28: =VLOOKUP($B28,Menu!$A$1:$F$20,MATCH(OrderLines!F$1,Menu!$A$1:$F$1,0),0) -> 38.23 | G28: =VLOOKUP($A28,Orders!$A$1:$H$361,MATCH($G$1,Orders!$A$1:$H$1,0),0) -> 45880 | H28: =VLOOKUP($A28,Orders!$A$1:$H$361,MATCH(OrderLines!$H$1,Orders!$A$1:$H$1,0),0) -> Head Office Café | I28: =VLOOKUP($A28,Orders!$A$1:$H$361,MATCH(OrderLines!$I$1,Orders!$A$1:$H$1,0),0) -> 0.1 | J28: =$C28*$D28*(1-$I28) -> 206.685 | K28: =TEXT($G28,"mmmm") -> August | L28: =VLOOKUP(OrderLines!$A28,Orders!$A$1:$H$361,MATCH(OrderLines!$L$1,Orders!$A$1:$H$1,0),0) -> Breakfast | M28: =VLOOKUP($A28,Orders!$A$1:$H$361,MATCH(OrderLines!$M$1,Orders!$A$1:$H$1,0),0) -> UPI | N28: =IF(AND(COUNTIFS(OrderID,$A28,Category,"hot meal")>=1,COUNTIFS(OrderID,$A28,Category,"beverage")>=1),"Combo","Single") -> Combo | O28: {=IF((SUMPRODUCT((OrderID=OrderLines!$A28)*Qty*UnitPrice*DiscountPct))>40,"HighDisc","OK")} -> HighDisc | P28: =(orderlinesTABLE[[#This Row],[UnitCost]]*orderlinesTABLE[[#This Row],[Qty]]) -> 114.69 | Q28: =(orderlinesTABLE[[#This Row],[LineNetAmount]]-orderlinesTABLE[[#This Row],[totalCOST]]) -> 91.995 | R28: =VLOOKUP($B28,Menu!$A$1:$F$20,MATCH(OrderLines!R$1,Menu!$A$1:$F$1,0),0) -> Gulab Jamun (2 pc) | S28: {=_xlfn.TEXTJOIN("+",TRUE,_xlfn._xlws.FILTER(orderlinesTABLE[ItemName],OrderID=orderlinesTABLE[[#This Row],[OrderID]]))} -> Gulab Jamun (2 pc)+Tea+Brownie+Chicken Thali | T28: =orderlinesTABLE[[#This Row],[Profit]]/orderlinesTABLE[[#This Row],[LineNetAmount]] -> 0.44509761 | U28: =(orderlinesTABLE[[#This Row],[Qty]]*orderlinesTABLE[[#This Row],[UnitCost]]) -> 114.69
A29: O00013 | B29: BTIQJ7 | C29: 2 | D29: =VLOOKUP($B29,Menu!$A$1:$F$20,MATCH($D$1,Menu!$A$1:$F$1,0),0) -> 30.34 | E29: =VLOOKUP($B29,Menu!$A$1:$F$20,MATCH(OrderLines!E$1,Menu!$A$1:$F$1,0),0) -> Beverage | F29: =VLOOKUP($B29,Menu!$A$1:$F$20,MATCH(OrderLines!F$1,Menu!$A$1:$F$1,0),0) -> 14.18 | G29: =VLOOKUP($A29,Orders!$A$1:$H$361,MATCH($G$1,Orders!$A$1:$H$1,0),0) -> 45880 | H29: =VLOOKUP($A29,Orders!$A$1:$H$361,MATCH(OrderLines!$H$1,Orders!$A$1:$H$1,0),0) -> Head Office Café | I29: =VLOOKUP($A29,Orders!$A$1:$H$361,MATCH(OrderLines!$I$1,Orders!$A$1:$H$1,0),0) -> 0.1 | J29: =$C29*$D29*(1-$I29) -> 54.612 | K29: =TEXT($G29,"mmmm") -> August | L29: =VLOOKUP(OrderLines!$A29,Orders!$A$1:$H$361,MATCH(OrderLines!$L$1,Orders!$A$1:$H$1,0),0) -> Breakfast | M29: =VLOOKUP($A29,Orders!$A$1:$H$361,MATCH(OrderLines!$M$1,Orders!$A$1:$H$1,0),0) -> UPI | N29: =IF(AND(COUNTIFS(OrderID,$A29,Category,"hot meal")>=1,COUNTIFS(OrderID,$A29,Category,"beverage")>=1),"Combo","Single") -> Combo | O29: {=IF((SUMPRODUCT((OrderID=OrderLines!$A29)*Qty*UnitPrice*DiscountPct))>40,"HighDisc","OK")} -> HighDisc | P29: =(orderlinesTABLE[[#This Row],[UnitCost]]*orderlinesTABLE[[#This Row],[Qty]]) -> 28.36 | Q29: =(orderlinesTABLE[[#This Row],[LineNetAmount]]-orderlinesTABLE[[#This Row],[totalCOST]]) -> 26.252 | R29: =VLOOKUP($B29,Menu!$A$1:$F$20,MATCH(OrderLines!R$1,Menu!$A$1:$F$1,0),0) -> Tea | S29: {=_xlfn.TEXTJOIN("+",TRUE,_xlfn._xlws.FILTER(orderlinesTABLE[ItemName],OrderID=orderlinesTABLE[[#This Row],[OrderID]]))} -> Gulab Jamun (2 pc)+Tea+Brownie+Chicken Thali | T29: =orderlinesTABLE[[#This Row],[Profit]]/orderlinesTABLE[[#This Row],[LineNetAmount]] -> 0.48070021 | U29: =(orderlinesTABLE[[#This Row],[Qty]]*orderlinesTABLE[[#This Row],[UnitCost]]) -> 28.36 | W29: Q5> | Y29: Calculate avg ticket size by shift for july and august combined (avg order totals not line amounts)
A30: O00013 | B30: D9T84A | C30: 3 | D30: =VLOOKUP($B30,Menu!$A$1:$F$20,MATCH($D$1,Menu!$A$1:$F$1,0),0) -> 116.8 | E30: =VLOOKUP($B30,Menu!$A$1:$F$20,MATCH(OrderLines!E$1,Menu!$A$1:$F$1,0),0) -> Dessert | F30: =VLOOKUP($B30,Menu!$A$1:$F$20,MATCH(OrderLines!F$1,Menu!$A$1:$F$1,0),0) -> 48.97 | G30: =VLOOKUP($A30,Orders!$A$1:$H$361,MATCH($G$1,Orders!$A$1:$H$1,0),0) -> 45880 | H30: =VLOOKUP($A30,Orders!$A$1:$H$361,MATCH(OrderLines!$H$1,Orders!$A$1:$H$1,0),0) -> Head Office Café | I30: =VLOOKUP($A30,Orders!$A$1:$H$361,MATCH(OrderLines!$I$1,Orders!$A$1:$H$1,0),0) -> 0.1 | J30: =$C30*$D30*(1-$I30) -> 315.36 | K30: =TEXT($G30,"mmmm") -> August | L30: =VLOOKUP(OrderLines!$A30,Orders!$A$1:$H$361,MATCH(OrderLines!$L$1,Orders!$A$1:$H$1,0),0) -> Breakfast | M30: =VLOOKUP($A30,Orders!$A$1:$H$361,MATCH(OrderLines!$M$1,Orders!$A$1:$H$1,0),0) -> UPI | N30: =IF(AND(COUNTIFS(OrderID,$A30,Category,"hot meal")>=1,COUNTIFS(OrderID,$A30,Category,"beverage")>=1),"Combo","Single") -> Combo | O30: {=IF((SUMPRODUCT((OrderID=OrderLines!$A30)*Qty*UnitPrice*DiscountPct))>40,"HighDisc","OK")} -> HighDisc | P30: =(orderlinesTABLE[[#This Row],[UnitCost]]*orderlinesTABLE[[#This Row],[Qty]]) -> 146.91 | Q30: =(orderlinesTABLE[[#This Row],[LineNetAmount]]-orderlinesTABLE[[#This Row],[totalCOST]]) -> 168.45 | R30: =VLOOKUP($B30,Menu!$A$1:$F$20,MATCH(OrderLines!R$1,Menu!$A$1:$F$1,0),0) -> Brownie | S30: {=_xlfn.TEXTJOIN("+",TRUE,_xlfn._xlws.FILTER(orderlinesTABLE[ItemName],OrderID=orderlinesTABLE[[#This Row],[OrderID]]))} -> Gulab Jamun (2 pc)+Tea+Brownie+Chicken Thali | T30: =orderlinesTABLE[[#This Row],[Profit]]/orderlinesTABLE[[#This Row],[LineNetAmount]] -> 0.53415145 | U30: =(orderlinesTABLE[[#This Row],[Qty]]*orderlinesTABLE[[#This Row],[UnitCost]]) -> 146.91
A31: O00013 | B31: HDPBHS | C31: 1 | D31: =VLOOKUP($B31,Menu!$A$1:$F$20,MATCH($D$1,Menu!$A$1:$F$1,0),0) -> 256.91 | E31: =VLOOKUP($B31,Menu!$A$1:$F$20,MATCH(OrderLines!E$1,Menu!$A$1:$F$1,0),0) -> Hot Meal | F31: =VLOOKUP($B31,Menu!$A$1:$F$20,MATCH(OrderLines!F$1,Menu!$A$1:$F$1,0),0) -> 121.24 | G31: =VLOOKUP($A31,Orders!$A$1:$H$361,MATCH($G$1,Orders!$A$1:$H$1,0),0) -> 45880 | H31: =VLOOKUP($A31,Orders!$A$1:$H$361,MATCH(OrderLines!$H$1,Orders!$A$1:$H$1,0),0) -> Head Office Café | I31: =VLOOKUP($A31,Orders!$A$1:$H$361,MATCH(OrderLines!$I$1,Orders!$A$1:$H$1,0),0) -> 0.1 | J31: =$C31*$D31*(1-$I31) -> 231.219 | K31: =TEXT($G31,"mmmm") -> August | L31: =VLOOKUP(OrderLines!$A31,Orders!$A$1:$H$361,MATCH(OrderLines!$L$1,Orders!$A$1:$H$1,0),0) -> Breakfast | M31: =VLOOKUP($A31,Orders!$A$1:$H$361,MATCH(OrderLines!$M$1,Orders!$A$1:$H$1,0),0) -> UPI | N31: =IF(AND(COUNTIFS(OrderID,$A31,Category,"hot meal")>=1,COUNTIFS(OrderID,$A31,Category,"beverage")>=1),"Combo","Single") -> Combo | O31: {=IF((SUMPRODUCT((OrderID=OrderLines!$A31)*Qty*UnitPrice*DiscountPct))>40,"HighDisc","OK")} -> HighDisc | P31: =(orderlinesTABLE[[#This Row],[UnitCost]]*orderlinesTABLE[[#This Row],[Qty]]) -> 121.24 | Q31: =(orderlinesTABLE[[#This Row],[LineNetAmount]]-orderlinesTABLE[[#This Row],[totalCOST]]) -> 109.979 | R31: =VLOOKUP($B31,Menu!$A$1:$F$20,MATCH(OrderLines!R$1,Menu!$A$1:$F$1,0),0) -> Chicken Thali | S31: {=_xlfn.TEXTJOIN("+",TRUE,_xlfn._xlws.FILTER(orderlinesTABLE[ItemName],OrderID=orderlinesTABLE[[#This Row],[OrderID]]))} -> Gulab Jamun (2 pc)+Tea+Brownie+Chicken Thali | T31: =orderlinesTABLE[[#This Row],[Profit]]/orderlinesTABLE[[#This Row],[LineNetAmount]] -> 0.47564863 | U31: =(orderlinesTABLE[[#This Row],[Qty]]*orderlinesTABLE[[#This Row],[UnitCost]]) -> 121.24
A32: O00014 | B32: B0T0PV | C32: 1 | D32: =VLOOKUP($B32,Menu!$A$1:$F$20,MATCH($D$1,Menu!$A$1:$F$1,0),0) -> 28.43 | E32: =VLOOKUP($B32,Menu!$A$1:$F$20,MATCH(OrderLines!E$1,Menu!$A$1:$F$1,0),0) -> Beverage | F32: =VLOOKUP($B32,Menu!$A$1:$F$20,MATCH(OrderLines!F$1,Menu!$A$1:$F$1,0),0) -> 13.89 | G32: =VLOOKUP($A32,Orders!$A$1:$H$361,MATCH($G$1,Orders!$A$1:$H$1,0),0) -> 45854 | H32: =VLOOKUP($A32,Orders!$A$1:$H$361,MATCH(OrderLines!$H$1,Orders!$A$1:$H$1,0),0) -> Plant 1 Canteen | I32: =VLOOKUP($A32,Orders!$A$1:$H$361,MATCH(OrderLines!$I$1,Orders!$A$1:$H$1,0),0) -> 0.1 | J32: =$C32*$D32*(1-$I32) -> 25.587 | K32: =TEXT($G32,"mmmm") -> July | L32: =VLOOKUP(OrderLines!$A32,Orders!$A$1:$H$361,MATCH(OrderLines!$L$1,Orders!$A$1:$H$1,0),0) -> Breakfast | M32: =VLOOKUP($A32,Orders!$A$1:$H$361,MATCH(OrderLines!$M$1,Orders!$A$1:$H$1,0),0) -> Cash | N32: =IF(AND(COUNTIFS(OrderID,$A32,Category,"hot meal")>=1,COUNTIFS(OrderID,$A32,Category,"beverage")>=1),"Combo","Single") -> Single | O32: {=IF((SUMPRODUCT((OrderID=OrderLines!$A32)*Qty*UnitPrice*DiscountPct))>40,"HighDisc","OK")} -> OK | P32: =(orderlinesTABLE[[#This Row],[UnitCost]]*orderlinesTABLE[[#This Row],[Qty]]) -> 13.89 | Q32: =(orderlinesTABLE[[#This Row],[LineNetAmount]]-orderlinesTABLE[[#This Row],[totalCOST]]) -> 11.697 | R32: =VLOOKUP($B32,Menu!$A$1:$F$20,MATCH(OrderLines!R$1,Menu!$A$1:$F$1,0),0) -> Bottled Water | S32: {=_xlfn.TEXTJOIN("+",TRUE,_xlfn._xlws.FILTER(orderlinesTABLE[ItemName],OrderID=orderlinesTABLE[[#This Row],[OrderID]]))} -> Bottled Water+Gulab Jamun (2 pc)+Nimbu Pani | T32: =orderlinesTABLE[[#This Row],[Profit]]/orderlinesTABLE[[#This Row],[LineNetAmount]] -> 0.45714621 | U32: =(orderlinesTABLE[[#This Row],[Qty]]*orderlinesTABLE[[#This Row],[UnitCost]]) -> 13.89
A33: O00014 | B33: DH9SDB | C33: 2 | D33: =VLOOKUP($B33,Menu!$A$1:$F$20,MATCH($D$1,Menu!$A$1:$F$1,0),0) -> 76.55 | E33: =VLOOKUP($B33,Menu!$A$1:$F$20,MATCH(OrderLines!E$1,Menu!$A$1:$F$1,0),0) -> Dessert | F33: =VLOOKUP($B33,Menu!$A$1:$F$20,MATCH(OrderLines!F$1,Menu!$A$1:$F$1,0),0) -> 38.23 | G33: =VLOOKUP($A33,Orders!$A$1:$H$361,MATCH($G$1,Orders!$A$1:$H$1,0),0) -> 45854 | H33: =VLOOKUP($A33,Orders!$A$1:$H$361,MATCH(OrderLines!$H$1,Orders!$A$1:$H$1,0),0) -> Plant 1 Canteen | I33: =VLOOKUP($A33,Orders!$A$1:$H$361,MATCH(OrderLines!$I$1,Orders!$A$1:$H$1,0),0) -> 0.1 | J33: =$C33*$D33*(1-$I33) -> 137.79 | K33: =TEXT($G33,"mmmm") -> July | L33: =VLOOKUP(OrderLines!$A33,Orders!$A$1:$H$361,MATCH(OrderLines!$L$1,Orders!$A$1:$H$1,0),0) -> Breakfast | M33: =VLOOKUP($A33,Orders!$A$1:$H$361,MATCH(OrderLines!$M$1,Orders!$A$1:$H$1,0),0) -> Cash | N33: =IF(AND(COUNTIFS(OrderID,$A33,Category,"hot meal")>=1,COUNTIFS(OrderID,$A33,Category,"beverage")>=1),"Combo","Single") -> Single | O33: {=IF((SUMPRODUCT((OrderID=OrderLines!$A33)*Qty*UnitPrice*DiscountPct))>40,"HighDisc","OK")} -> OK | P33: =(orderlinesTABLE[[#This Row],[UnitCost]]*orderlinesTABLE[[#This Row],[Qty]]) -> 76.46 | Q33: =(orderlinesTABLE[[#This Row],[LineNetAmount]]-orderlinesTABLE[[#This Row],[totalCOST]]) -> 61.33 | R33: =VLOOKUP($B33,Menu!$A$1:$F$20,MATCH(OrderLines!R$1,Menu!$A$1:$F$1,0),0) -> Gulab Jamun (2 pc) | S33: {=_xlfn.TEXTJOIN("+",TRUE,_xlfn._xlws.FILTER(orderlinesTABLE[ItemName],OrderID=orderlinesTABLE[[#This Row],[OrderID]]))} -> Bottled Water+Gulab Jamun (2 pc)+Nimbu Pani | T33: =orderlinesTABLE[[#This Row],[Profit]]/orderlinesTABLE[[#This Row],[LineNetAmount]] -> 0.44509761 | U33: =(orderlinesTABLE[[#This Row],[Qty]]*orderlinesTABLE[[#This Row],[UnitCost]]) -> 76.46
A34: O00014 | B34: BXO6QJ | C34: 1 | D34: =VLOOKUP($B34,Menu!$A$1:$F$20,MATCH($D$1,Menu!$A$1:$F$1,0),0) -> 20.11 | E34: =VLOOKUP($B34,Menu!$A$1:$F$20,MATCH(OrderLines!E$1,Menu!$A$1:$F$1,0),0) -> Beverage | F34: =VLOOKUP($B34,Menu!$A$1:$F$20,MATCH(OrderLines!F$1,Menu!$A$1:$F$1,0),0) -> 8 | G34: =VLOOKUP($A34,Orders!$A$1:$H$361,MATCH($G$1,Orders!$A$1:$H$1,0),0) -> 45854 | H34: =VLOOKUP($A34,Orders!$A$1:$H$361,MATCH(OrderLines!$H$1,Orders!$A$1:$H$1,0),0) -> Plant 1 Canteen | I34: =VLOOKUP($A34,Orders!$A$1:$H$361,MATCH(OrderLines!$I$1,Orders!$A$1:$H$1,0),0) -> 0.1 | J34: =$C34*$D34*(1-$I34) -> 18.099 | K34: =TEXT($G34,"mmmm") -> July | L34: =VLOOKUP(OrderLines!$A34,Orders!$A$1:$H$361,MATCH(OrderLines!$L$1,Orders!$A$1:$H$1,0),0) -> Breakfast | M34: =VLOOKUP($A34,Orders!$A$1:$H$361,MATCH(OrderLines!$M$1,Orders!$A$1:$H$1,0),0) -> Cash | N34: =IF(AND(COUNTIFS(OrderID,$A34,Category,"hot meal")>=1,COUNTIFS(OrderID,$A34,Category,"beverage")>=1),"Combo","Single") -> Single | O34: {=IF((SUMPRODUCT((OrderID=OrderLines!$A34)*Qty*UnitPrice*DiscountPct))>40,"HighDisc","OK")} -> OK | P34: =(orderlinesTABLE[[#This Row],[UnitCost]]*orderlinesTABLE[[#This Row],[Qty]]) -> 8 | Q34: =(orderlinesTABLE[[#This Row],[LineNetAmount]]-orderlinesTABLE[[#This Row],[totalCOST]]) -> 10.099 | R34: =VLOOKUP($B34,Menu!$A$1:$F$20,MATCH(OrderLines!R$1,Menu!$A$1:$F$1,0),0) -> Nimbu Pani | S34: {=_xlfn.TEXTJOIN("+",TRUE,_xlfn._xlws.FILTER(orderlinesTABLE[ItemName],OrderID=orderlinesTABLE[[#This Row],[OrderID]]))} -> Bottled Water+Gulab Jamun (2 pc)+Nimbu Pani | T34: =orderlinesTABLE[[#This Row],[Profit]]/orderlinesTABLE[[#This Row],[LineNetAmount]] -> 0.55798663 | U34: =(orderlinesTABLE[[#This Row],[Qty]]*orderlinesTABLE[[#This Row],[UnitCost]]) -> 8 | W34: method 1> | Y34: shift | Z34: AverageTicketSize
A35: O00015 | B35: H3A3ZM | C35: 1 | D35: =VLOOKUP($B35,Menu!$A$1:$F$20,MATCH($D$1,Menu!$A$1:$F$1,0),0) -> 170.83 | E35: =VLOOKUP($B35,Menu!$A$1:$F$20,MATCH(OrderLines!E$1,Menu!$A$1:$F$1,0),0) -> Hot Meal | F35: =VLOOKUP($B35,Menu!$A$1:$F$20,MATCH(OrderLines!F$1,Menu!$A$1:$F$1,0),0) -> 74.07 | G35: =VLOOKUP($A35,Orders!$A$1:$H$361,MATCH($G$1,Orders!$A$1:$H$1,0),0) -> 45895 | H35: =VLOOKUP($A35,Orders!$A$1:$H$361,MATCH(OrderLines!$H$1,Orders!$A$1:$H$1,0),0) -> Head Office Café | I35: =VLOOKUP($A35,Orders!$A$1:$H$361,MATCH(OrderLines!$I$1,Orders!$A$1:$H$1,0),0) -> 0.03 | J35: =$C35*$D35*(1-$I35) -> 165.7051 | K35: =TEXT($G35,"mmmm") -> August | L35: =VLOOKUP(OrderLines!$A35,Orders!$A$1:$H$361,MATCH(OrderLines!$L$1,Orders!$A$1:$H$1,0),0) -> Lunch | M35: =VLOOKUP($A35,Orders!$A$1:$H$361,MATCH(OrderLines!$M$1,Orders!$A$1:$H$1,0),0) -> Cash | N35: =IF(AND(COUNTIFS(OrderID,$A35,Category,"hot meal")>=1,COUNTIFS(OrderID,$A35,Category,"beverage")>=1),"Combo","Single") -> Combo | O35: {=IF((SUMPRODUCT((OrderID=OrderLines!$A35)*Qty*UnitPrice*DiscountPct))>40,"HighDisc","OK")} -> OK | P35: =(orderlinesTABLE[[#This Row],[UnitCost]]*orderlinesTABLE[[#This Row],[Qty]]) -> 74.07 | Q35: =(orderlinesTABLE[[#This Row],[LineNetAmount]]-orderlinesTABLE[[#This Row],[totalCOST]]) -> 91.6351 | R35: =VLOOKUP($B35,Menu!$A$1:$F$20,MATCH(OrderLines!R$1,Menu!$A$1:$F$1,0),0) -> Paneer Butter Masala + Naan | S35: {=_xlfn.TEXTJOIN("+",TRUE,_xlfn._xlws.FILTER(orderlinesTABLE[ItemName],OrderID=orderlinesTABLE[[#This Row],[OrderID]]))} -> Paneer Butter Masala + Naan+Masala Chaas+Gulab Jamun (2 pc) | T35: =orderlinesTABLE[[#This Row],[Profit]]/orderlinesTABLE[[#This Row],[LineNetAmount]] -> 0.55300108 | U35: =(orderlinesTABLE[[#This Row],[Qty]]*orderlinesTABLE[[#This Row],[UnitCost]]) -> 74.07 | Y35: breakfast | Z35: {=(SUMIFS(LineNetAmount,Shift,$Y35))/COUNTA(_xlfn.UNIQUE(_xlfn._xlws.FILTER(OrderID,(Shift=$Y35))))} -> 360.57145
A36: O00015 | B36: BOC6UZ | C36: 3 | D36: =VLOOKUP($B36,Menu!$A$1:$F$20,MATCH($D$1,Menu!$A$1:$F$1,0),0) -> 32.98 | E36: =VLOOKUP($B36,Menu!$A$1:$F$20,MATCH(OrderLines!E$1,Menu!$A$1:$F$1,0),0) -> Beverage | F36: =VLOOKUP($B36,Menu!$A$1:$F$20,MATCH(OrderLines!F$1,Menu!$A$1:$F$1,0),0) -> 11.84 | G36: =VLOOKUP($A36,Orders!$A$1:$H$361,MATCH($G$1,Orders!$A$1:$H$1,0),0) -> 45895 | H36: =VLOOKUP($A36,Orders!$A$1:$H$361,MATCH(OrderLines!$H$1,Orders!$A$1:$H$1,0),0) -> Head Office Café | I36: =VLOOKUP($A36,Orders!$A$1:$H$361,MATCH(OrderLines!$I$1,Orders!$A$1:$H$1,0),0) -> 0.03 | J36: =$C36*$D36*(1-$I36) -> 95.9718 | K36: =TEXT($G36,"mmmm") -> August | L36: =VLOOKUP(OrderLines!$A36,Orders!$A$1:$H$361,MATCH(OrderLines!$L$1,Orders!$A$1:$H$1,0),0) -> Lunch | M36: =VLOOKUP($A36,Orders!$A$1:$H$361,MATCH(OrderLines!$M$1,Orders!$A$1:$H$1,0),0) -> Cash | N36: =IF(AND(COUNTIFS(OrderID,$A36,Category,"hot meal")>=1,COUNTIFS(OrderID,$A36,Category,"beverage")>=1),"Combo","Single") -> Combo | O36: {=IF((SUMPRODUCT((OrderID=OrderLines!$A36)*Qty*UnitPrice*DiscountPct))>40,"HighDisc","OK")} -> OK | P36: =(orderlinesTABLE[[#This Row],[UnitCost]]*orderlinesTABLE[[#This Row],[Qty]]) -> 35.52 | Q36: =(orderlinesTABLE[[#This Row],[LineNetAmount]]-orderlinesTABLE[[#This Row],[totalCOST]]) -> 60.4518 | R36: =VLOOKUP($B36,Menu!$A$1:$F$20,MATCH(OrderLines!R$1,Menu!$A$1:$F$1,0),0) -> Masala Chaas | S36: {=_xlfn.TEXTJOIN("+",TRUE,_xlfn._xlws.FILTER(orderlinesTABLE[ItemName],OrderID=orderlinesTABLE[[#This Row],[OrderID]]))} -> Paneer Butter Masala + Naan+Masala Chaas+Gulab Jamun (2 pc) | T36: =orderlinesTABLE[[#This Row],[Profit]]/orderlinesTABLE[[#This Row],[LineNetAmount]] -> 0.62989128 | U36: =(orderlinesTABLE[[#This Row],[Qty]]*orderlinesTABLE[[#This Row],[UnitCost]]) -> 35.52 | Y36: lunch | Z36: {=(SUMIFS(LineNetAmount,Shift,$Y36))/COUNTA(_xlfn.UNIQUE(_xlfn._xlws.FILTER(OrderID,(Shift=$Y36))))} -> 372.02587
A37: O00015 | B37: DH9SDB | C37: 2 | D37: =VLOOKUP($B37,Menu!$A$1:$F$20,MATCH($D$1,Menu!$A$1:$F$1,0),0) -> 76.55 | E37: =VLOOKUP($B37,Menu!$A$1:$F$20,MATCH(OrderLines!E$1,Menu!$A$1:$F$1,0),0) -> Dessert | F37: =VLOOKUP($B37,Menu!$A$1:$F$20,MATCH(OrderLines!F$1,Menu!$A$1:$F$1,0),0) -> 38.23 | G37: =VLOOKUP($A37,Orders!$A$1:$H$361,MATCH($G$1,Orders!$A$1:$H$1,0),0) -> 45895 | H37: =VLOOKUP($A37,Orders!$A$1:$H$361,MATCH(OrderLines!$H$1,Orders!$A$1:$H$1,0),0) -> Head Office Café | I37: =VLOOKUP($A37,Orders!$A$1:$H$361,MATCH(OrderLines!$I$1,Orders!$A$1:$H$1,0),0) -> 0.03 | J37: =$C37*$D37*(1-$I37) -> 148.507 | K37: =TEXT($G37,"mmmm") -> August | L37: =VLOOKUP(OrderLines!$A37,Orders!$A$1:$H$361,MATCH(OrderLines!$L$1,Orders!$A$1:$H$1,0),0) -> Lunch | M37: =VLOOKUP($A37,Orders!$A$1:$H$361,MATCH(OrderLines!$M$1,Orders!$A$1:$H$1,0),0) -> Cash | N37: =IF(AND(COUNTIFS(OrderID,$A37,Category,"hot meal")>=1,COUNTIFS(OrderID,$A37,Category,"beverage")>=1),"Combo","Single") -> Combo | O37: {=IF((SUMPRODUCT((OrderID=OrderLines!$A37)*Qty*UnitPrice*DiscountPct))>40,"HighDisc","OK")} -> OK | P37: =(orderlinesTABLE[[#This Row],[UnitCost]]*orderlinesTABLE[[#This Row],[Qty]]) -> 76.46 | Q37: =(orderlinesTABLE[[#This Row],[LineNetAmount]]-orderlinesTABLE[[#This Row],[totalCOST]]) -> 72.047 | R37: =VLOOKUP($B37,Menu!$A$1:$F$20,MATCH(OrderLines!R$1,Menu!$A$1:$F$1,0),0) -> Gulab Jamun (2 pc) | S37: {=_xlfn.TEXTJOIN("+",TRUE,_xlfn._xlws.FILTER(orderlinesTABLE[ItemName],OrderID=orderlinesTABLE[[#This Row],[OrderID]]))} -> Paneer Butter Masala + Naan+Masala Chaas+Gulab Jamun (2 pc) | T37: =orderlinesTABLE[[#This Row],[Profit]]/orderlinesTABLE[[#This Row],[LineNetAmount]] -> 0.48514211 | U37: =(orderlinesTABLE[[#This Row],[Qty]]*orderlinesTABLE[[#This Row],[UnitCost]]) -> 76.46 | Y37: dinner | Z37: {=(SUMIFS(LineNetAmount,Shift,$Y37))/COUNTA(_xlfn.UNIQUE(_xlfn._xlws.FILTER(OrderID,(Shift=$Y37))))} -> 378.80541
A38: O00016 | B38: DYTJXE | C38: 1 | D38: =VLOOKUP($B38,Menu!$A$1:$F$20,MATCH($D$1,Menu!$A$1:$F$1,0),0) -> 57.07 | E38: =VLOOKUP($B38,Menu!$A$1:$F$20,MATCH(OrderLines!E$1,Menu!$A$1:$F$1,0),0) -> Dessert | F38: =VLOOKUP($B38,Menu!$A$1:$F$20,MATCH(OrderLines!F$1,Menu!$A$1:$F$1,0),0) -> 29.14 | G38: =VLOOKUP($A38,Orders!$A$1:$H$361,MATCH($G$1,Orders!$A$1:$H$1,0),0) -> 45844 | H38: =VLOOKUP($A38,Orders!$A$1:$H$361,MATCH(OrderLines!$H$1,Orders!$A$1:$H$1,0),0) -> Plant 1 Canteen | I38: =VLOOKUP($A38,Orders!$A$1:$H$361,MATCH(OrderLines!$I$1,Orders!$A$1:$H$1,0),0) -> 0.05 | J38: =$C38*$D38*(1-$I38) -> 54.2165 | K38: =TEXT($G38,"mmmm") -> July | L38: =VLOOKUP(OrderLines!$A38,Orders!$A$1:$H$361,MATCH(OrderLines!$L$1,Orders!$A$1:$H$1,0),0) -> Dinner | M38: =VLOOKUP($A38,Orders!$A$1:$H$361,MATCH(OrderLines!$M$1,Orders!$A$1:$H$1,0),0) -> Card | N38: =IF(AND(COUNTIFS(OrderID,$A38,Category,"hot meal")>=1,COUNTIFS(OrderID,$A38,Category,"beverage")>=1),"Combo","Single") -> Single | O38: {=IF((SUMPRODUCT((OrderID=OrderLines!$A38)*Qty*UnitPrice*DiscountPct))>40,"HighDisc","OK")} -> OK | P38: =(orderlinesTABLE[[#This Row],[UnitCost]]*orderlinesTABLE[[#This Row],[Qty]]) -> 29.14 | Q38: =(orderlinesTABLE[[#This Row],[LineNetAmount]]-orderlinesTABLE[[#This Row],[totalCOST]]) -> 25.0765 | R38: =VLOOKUP($B38,Menu!$A$1:$F$20,MATCH(OrderLines!R$1,Menu!$A$1:$F$1,0),0) -> Fruit Cup | S38: {=_xlfn.TEXTJOIN("+",TRUE,_xlfn._xlws.FILTER(orderlinesTABLE[ItemName],OrderID=orderlinesTABLE[[#This Row],[OrderID]]))} -> Fruit Cup+Veg Sandwich+Poha+Veg Thali | T38: =orderlinesTABLE[[#This Row],[Profit]]/orderlinesTABLE[[#This Row],[LineNetAmount]] -> 0.46252525 | U38: =(orderlinesTABLE[[#This Row],[Qty]]*orderlinesTABLE[[#This Row],[UnitCost]]) -> 29.14
A39: O00016 | B39: SCKW5N | C39: 1 | D39: =VLOOKUP($B39,Menu!$A$1:$F$20,MATCH($D$1,Menu!$A$1:$F$1,0),0) -> 70.54 | E39: =VLOOKUP($B39,Menu!$A$1:$F$20,MATCH(OrderLines!E$1,Menu!$A$1:$F$1,0),0) -> Snack | F39: =VLOOKUP($B39,Menu!$A$1:$F$20,MATCH(OrderLines!F$1,Menu!$A$1:$F$1,0),0) -> 35.81 | G39: =VLOOKUP($A39,Orders!$A$1:$H$361,MATCH($G$1,Orders!$A$1:$H$1,0),0) -> 45844 | H39: =VLOOKUP($A39,Orders!$A$1:$H$361,MATCH(OrderLines!$H$1,Orders!$A$1:$H$1,0),0) -> Plant 1 Canteen | I39: =VLOOKUP($A39,Orders!$A$1:$H$361,MATCH(OrderLines!$I$1,Orders!$A$1:$H$1,0),0) -> 0.05 | J39: =$C39*$D39*(1-$I39) -> 67.013 | K39: =TEXT($G39,"mmmm") -> July | L39: =VLOOKUP(OrderLines!$A39,Orders!$A$1:$H$361,MATCH(OrderLines!$L$1,Orders!$A$1:$H$1,0),0) -> Dinner | M39: =VLOOKUP($A39,Orders!$A$1:$H$361,MATCH(OrderLines!$M$1,Orders!$A$1:$H$1,0),0) -> Card | N39: =IF(AND(COUNTIFS(OrderID,$A39,Category,"hot meal")>=1,COUNTIFS(OrderID,$A39,Category,"beverage")>=1),"Combo","Single") -> Single | O39: {=IF((SUMPRODUCT((OrderID=OrderLines!$A39)*Qty*UnitPrice*DiscountPct))>40,"HighDisc","OK")} -> OK | P39: =(orderlinesTABLE[[#This Row],[UnitCost]]*orderlinesTABLE[[#This Row],[Qty]]) -> 35.81 | Q39: =(orderlinesTABLE[[#This Row],[LineNetAmount]]-orderlinesTABLE[[#This Row],[totalCOST]]) -> 31.203 | R39: =VLOOKUP($B39,Menu!$A$1:$F$20,MATCH(OrderLines!R$1,Menu!$A$1:$F$1,0),0) -> Veg Sandwich | S39: {=_xlfn.TEXTJOIN("+",TRUE,_xlfn._xlws.FILTER(orderlinesTABLE[ItemName],OrderID=orderlinesTABLE[[#This Row],[OrderID]]))} -> Fruit Cup+Veg Sandwich+Poha+Veg Thali | T39: =orderlinesTABLE[[#This Row],[Profit]]/orderlinesTABLE[[#This Row],[LineNetAmount]] -> 0.46562607 | U39: =(orderlinesTABLE[[#This Row],[Qty]]*orderlinesTABLE[[#This Row],[UnitCost]]) -> 35.81
A40: O00016 | B40: SHJ7XV | C40: 3 | D40: =VLOOKUP($B40,Menu!$A$1:$F$20,MATCH($D$1,Menu!$A$1:$F$1,0),0) -> 52.45 | E40: =VLOOKUP($B40,Menu!$A$1:$F$20,MATCH(OrderLines!E$1,Menu!$A$1:$F$1,0),0) -> Snack | F40: =VLOOKUP($B40,Menu!$A$1:$F$20,MATCH(OrderLines!F$1,Menu!$A$1:$F$1,0),0) -> 25.8 | G40: =VLOOKUP($A40,Orders!$A$1:$H$361,MATCH($G$1,Orders!$A$1:$H$1,0),0) -> 45844 | H40: =VLOOKUP($A40,Orders!$A$1:$H$361,MATCH(OrderLines!$H$1,Orders!$A$1:$H$1,0),0) -> Plant 1 Canteen | I40: =VLOOKUP($A40,Orders!$A$1:$H$361,MATCH(OrderLines!$I$1,Orders!$A$1:$H$1,0),0) -> 0.05 | J40: =$C40*$D40*(1-$I40) -> 149.4825 | K40: =TEXT($G40,"mmmm") -> July | L40: =VLOOKUP(OrderLines!$A40,Orders!$A$1:$H$361,MATCH(OrderLines!$L$1,Orders!$A$1:$H$1,0),0) -> Dinner | M40: =VLOOKUP($A40,Orders!$A$1:$H$361,MATCH(OrderLines!$M$1,Orders!$A$1:$H$1,0),0) -> Card | N40: =IF(AND(COUNTIFS(OrderID,$A40,Category,"hot meal")>=1,COUNTIFS(OrderID,$A40,Category,"beverage")>=1),"Combo","Single") -> Single | O40: {=IF((SUMPRODUCT((OrderID=OrderLines!$A40)*Qty*UnitPrice*DiscountPct))>40,"HighDisc","OK")} -> OK | P40: =(orderlinesTABLE[[#This Row],[UnitCost]]*orderlinesTABLE[[#This Row],[Qty]]) -> 77.4 | Q40: =(orderlinesTABLE[[#This Row],[LineNetAmount]]-orderlinesTABLE[[#This Row],[totalCOST]]) -> 72.0825 | R40: =VLOOKUP($B40,Menu!$A$1:$F$20,MATCH(OrderLines!R$1,Menu!$A$1:$F$1,0),0) -> Poha | S40: {=_xlfn.TEXTJOIN("+",TRUE,_xlfn._xlws.FILTER(orderlinesTABLE[ItemName],OrderID=orderlinesTABLE[[#This Row],[OrderID]]))} -> Fruit Cup+Veg Sandwich+Poha+Veg Thali | T40: =orderlinesTABLE[[#This Row],[Profit]]/orderlinesTABLE[[#This Row],[LineNetAmount]] -> 0.48221364 | U40: =(orderlinesTABLE[[#This Row],[Qty]]*orderlinesTABLE[[#This Row],[UnitCost]]) -> 77.4
A41: O00016 | B41: HXAJI0 | C41: 1 | D41: =VLOOKUP($B41,Menu!$A$1:$F$20,MATCH($D$1,Menu!$A$1:$F$1,0),0) -> 227.61 | E41: =VLOOKUP($B41,Menu!$A$1:$F$20,MATCH(OrderLines!E$1,Menu!$A$1:$F$1,0),0) -> Hot Meal | F41: =VLOOKUP($B41,Menu!$A$1:$F$20,MATCH(OrderLines!F$1,Menu!$A$1:$F$1,0),0) -> 96.22 | G41: =VLOOKUP($A41,Orders!$A$1:$H$361,MATCH($G$1,Orders!$A$1:$H$1,0),0) -> 45844 | H41: =VLOOKUP($A41,Orders!$A$1:$H$361,MATCH(OrderLines!$H$1,Orders!$A$1:$H$1,0),0) -> Plant 1 Canteen | I41: =VLOOKUP($A41,Orders!$A$1:$H$361,MATCH(OrderLines!$I$1,Orders!$A$1:$H$1,0),0) -> 0.05 | J41: =$C41*$D41*(1-$I41) -> 216.2295 | K41: =TEXT($G41,"mmmm") -> July | L41: =VLOOKUP(OrderLines!$A41,Orders!$A$1:$H$361,MATCH(OrderLines!$L$1,Orders!$A$1:$H$1,0),0) -> Dinner | M41: =VLOOKUP($A41,Orders!$A$1:$H$361,MATCH(OrderLines!$M$1,Orders!$A$1:$H$1,0),0) -> Card | N41: =IF(AND(COUNTIFS(OrderID,$A41,Category,"hot meal")>=1,COUNTIFS(OrderID,$A41,Category,"beverage")>=1),"Combo","Single") -> Single | O41: {=IF((SUMPRODUCT((OrderID=OrderLines!$A41)*Qty*UnitPrice*DiscountPct))>40,"HighDisc","OK")} -> OK | P41: =(orderlinesTABLE[[#This Row],[UnitCost]]*orderlinesTABLE[[#This Row],[Qty]]) -> 96.22 | Q41: =(orderlinesTABLE[[#This Row],[LineNetAmount]]-orderlinesTABLE[[#This Row],[totalCOST]]) -> 120.0095 | R41: =VLOOKUP($B41,Menu!$A$1:$F$20,MATCH(OrderLines!R$1,Menu!$A$1:$F$1,0),0) -> Veg Thali | S41: {=_xlfn.TEXTJOIN("+",TRUE,_xlfn._xlws.FILTER(orderlinesTABLE[ItemName],OrderID=orderlinesTABLE[[#This Row],[OrderID]]))} -> Fruit Cup+Veg Sandwich+Poha+Veg Thali | T41: =orderlinesTABLE[[#This Row],[Profit]]/orderlinesTABLE[[#This Row],[LineNetAmount]] -> 0.55500984 | U41: =(orderlinesTABLE[[#This Row],[Qty]]*orderlinesTABLE[[#This Row],[UnitCost]]) -> 96.22 | W41: method2> | Y41: Row Labels | Z41: Distinct Count of OrderID | AA41: Sum of LineNetAmount | AB41: AverageTicketSize
A42: O00017 | B42: BOC6UZ | C42: 1 | D42: =VLOOKUP($B42,Menu!$A$1:$F$20,MATCH($D$1,Menu!$A$1:$F$1,0),0) -> 32.98 | E42: =VLOOKUP($B42,Menu!$A$1:$F$20,MATCH(OrderLines!E$1,Menu!$A$1:$F$1,0),0) -> Beverage | F42: =VLOOKUP($B42,Menu!$A$1:$F$20,MATCH(OrderLines!F$1,Menu!$A$1:$F$1,0),0) -> 11.84 | G42: =VLOOKUP($A42,Orders!$A$1:$H$361,MATCH($G$1,Orders!$A$1:$H$1,0),0) -> 45890 | H42: =VLOOKUP($A42,Orders!$A$1:$H$361,MATCH(OrderLines!$H$1,Orders!$A$1:$H$1,0),0) -> Plant 1 Canteen | I42: =VLOOKUP($A42,Orders!$A$1:$H$361,MATCH(OrderLines!$I$1,Orders!$A$1:$H$1,0),0) -> 0.07 | J42: =$C42*$D42*(1-$I42) -> 30.6714 | K42: =TEXT($G42,"mmmm") -> August | L42: =VLOOKUP(OrderLines!$A42,Orders!$A$1:$H$361,MATCH(OrderLines!$L$1,Orders!$A$1:$H$1,0),0) -> Dinner | M42: =VLOOKUP($A42,Orders!$A$1:$H$361,MATCH(OrderLines!$M$1,Orders!$A$1:$H$1,0),0) -> UPI | N42: =IF(AND(COUNTIFS(OrderID,$A42,Category,"hot meal")>=1,COUNTIFS(OrderID,$A42,Category,"beverage")>=1),"Combo","Single") -> Single | O42: {=IF((SUMPRODUCT((OrderID=OrderLines!$A42)*Qty*UnitPrice*DiscountPct))>40,"HighDisc","OK")} -> OK | P42: =(orderlinesTABLE[[#This Row],[UnitCost]]*orderlinesTABLE[[#This Row],[Qty]]) -> 11.84 | Q42: =(orderlinesTABLE[[#This Row],[LineNetAmount]]-orderlinesTABLE[[#This Row],[totalCOST]]) -> 18.8314 | R42: =VLOOKUP($B42,Menu!$A$1:$F$20,MATCH(OrderLines!R$1,Menu!$A$1:$F$1,0),0) -> Masala Chaas | S42: {=_xlfn.TEXTJOIN("+",TRUE,_xlfn._xlws.FILTER(orderlinesTABLE[ItemName],OrderID=orderlinesTABLE[[#This Row],[OrderID]]))} -> Masala Chaas | T42: =orderlinesTABLE[[#This Row],[Profit]]/orderlinesTABLE[[#This Row],[LineNetAmount]] -> 0.61397263 | U42: =(orderlinesTABLE[[#This Row],[Qty]]*orderlinesTABLE[[#This Row],[UnitCost]]) -> 11.84 | Y42: Breakfast | Z42: 177 | AA42: 63821.147 | AB42: =(GETPIVOTDATA("[Measures].[Sum of LineNetAmount]",$Y$41,"[Range].[Shift]","[Range].[Shift].&[Breakfast]")/GETPIVOTDATA("[Measures].[Distinct Count of OrderID]",$Y$41,"[Range].[Shift]","[Range].[Shift].&[Breakfast]")) -> 360.57145
A43: O00018 | B43: D9T84A | C43: 1 | D43: =VLOOKUP($B43,Menu!$A$1:$F$20,MATCH($D$1,Menu!$A$1:$F$1,0),0) -> 116.8 | E43: =VLOOKUP($B43,Menu!$A$1:$F$20,MATCH(OrderLines!E$1,Menu!$A$1:$F$1,0),0) -> Dessert | F43: =VLOOKUP($B43,Menu!$A$1:$F$20,MATCH(OrderLines!F$1,Menu!$A$1:$F$1,0),0) -> 48.97 | G43: =VLOOKUP($A43,Orders!$A$1:$H$361,MATCH($G$1,Orders!$A$1:$H$1,0),0) -> 45857 | H43: =VLOOKUP($A43,Orders!$A$1:$H$361,MATCH(OrderLines!$H$1,Orders!$A$1:$H$1,0),0) -> Plant 1 Canteen | I43: =VLOOKUP($A43,Orders!$A$1:$H$361,MATCH(OrderLines!$I$1,Orders!$A$1:$H$1,0),0) -> 0.1 | J43: =$C43*$D43*(1-$I43) -> 105.12 | K43: =TEXT($G43,"mmmm") -> July | L43: =VLOOKUP(OrderLines!$A43,Orders!$A$1:$H$361,MATCH(OrderLines!$L$1,Orders!$A$1:$H$1,0),0) -> Breakfast | M43: =VLOOKUP($A43,Orders!$A$1:$H$361,MATCH(OrderLines!$M$1,Orders!$A$1:$H$1,0),0) -> Cash | N43: =IF(AND(COUNTIFS(OrderID,$A43,Category,"hot meal")>=1,COUNTIFS(OrderID,$A43,Category,"beverage")>=1),"Combo","Single") -> Single | O43: {=IF((SUMPRODUCT((OrderID=OrderLines!$A43)*Qty*UnitPrice*DiscountPct))>40,"HighDisc","OK")} -> OK | P43: =(orderlinesTABLE[[#This Row],[UnitCost]]*orderlinesTABLE[[#This Row],[Qty]]) -> 48.97 | Q43: =(orderlinesTABLE[[#This Row],[LineNetAmount]]-orderlinesTABLE[[#This Row],[totalCOST]]) -> 56.15 | R43: =VLOOKUP($B43,Menu!$A$1:$F$20,MATCH(OrderLines!R$1,Menu!$A$1:$F$1,0),0) -> Brownie | S43: {=_xlfn.TEXTJOIN("+",TRUE,_xlfn._xlws.FILTER(orderlinesTABLE[ItemName],OrderID=orderlinesTABLE[[#This Row],[OrderID]]))} -> Brownie+Masala Chaas | T43: =orderlinesTABLE[[#This Row],[Profit]]/orderlinesTABLE[[#This Row],[LineNetAmount]] -> 0.53415145 | U43: =(orderlinesTABLE[[#This Row],[Qty]]*orderlinesTABLE[[#This Row],[UnitCost]]) -> 48.97 | Y43: Dinner | Z43: 110 | AA43: 41668.595 | AB43: =(GETPIVOTDATA("[Measures].[Sum of LineNetAmount]",$Y$41,"[Range].[Shift]","[Range].[Shift].&[Dinner]")/GETPIVOTDATA("[Measures].[Distinct Count of OrderID]",$Y$41,"[Range].[Shift]","[Range].[Shift].&[Dinner]")) -> 378.80541
A44: O00018 | B44: BOC6UZ | C44: 2 | D44: =VLOOKUP($B44,Menu!$A$1:$F$20,MATCH($D$1,Menu!$A$1:$F$1,0),0) -> 32.98 | E44: =VLOOKUP($B44,Menu!$A$1:$F$20,MATCH(OrderLines!E$1,Menu!$A$1:$F$1,0),0) -> Beverage | F44: =VLOOKUP($B44,Menu!$A$1:$F$20,MATCH(OrderLines!F$1,Menu!$A$1:$F$1,0),0) -> 11.84 | G44: =VLOOKUP($A44,Orders!$A$1:$H$361,MATCH($G$1,Orders!$A$1:$H$1,0),0) -> 45857 | H44: =VLOOKUP($A44,Orders!$A$1:$H$361,MATCH(OrderLines!$H$1,Orders!$A$1:$H$1,0),0) -> Plant 1 Canteen | I44: =VLOOKUP($A44,Orders!$A$1:$H$361,MATCH(OrderLines!$I$1,Orders!$A$1:$H$1,0),0) -> 0.1 | J44: =$C44*$D44*(1-$I44) -> 59.364 | K44: =TEXT($G44,"mmmm") -> July | L44: =VLOOKUP(OrderLines!$A44,Orders!$A$1:$H$361,MATCH(OrderLines!$L$1,Orders!$A$1:$H$1,0),0) -> Breakfast | M44: =VLOOKUP($A44,Orders!$A$1:$H$361,MATCH(OrderLines!$M$1,Orders!$A$1:$H$1,0),0) -> Cash | N44: =IF(AND(COUNTIFS(OrderID,$A44,Category,"hot meal")>=1,COUNTIFS(OrderID,$A44,Category,"beverage")>=1),"Combo","Single") -> Single | O44: {=IF((SUMPRODUCT((OrderID=OrderLines!$A44)*Qty*UnitPrice*DiscountPct))>40,"HighDisc","OK")} -> OK | P44: =(orderlinesTABLE[[#This Row],[UnitCost]]*orderlinesTABLE[[#This Row],[Qty]]) -> 23.68 | Q44: =(orderlinesTABLE[[#This Row],[LineNetAmount]]-orderlinesTABLE[[#This Row],[totalCOST]]) -> 35.684 | R44: =VLOOKUP($B44,Menu!$A$1:$F$20,MATCH(OrderLines!R$1,Menu!$A$1:$F$1,0),0) -> Masala Chaas | S44: {=_xlfn.TEXTJOIN("+",TRUE,_xlfn._xlws.FILTER(orderlinesTABLE[ItemName],OrderID=orderlinesTABLE[[#This Row],[OrderID]]))} -> Brownie+Masala Chaas | T44: =orderlinesTABLE[[#This Row],[Profit]]/orderlinesTABLE[[#This Row],[LineNetAmount]] -> 0.60110505 | U44: =(orderlinesTABLE[[#This Row],[Qty]]*orderlinesTABLE[[#This Row],[UnitCost]]) -> 23.68 | Y44: Lunch | Z44: 73 | AA44: 27157.888 | AB44: =(GETPIVOTDATA("[Measures].[Sum of LineNetAmount]",$Y$41,"[Range].[Shift]","[Range].[Shift].&[Lunch]")/GETPIVOTDATA("[Measures].[Distinct Count of OrderID]",$Y$41,"[Range].[Shift]","[Range].[Shift].&[Lunch]")) -> 372.02587
A45: O00019 | B45: HUZZPQ | C45: 1 | D45: =VLOOKUP($B45,Menu!$A$1:$F$20,MATCH($D$1,Menu!$A$1:$F$1,0),0) -> 146.4 | E45: =VLOOKUP($B45,Menu!$A$1:$F$20,MATCH(OrderLines!E$1,Menu!$A$1:$F$1,0),0) -> Hot Meal | F45: =VLOOKUP($B45,Menu!$A$1:$F$20,MATCH(OrderLines!F$1,Menu!$A$1:$F$1,0),0) -> 80.92 | G45: =VLOOKUP($A45,Orders!$A$1:$H$361,MATCH($G$1,Orders!$A$1:$H$1,0),0) -> 45878 | H45: =VLOOKUP($A45,Orders!$A$1:$H$361,MATCH(OrderLines!$H$1,Orders!$A$1:$H$1,0),0) -> Plant 1 Canteen | I45: =VLOOKUP($A45,Orders!$A$1:$H$361,MATCH(OrderLines!$I$1,Orders!$A$1:$H$1,0),0) -> 0.04 | J45: =$C45*$D45*(1-$I45) -> 140.544 | K45: =TEXT($G45,"mmmm") -> August | L45: =VLOOKUP(OrderLines!$A45,Orders!$A$1:$H$361,MATCH(OrderLines!$L$1,Orders!$A$1:$H$1,0),0) -> Breakfast | M45: =VLOOKUP($A45,Orders!$A$1:$H$361,MATCH(OrderLines!$M$1,Orders!$A$1:$H$1,0),0) -> Cash | N45: =IF(AND(COUNTIFS(OrderID,$A45,Category,"hot meal")>=1,COUNTIFS(OrderID,$A45,Category,"beverage")>=1),"Combo","Single") -> Single | O45: {=IF((SUMPRODUCT((OrderID=OrderLines!$A45)*Qty*UnitPrice*DiscountPct))>40,"HighDisc","OK")} -> OK | P45: =(orderlinesTABLE[[#This Row],[UnitCost]]*orderlinesTABLE[[#This Row],[Qty]]) -> 80.92 | Q45: =(orderlinesTABLE[[#This Row],[LineNetAmount]]-orderlinesTABLE[[#This Row],[totalCOST]]) -> 59.624 | R45: =VLOOKUP($B45,Menu!$A$1:$F$20,MATCH(OrderLines!R$1,Menu!$A$1:$F$1,0),0) -> Rajma Chawal | S45: {=_xlfn.TEXTJOIN("+",TRUE,_xlfn._xlws.FILTER(orderlinesTABLE[ItemName],OrderID=orderlinesTABLE[[#This Row],[OrderID]]))} -> Rajma Chawal+Veg Sandwich+Chicken Thali | T45: =orderlinesTABLE[[#This Row],[Profit]]/orderlinesTABLE[[#This Row],[LineNetAmount]] -> 0.42423725 | U45: =(orderlinesTABLE[[#This Row],[Qty]]*orderlinesTABLE[[#This Row],[UnitCost]]) -> 80.92 | Y45: Grand Total | Z45: 360 | AA45: 132647.63
A46: O00019 | B46: SCKW5N | C46: 1 | D46: =VLOOKUP($B46,Menu!$A$1:$F$20,MATCH($D$1,Menu!$A$1:$F$1,0),0) -> 70.54 | E46: =VLOOKUP($B46,Menu!$A$1:$F$20,MATCH(OrderLines!E$1,Menu!$A$1:$F$1,0),0) -> Snack | F46: =VLOOKUP($B46,Menu!$A$1:$F$20,MATCH(OrderLines!F$1,Menu!$A$1:$F$1,0),0) -> 35.81 | G46: =VLOOKUP($A46,Orders!$A$1:$H$361,MATCH($G$1,Orders!$A$1:$H$1,0),0) -> 45878 | H46: =VLOOKUP($A46,Orders!$A$1:$H$361,MATCH(OrderLines!$H$1,Orders!$A$1:$H$1,0),0) -> Plant 1 Canteen | I46: =VLOOKUP($A46,Orders!$A$1:$H$361,MATCH(OrderLines!$I$1,Orders!$A$1:$H$1,0),0) -> 0.04 | J46: =$C46*$D46*(1-$I46) -> 67.7184 | K46: =TEXT($G46,"mmmm") -> August | L46: =VLOOKUP(OrderLines!$A46,Orders!$A$1:$H$361,MATCH(OrderLines!$L$1,Orders!$A$1:$H$1,0),0) -> Breakfast | M46: =VLOOKUP($A46,Orders!$A$1:$H$361,MATCH(OrderLines!$M$1,Orders!$A$1:$H$1,0),0) -> Cash | N46: =IF(AND(COUNTIFS(OrderID,$A46,Category,"hot meal")>=1,COUNTIFS(OrderID,$A46,Category,"beverage")>=1),"Combo","Single") -> Single | O46: {=IF((SUMPRODUCT((OrderID=OrderLines!$A46)*Qty*UnitPrice*DiscountPct))>40,"HighDisc","OK")} -> OK | P46: =(orderlinesTABLE[[#This Row],[UnitCost]]*orderlinesTABLE[[#This Row],[Qty]]) -> 35.81 | Q46: =(orderlinesTABLE[[#This Row],[LineNetAmount]]-orderlinesTABLE[[#This Row],[totalCOST]]) -> 31.9084 | R46: =VLOOKUP($B46,Menu!$A$1:$F$20,MATCH(OrderLines!R$1,Menu!$A$1:$F$1,0),0) -> Veg Sandwich | S46: {=_xlfn.TEXTJOIN("+",TRUE,_xlfn._xlws.FILTER(orderlinesTABLE[ItemName],OrderID=orderlinesTABLE[[#This Row],[OrderID]]))} -> Rajma Chawal+Veg Sandwich+Chicken Thali | T46: =orderlinesTABLE[[#This Row],[Profit]]/orderlinesTABLE[[#This Row],[LineNetAmount]] -> 0.47119247 | U46: =(orderlinesTABLE[[#This Row],[Qty]]*orderlinesTABLE[[#This Row],[UnitCost]]) -> 35.81
A47: O00019 | B47: HDPBHS | C47: 2 | D47: =VLOOKUP($B47,Menu!$A$1:$F$20,MATCH($D$1,Menu!$A$1:$F$1,0),0) -> 256.91 | E47: =VLOOKUP($B47,Menu!$A$1:$F$20,MATCH(OrderLines!E$1,Menu!$A$1:$F$1,0),0) -> Hot Meal | F47: =VLOOKUP($B47,Menu!$A$1:$F$20,MATCH(OrderLines!F$1,Menu!$A$1:$F$1,0),0) -> 121.24 | G47: =VLOOKUP($A47,Orders!$A$1:$H$361,MATCH($G$1,Orders!$A$1:$H$1,0),0) -> 45878 | H47: =VLOOKUP($A47,Orders!$A$1:$H$361,MATCH(OrderLines!$H$1,Orders!$A$1:$H$1,0),0) -> Plant 1 Canteen | I47: =VLOOKUP($A47,Orders!$A$1:$H$361,MATCH(OrderLines!$I$1,Orders!$A$1:$H$1,0),0) -> 0.04 | J47: =$C47*$D47*(1-$I47) -> 493.2672 | K47: =TEXT($G47,"mmmm") -> August | L47: =VLOOKUP(OrderLines!$A47,Orders!$A$1:$H$361,MATCH(OrderLines!$L$1,Orders!$A$1:$H$1,0),0) -> Breakfast | M47: =VLOOKUP($A47,Orders!$A$1:$H$361,MATCH(OrderLines!$M$1,Orders!$A$1:$H$1,0),0) -> Cash | N47: =IF(AND(COUNTIFS(OrderID,$A47,Category,"hot meal")>=1,COUNTIFS(OrderID,$A47,Category,"beverage")>=1),"Combo","Single") -> Single | O47: {=IF((SUMPRODUCT((OrderID=OrderLines!$A47)*Qty*UnitPrice*DiscountPct))>40,"HighDisc","OK")} -> OK | P47: =(orderlinesTABLE[[#This Row],[UnitCost]]*orderlinesTABLE[[#This Row],[Qty]]) -> 242.48 | Q47: =(orderlinesTABLE[[#This Row],[LineNetAmount]]-orderlinesTABLE[[#This Row],[totalCOST]]) -> 250.7872 | R47: =VLOOKUP($B47,Menu!$A$1:$F$20,MATCH(OrderLines!R$1,Menu!$A$1:$F$1,0),0) -> Chicken Thali | S47: {=_xlfn.TEXTJOIN("+",TRUE,_xlfn._xlws.FILTER(orderlinesTABLE[ItemName],OrderID=orderlinesTABLE[[#This Row],[OrderID]]))} -> Rajma Chawal+Veg Sandwich+Chicken Thali | T47: =orderlinesTABLE[[#This Row],[Profit]]/orderlinesTABLE[[#This Row],[LineNetAmount]] -> 0.50842059 | U47: =(orderlinesTABLE[[#This Row],[Qty]]*orderlinesTABLE[[#This Row],[UnitCost]]) -> 242.48
A48: O00020 | B48: DFFYVN | C48: 3 | D48: =VLOOKUP($B48,Menu!$A$1:$F$20,MATCH($D$1,Menu!$A$1:$F$1,0),0) -> 54.2 | E48: =VLOOKUP($B48,Menu!$A$1:$F$20,MATCH(OrderLines!E$1,Menu!$A$1:$F$1,0),0) -> Dessert | F48: =VLOOKUP($B48,Menu!$A$1:$F$20,MATCH(OrderLines!F$1,Menu!$A$1:$F$1,0),0) -> 21.95 | G48: =VLOOKUP($A48,Orders!$A$1:$H$361,MATCH($G$1,Orders!$A$1:$H$1,0),0) -> 45847 | H48: =VLOOKUP($A48,Orders!$A$1:$H$361,MATCH(OrderLines!$H$1,Orders!$A$1:$H$1,0),0) -> Plant 2 Canteen | I48: =VLOOKUP($A48,Orders!$A$1:$H$361,MATCH(OrderLines!$I$1,Orders!$A$1:$H$1,0),0) -> 0.05 | J48: =$C48*$D48*(1-$I48) -> 154.47 | K48: =TEXT($G48,"mmmm") -> July | L48: =VLOOKUP(OrderLines!$A48,Orders!$A$1:$H$361,MATCH(OrderLines!$L$1,Orders!$A$1:$H$1,0),0) -> Breakfast | M48: =VLOOKUP($A48,Orders!$A$1:$H$361,MATCH(OrderLines!$M$1,Orders!$A$1:$H$1,0),0) -> UPI | N48: =IF(AND(COUNTIFS(OrderID,$A48,Category,"hot meal")>=1,COUNTIFS(OrderID,$A48,Category,"beverage")>=1),"Combo","Single") -> Combo | O48: {=IF((SUMPRODUCT((OrderID=OrderLines!$A48)*Qty*UnitPrice*DiscountPct))>40,"HighDisc","OK")} -> OK | P48: =(orderlinesTABLE[[#This Row],[UnitCost]]*orderlinesTABLE[[#This Row],[Qty]]) -> 65.85 | Q48: =(orderlinesTABLE[[#This Row],[LineNetAmount]]-orderlinesTABLE[[#This Row],[totalCOST]]) -> 88.62 | R48: =VLOOKUP($B48,Menu!$A$1:$F$20,MATCH(OrderLines!R$1,Menu!$A$1:$F$1,0),0) -> Kheer Cup | S48: {=_xlfn.TEXTJOIN("+",TRUE,_xlfn._xlws.FILTER(orderlinesTABLE[ItemName],OrderID=orderlinesTABLE[[#This Row],[OrderID]]))} -> Kheer Cup+Veg Thali+Masala Chaas+Gulab Jamun (2 pc) | T48: =orderlinesTABLE[[#This Row],[Profit]]/orderlinesTABLE[[#This Row],[LineNetAmount]] -> 0.57370363 | U48: =(orderlinesTABLE[[#This Row],[Qty]]*orderlinesTABLE[[#This Row],[UnitCost]]) -> 65.85
A49: O00020 | B49: HXAJI0 | C49: 1 | D49: =VLOOKUP($B49,Menu!$A$1:$F$20,MATCH($D$1,Menu!$A$1:$F$1,0),0) -> 227.61 | E49: =VLOOKUP($B49,Menu!$A$1:$F$20,MATCH(OrderLines!E$1,Menu!$A$1:$F$1,0),0) -> Hot Meal | F49: =VLOOKUP($B49,Menu!$A$1:$F$20,MATCH(OrderLines!F$1,Menu!$A$1:$F$1,0),0) -> 96.22 | G49: =VLOOKUP($A49,Orders!$A$1:$H$361,MATCH($G$1,Orders!$A$1:$H$1,0),0) -> 45847 | H49: =VLOOKUP($A49,Orders!$A$1:$H$361,MATCH(OrderLines!$H$1,Orders!$A$1:$H$1,0),0) -> Plant 2 Canteen | I49: =VLOOKUP($A49,Orders!$A$1:$H$361,MATCH(OrderLines!$I$1,Orders!$A$1:$H$1,0),0) -> 0.05 | J49: =$C49*$D49*(1-$I49) -> 216.2295 | K49: =TEXT($G49,"mmmm") -> July | L49: =VLOOKUP(OrderLines!$A49,Orders!$A$1:$H$361,MATCH(OrderLines!$L$1,Orders!$A$1:$H$1,0),0) -> Breakfast | M49: =VLOOKUP($A49,Orders!$A$1:$H$361,MATCH(OrderLines!$M$1,Orders!$A$1:$H$1,0),0) -> UPI | N49: =IF(AND(COUNTIFS(OrderID,$A49,Category,"hot meal")>=1,COUNTIFS(OrderID,$A49,Category,"beverage")>=1),"Combo","Single") -> Combo | O49: {=IF((SUMPRODUCT((OrderID=OrderLines!$A49)*Qty*UnitPrice*DiscountPct))>40,"HighDisc","OK")} -> OK | P49: =(orderlinesTABLE[[#This Row],[UnitCost]]*orderlinesTABLE[[#This Row],[Qty]]) -> 96.22 | Q49: =(orderlinesTABLE[[#This Row],[LineNetAmount]]-orderlinesTABLE[[#This Row],[totalCOST]]) -> 120.0095 | R49: =VLOOKUP($B49,Menu!$A$1:$F$20,MATCH(OrderLines!R$1,Menu!$A$1:$F$1,0),0) -> Veg Thali | S49: {=_xlfn.TEXTJOIN("+",TRUE,_xlfn._xlws.FILTER(orderlinesTABLE[ItemName],OrderID=orderlinesTABLE[[#This Row],[OrderID]]))} -> Kheer Cup+Veg Thali+Masala Chaas+Gulab Jamun (2 pc) | T49: =orderlinesTABLE[[#This Row],[Profit]]/orderlinesTABLE[[#This Row],[LineNetAmount]] -> 0.55500984 | U49: =(orderlinesTABLE[[#This Row],[Qty]]*orderlinesTABLE[[#This Row],[UnitCost]]) -> 96.22
A50: O00020 | B50: BOC6UZ | C50: 1 | D50: =VLOOKUP($B50,Menu!$A$1:$F$20,MATCH($D$1,Menu!$A$1:$F$1,0),0) -> 32.98 | E50: =VLOOKUP($B50,Menu!$A$1:$F$20,MATCH(OrderLines!E$1,Menu!$A$1:$F$1,0),0) -> Beverage | F50: =VLOOKUP($B50,Menu!$A$1:$F$20,MATCH(OrderLines!F$1,Menu!$A$1:$F$1,0),0) -> 11.84 | G50: =VLOOKUP($A50,Orders!$A$1:$H$361,MATCH($G$1,Orders!$A$1:$H$1,0),0) -> 45847 | H50: =VLOOKUP($A50,Orders!$A$1:$H$361,MATCH(OrderLines!$H$1,Orders!$A$1:$H$1,0),0) -> Plant 2 Canteen | I50: =VLOOKUP($A50,Orders!$A$1:$H$361,MATCH(OrderLines!$I$1,Orders!$A$1:$H$1,0),0) -> 0.05 | J50: =$C50*$D50*(1-$I50) -> 31.331 | K50: =TEXT($G50,"mmmm") -> July | L50: =VLOOKUP(OrderLines!$A50,Orders!$A$1:$H$361,MATCH(OrderLines!$L$1,Orders!$A$1:$H$1,0),0) -> Breakfast | M50: =VLOOKUP($A50,Orders!$A$1:$H$361,MATCH(OrderLines!$M$1,Orders!$A$1:$H$1,0),0) -> UPI | N50: =IF(AND(COUNTIFS(OrderID,$A50,Category,"hot meal")>=1,COUNTIFS(OrderID,$A50,Category,"beverage")>=1),"Combo","Single") -> Combo | O50: {=IF((SUMPRODUCT((OrderID=OrderLines!$A50)*Qty*UnitPrice*DiscountPct))>40,"HighDisc","OK")} -> OK | P50: =(orderlinesTABLE[[#This Row],[UnitCost]]*orderlinesTABLE[[#This Row],[Qty]]) -> 11.84 | Q50: =(orderlinesTABLE[[#This Row],[LineNetAmount]]-orderlinesTABLE[[#This Row],[totalCOST]]) -> 19.491 | R50: =VLOOKUP($B50,Menu!$A$1:$F$20,MATCH(OrderLines!R$1,Menu!$A$1:$F$1,0),0) -> Masala Chaas | S50: {=_xlfn.TEXTJOIN("+",TRUE,_xlfn._xlws.FILTER(orderlinesTABLE[ItemName],OrderID=orderlinesTABLE[[#This Row],[OrderID]]))} -> Kheer Cup+Veg Thali+Masala Chaas+Gulab Jamun (2 pc) | T50: =orderlinesTABLE[[#This Row],[Profit]]/orderlinesTABLE[[#This Row],[LineNetAmount]] -> 0.62209952 | U50: =(orderlinesTABLE[[#This Row],[Qty]]*orderlinesTABLE[[#This Row],[UnitCost]]) -> 11.84
A51: O00020 | B51: DH9SDB | C51: 1 | D51: =VLOOKUP($B51,Menu!$A$1:$F$20,MATCH($D$1,Menu!$A$1:$F$1,0),0) -> 76.55 | E51: =VLOOKUP($B51,Menu!$A$1:$F$20,MATCH(OrderLines!E$1,Menu!$A$1:$F$1,0),0) -> Dessert | F51: =VLOOKUP($B51,Menu!$A$1:$F$20,MATCH(OrderLines!F$1,Menu!$A$1:$F$1,0),0) -> 38.23 | G51: =VLOOKUP($A51,Orders!$A$1:$H$361,MATCH($G$1,Orders!$A$1:$H$1,0),0) -> 45847 | H51: =VLOOKUP($A51,Orders!$A$1:$H$361,MATCH(OrderLines!$H$1,Orders!$A$1:$H$1,0),0) -> Plant 2 Canteen | I51: =VLOOKUP($A51,Orders!$A$1:$H$361,MATCH(OrderLines!$I$1,Orders!$A$1:$H$1,0),0) -> 0.05 | J51: =$C51*$D51*(1-$I51) -> 72.7225 | K51: =TEXT($G51,"mmmm") -> July | L51: =VLOOKUP(OrderLines!$A51,Orders!$A$1:$H$361,MATCH(OrderLines!$L$1,Orders!$A$1:$H$1,0),0) -> Breakfast | M51: =VLOOKUP($A51,Orders!$A$1:$H$361,MATCH(OrderLines!$M$1,Orders!$A$1:$H$1,0),0) -> UPI | N51: =IF(AND(COUNTIFS(OrderID,$A51,Category,"hot meal")>=1,COUNTIFS(OrderID,$A51,Category,"beverage")>=1),"Combo","Single") -> Combo | O51: {=IF((SUMPRODUCT((OrderID=OrderLines!$A51)*Qty*UnitPrice*DiscountPct))>40,"HighDisc","OK")} -> OK | P51: =(orderlinesTABLE[[#This Row],[UnitCost]]*orderlinesTABLE[[#This Row],[Qty]]) -> 38.23 | Q51: =(orderlinesTABLE[[#This Row],[LineNetAmount]]-orderlinesTABLE[[#This Row],[totalCOST]]) -> 34.4925 | R51: =VLOOKUP($B51,Menu!$A$1:$F$20,MATCH(OrderLines!R$1,Menu!$A$1:$F$1,0),0) -> Gulab Jamun (2 pc) | S51: {=_xlfn.TEXTJOIN("+",TRUE,_xlfn._xlws.FILTER(orderlinesTABLE[ItemName],OrderID=orderlinesTABLE[[#This Row],[OrderID]]))} -> Kheer Cup+Veg Thali+Masala Chaas+Gulab Jamun (2 pc) | T51: =orderlinesTABLE[[#This Row],[Profit]]/orderlinesTABLE[[#This Row],[LineNetAmount]] -> 0.474303 | U51: =(orderlinesTABLE[[#This Row],[Qty]]*orderlinesTABLE[[#This Row],[UnitCost]]) -> 38.23 | W51: {=(_xlfn.UNIQUE(SKU))} -> SHJ7XV
A52: O00021 | B52: SHJ7XV | C52: 3 | D52: =VLOOKUP($B52,Menu!$A$1:$F$20,MATCH($D$1,Menu!$A$1:$F$1,0),0) -> 52.45 | E52: =VLOOKUP($B52,Menu!$A$1:$F$20,MATCH(OrderLines!E$1,Menu!$A$1:$F$1,0),0) -> Snack | F52: =VLOOKUP($B52,Menu!$A$1:$F$20,MATCH(OrderLines!F$1,Menu!$A$1:$F$1,0),0) -> 25.8 | G52: =VLOOKUP($A52,Orders!$A$1:$H$361,MATCH($G$1,Orders!$A$1:$H$1,0),0) -> 45869 | H52: =VLOOKUP($A52,Orders!$A$1:$H$361,MATCH(OrderLines!$H$1,Orders!$A$1:$H$1,0),0) -> Plant 2 Canteen | I52: =VLOOKUP($A52,Orders!$A$1:$H$361,MATCH(OrderLines!$I$1,Orders!$A$1:$H$1,0),0) -> 0.02 | J52: =$C52*$D52*(1-$I52) -> 154.203 | K52: =TEXT($G52,"mmmm") -> July | L52: =VLOOKUP(OrderLines!$A52,Orders!$A$1:$H$361,MATCH(OrderLines!$L$1,Orders!$A$1:$H$1,0),0) -> Dinner | M52: =VLOOKUP($A52,Orders!$A$1:$H$361,MATCH(OrderLines!$M$1,Orders!$A$1:$H$1,0),0) -> UPI | N52: =IF(AND(COUNTIFS(OrderID,$A52,Category,"hot meal")>=1,COUNTIFS(OrderID,$A52,Category,"beverage")>=1),"Combo","Single") -> Single | O52: {=IF((SUMPRODUCT((OrderID=OrderLines!$A52)*Qty*UnitPrice*DiscountPct))>40,"HighDisc","OK")} -> OK | P52: =(orderlinesTABLE[[#This Row],[UnitCost]]*orderlinesTABLE[[#This Row],[Qty]]) -> 77.4 | Q52: =(orderlinesTABLE[[#This Row],[LineNetAmount]]-orderlinesTABLE[[#This Row],[totalCOST]]) -> 76.803 | R52: =VLOOKUP($B52,Menu!$A$1:$F$20,MATCH(OrderLines!R$1,Menu!$A$1:$F$1,0),0) -> Poha | S52: {=_xlfn.TEXTJOIN("+",TRUE,_xlfn._xlws.FILTER(orderlinesTABLE[ItemName],OrderID=orderlinesTABLE[[#This Row],[OrderID]]))} -> Poha+Samosa+Masala Puff | T52: =orderlinesTABLE[[#This Row],[Profit]]/orderlinesTABLE[[#This Row],[LineNetAmount]] -> 0.49806424 | U52: =(orderlinesTABLE[[#This Row],[Qty]]*orderlinesTABLE[[#This Row],[UnitCost]]) -> 77.4 | W52: BTIQJ7
A53: O00021 | B53: SV30T9 | C53: 1 | D53: =VLOOKUP($B53,Menu!$A$1:$F$20,MATCH($D$1,Menu!$A$1:$F$1,0),0) -> 39.95 | E53: =VLOOKUP($B53,Menu!$A$1:$F$20,MATCH(OrderLines!E$1,Menu!$A$1:$F$1,0),0) -> Snack | F53: =VLOOKUP($B53,Menu!$A$1:$F$20,MATCH(OrderLines!F$1,Menu!$A$1:$F$1,0),0) -> 15.51 | G53: =VLOOKUP($A53,Orders!$A$1:$H$361,MATCH($G$1,Orders!$A$1:$H$1,0),0) -> 45869 | H53: =VLOOKUP($A53,Orders!$A$1:$H$361,MATCH(OrderLines!$H$1,Orders!$A$1:$H$1,0),0) -> Plant 2 Canteen | I53: =VLOOKUP($A53,Orders!$A$1:$H$361,MATCH(OrderLines!$I$1,Orders!$A$1:$H$1,0),0) -> 0.02 | J53: =$C53*$D53*(1-$I53) -> 39.151 | K53: =TEXT($G53,"mmmm") -> July | L53: =VLOOKUP(OrderLines!$A53,Orders!$A$1:$H$361,MATCH(OrderLines!$L$1,Orders!$A$1:$H$1,0),0) -> Dinner | M53: =VLOOKUP($A53,Orders!$A$1:$H$361,MATCH(OrderLines!$M$1,Orders!$A$1:$H$1,0),0) -> UPI | N53: =IF(AND(COUNTIFS(OrderID,$A53,Category,"hot meal")>=1,COUNTIFS(OrderID,$A53,Category,"beverage")>=1),"Combo","Single") -> Single | O53: {=IF((SUMPRODUCT((OrderID=OrderLines!$A53)*Qty*UnitPrice*DiscountPct))>40,"HighDisc","OK")} -> OK | P53: =(orderlinesTABLE[[#This Row],[UnitCost]]*orderlinesTABLE[[#This Row],[Qty]]) -> 15.51 | Q53: =(orderlinesTABLE[[#This Row],[LineNetAmount]]-orderlinesTABLE[[#This Row],[totalCOST]]) -> 23.641 | R53: =VLOOKUP($B53,Menu!$A$1:$F$20,MATCH(OrderLines!R$1,Menu!$A$1:$F$1,0),0) -> Samosa | S53: {=_xlfn.TEXTJOIN("+",TRUE,_xlfn._xlws.FILTER(orderlinesTABLE[ItemName],OrderID=orderlinesTABLE[[#This Row],[OrderID]]))} -> Poha+Samosa+Masala Puff | T53: =orderlinesTABLE[[#This Row],[Profit]]/orderlinesTABLE[[#This Row],[LineNetAmount]] -> 0.60384154 | U53: =(orderlinesTABLE[[#This Row],[Qty]]*orderlinesTABLE[[#This Row],[UnitCost]]) -> 15.51 | W53: DH9SDB
A54: O00021 | B54: S5NQ4F | C54: 2 | D54: =VLOOKUP($B54,Menu!$A$1:$F$20,MATCH($D$1,Menu!$A$1:$F$1,0),0) -> 50.19 | E54: =VLOOKUP($B54,Menu!$A$1:$F$20,MATCH(OrderLines!E$1,Menu!$A$1:$F$1,0),0) -> Snack | F54: =VLOOKUP($B54,Menu!$A$1:$F$20,MATCH(OrderLines!F$1,Menu!$A$1:$F$1,0),0) -> 22.61 | G54: =VLOOKUP($A54,Orders!$A$1:$H$361,MATCH($G$1,Orders!$A$1:$H$1,0),0) -> 45869 | H54: =VLOOKUP($A54,Orders!$A$1:$H$361,MATCH(OrderLines!$H$1,Orders!$A$1:$H$1,0),0) -> Plant 2 Canteen | I54: =VLOOKUP($A54,Orders!$A$1:$H$361,MATCH(OrderLines!$I$1,Orders!$A$1:$H$1,0),0) -> 0.02 | J54: =$C54*$D54*(1-$I54) -> 98.3724 | K54: =TEXT($G54,"mmmm") -> July | L54: =VLOOKUP(OrderLines!$A54,Orders!$A$1:$H$361,MATCH(OrderLines!$L$1,Orders!$A$1:$H$1,0),0) -> Dinner | M54: =VLOOKUP($A54,Orders!$A$1:$H$361,MATCH(OrderLines!$M$1,Orders!$A$1:$H$1,0),0) -> UPI | N54: =IF(AND(COUNTIFS(OrderID,$A54,Category,"hot meal")>=1,COUNTIFS(OrderID,$A54,Category,"beverage")>=1),"Combo","Single") -> Single | O54: {=IF((SUMPRODUCT((OrderID=OrderLines!$A54)*Qty*UnitPrice*DiscountPct))>40,"HighDisc","OK")} -> OK | P54: =(orderlinesTABLE[[#This Row],[UnitCost]]*orderlinesTABLE[[#This Row],[Qty]]) -> 45.22 | Q54: =(orderlinesTABLE[[#This Row],[LineNetAmount]]-orderlinesTABLE[[#This Row],[totalCOST]]) -> 53.1524 | R54: =VLOOKUP($B54,Menu!$A$1:$F$20,MATCH(OrderLines!R$1,Menu!$A$1:$F$1,0),0) -> Masala Puff | S54: {=_xlfn.TEXTJOIN("+",TRUE,_xlfn._xlws.FILTER(orderlinesTABLE[ItemName],OrderID=orderlinesTABLE[[#This Row],[OrderID]]))} -> Poha+Samosa+Masala Puff | T54: =orderlinesTABLE[[#This Row],[Profit]]/orderlinesTABLE[[#This Row],[LineNetAmount]] -> 0.54031822 | U54: =(orderlinesTABLE[[#This Row],[Qty]]*orderlinesTABLE[[#This Row],[UnitCost]]) -> 45.22 | W54: BOC6UZ
A55: O00022 | B55: DFFYVN | C55: 1 | D55: =VLOOKUP($B55,Menu!$A$1:$F$20,MATCH($D$1,Menu!$A$1:$F$1,0),0) -> 54.2 | E55: =VLOOKUP($B55,Menu!$A$1:$F$20,MATCH(OrderLines!E$1,Menu!$A$1:$F$1,0),0) -> Dessert | F55: =VLOOKUP($B55,Menu!$A$1:$F$20,MATCH(OrderLines!F$1,Menu!$A$1:$F$1,0),0) -> 21.95 | G55: =VLOOKUP($A55,Orders!$A$1:$H$361,MATCH($G$1,Orders!$A$1:$H$1,0),0) -> 45862 | H55: =VLOOKUP($A55,Orders!$A$1:$H$361,MATCH(OrderLines!$H$1,Orders!$A$1:$H$1,0),0) -> Plant 2 Canteen | I55: =VLOOKUP($A55,Orders!$A$1:$H$361,MATCH(OrderLines!$I$1,Orders!$A$1:$H$1,0),0) -> 0.01 | J55: =$C55*$D55*(1-$I55) -> 53.658 | K55: =TEXT($G55,"mmmm") -> July | L55: =VLOOKUP(OrderLines!$A55,Orders!$A$1:$H$361,MATCH(OrderLines!$L$1,Orders!$A$1:$H$1,0),0) -> Breakfast | M55: =VLOOKUP($A55,Orders!$A$1:$H$361,MATCH(OrderLines!$M$1,Orders!$A$1:$H$1,0),0) -> Cash | N55: =IF(AND(COUNTIFS(OrderID,$A55,Category,"hot meal")>=1,COUNTIFS(OrderID,$A55,Category,"beverage")>=1),"Combo","Single") -> Combo | O55: {=IF((SUMPRODUCT((OrderID=OrderLines!$A55)*Qty*UnitPrice*DiscountPct))>40,"HighDisc","OK")} -> OK | P55: =(orderlinesTABLE[[#This Row],[UnitCost]]*orderlinesTABLE[[#This Row],[Qty]]) -> 21.95 | Q55: =(orderlinesTABLE[[#This Row],[LineNetAmount]]-orderlinesTABLE[[#This Row],[totalCOST]]) -> 31.708 | R55: =VLOOKUP($B55,Menu!$A$1:$F$20,MATCH(OrderLines!R$1,Menu!$A$1:$F$1,0),0) -> Kheer Cup | S55: {=_xlfn.TEXTJOIN("+",TRUE,_xlfn._xlws.FILTER(orderlinesTABLE[ItemName],OrderID=orderlinesTABLE[[#This Row],[OrderID]]))} -> Kheer Cup+Bottled Water+Chicken Thali | T55: =orderlinesTABLE[[#This Row],[Profit]]/orderlinesTABLE[[#This Row],[LineNetAmount]] -> 0.59092773 | U55: =(orderlinesTABLE[[#This Row],[Qty]]*orderlinesTABLE[[#This Row],[UnitCost]]) -> 21.95 | W55: H3A3ZM
A56: O00022 | B56: B0T0PV | C56: 2 | D56: =VLOOKUP($B56,Menu!$A$1:$F$20,MATCH($D$1,Menu!$A$1:$F$1,0),0) -> 28.43 | E56: =VLOOKUP($B56,Menu!$A$1:$F$20,MATCH(OrderLines!E$1,Menu!$A$1:$F$1,0),0) -> Beverage | F56: =VLOOKUP($B56,Menu!$A$1:$F$20,MATCH(OrderLines!F$1,Menu!$A$1:$F$1,0),0) -> 13.89 | G56: =VLOOKUP($A56,Orders!$A$1:$H$361,MATCH($G$1,Orders!$A$1:$H$1,0),0) -> 45862 | H56: =VLOOKUP($A56,Orders!$A$1:$H$361,MATCH(OrderLines!$H$1,Orders!$A$1:$H$1,0),0) -> Plant 2 Canteen | I56: =VLOOKUP($A56,Orders!$A$1:$H$361,MATCH(OrderLines!$I$1,Orders!$A$1:$H$1,0),0) -> 0.01 | J56: =$C56*$D56*(1-$I56) -> 56.2914 | K56: =TEXT($G56,"mmmm") -> July | L56: =VLOOKUP(OrderLines!$A56,Orders!$A$1:$H$361,MATCH(OrderLines!$L$1,Orders!$A$1:$H$1,0),0) -> Breakfast | M56: =VLOOKUP($A56,Orders!$A$1:$H$361,MATCH(OrderLines!$M$1,Orders!$A$1:$H$1,0),0) -> Cash | N56: =IF(AND(COUNTIFS(OrderID,$A56,Category,"hot meal")>=1,COUNTIFS(OrderID,$A56,Category,"beverage")>=1),"Combo","Single") -> Combo | O56: {=IF((SUMPRODUCT((OrderID=OrderLines!$A56)*Qty*UnitPrice*DiscountPct))>40,"HighDisc","OK")} -> OK | P56: =(orderlinesTABLE[[#This Row],[UnitCost]]*orderlinesTABLE[[#This Row],[Qty]]) -> 27.78 | Q56: =(orderlinesTABLE[[#This Row],[LineNetAmount]]-orderlinesTABLE[[#This Row],[totalCOST]]) -> 28.5114 | R56: =VLOOKUP($B56,Menu!$A$1:$F$20,MATCH(OrderLines!R$1,Menu!$A$1:$F$1,0),0) -> Bottled Water | S56: {=_xlfn.TEXTJOIN("+",TRUE,_xlfn._xlws.FILTER(orderlinesTABLE[ItemName],OrderID=orderlinesTABLE[[#This Row],[OrderID]]))} -> Kheer Cup+Bottled Water+Chicken Thali | T56: =orderlinesTABLE[[#This Row],[Profit]]/orderlinesTABLE[[#This Row],[LineNetAmount]] -> 0.50649655 | U56: =(orderlinesTABLE[[#This Row],[Qty]]*orderlinesTABLE[[#This Row],[UnitCost]]) -> 27.78 | W56: SZBIKC
A57: O00022 | B57: HDPBHS | C57: 1 | D57: =VLOOKUP($B57,Menu!$A$1:$F$20,MATCH($D$1,Menu!$A$1:$F$1,0),0) -> 256.91 | E57: =VLOOKUP($B57,Menu!$A$1:$F$20,MATCH(OrderLines!E$1,Menu!$A$1:$F$1,0),0) -> Hot Meal | F57: =VLOOKUP($B57,Menu!$A$1:$F$20,MATCH(OrderLines!F$1,Menu!$A$1:$F$1,0),0) -> 121.24 | G57: =VLOOKUP($A57,Orders!$A$1:$H$361,MATCH($G$1,Orders!$A$1:$H$1,0),0) -> 45862 | H57: =VLOOKUP($A57,Orders!$A$1:$H$361,MATCH(OrderLines!$H$1,Orders!$A$1:$H$1,0),0) -> Plant 2 Canteen | I57: =VLOOKUP($A57,Orders!$A$1:$H$361,MATCH(OrderLines!$I$1,Orders!$A$1:$H$1,0),0) -> 0.01 | J57: =$C57*$D57*(1-$I57) -> 254.3409 | K57: =TEXT($G57,"mmmm") -> July | L57: =VLOOKUP(OrderLines!$A57,Orders!$A$1:$H$361,MATCH(OrderLines!$L$1,Orders!$A$1:$H$1,0),0) -> Breakfast | M57: =VLOOKUP($A57,Orders!$A$1:$H$361,MATCH(OrderLines!$M$1,Orders!$A$1:$H$1,0),0) -> Cash | N57: =IF(AND(COUNTIFS(OrderID,$A57,Category,"hot meal")>=1,COUNTIFS(OrderID,$A57,Category,"beverage")>=1),"Combo","Single") -> Combo | O57: {=IF((SUMPRODUCT((OrderID=OrderLines!$A57)*Qty*UnitPrice*DiscountPct))>40,"HighDisc","OK")} -> OK | P57: =(orderlinesTABLE[[#This Row],[UnitCost]]*orderlinesTABLE[[#This Row],[Qty]]) -> 121.24 | Q57: =(orderlinesTABLE[[#This Row],[LineNetAmount]]-orderlinesTABLE[[#This Row],[totalCOST]]) -> 133.1009 | R57: =VLOOKUP($B57,Menu!$A$1:$F$20,MATCH(OrderLines!R$1,Menu!$A$1:$F$1,0),0) -> Chicken Thali | S57: {=_xlfn.TEXTJOIN("+",TRUE,_xlfn._xlws.FILTER(orderlinesTABLE[ItemName],OrderID=orderlinesTABLE[[#This Row],[OrderID]]))} -> Kheer Cup+Bottled Water+Chicken Thali | T57: =orderlinesTABLE[[#This Row],[Profit]]/orderlinesTABLE[[#This Row],[LineNetAmount]] -> 0.52331693 | U57: =(orderlinesTABLE[[#This Row],[Qty]]*orderlinesTABLE[[#This Row],[UnitCost]]) -> 121.24 | W57: HH1DNM
A58: O00023 | B58: BXO6QJ | C58: 1 | D58: =VLOOKUP($B58,Menu!$A$1:$F$20,MATCH($D$1,Menu!$A$1:$F$1,0),0) -> 20.11 | E58: =VLOOKUP($B58,Menu!$A$1:$F$20,MATCH(OrderLines!E$1,Menu!$A$1:$F$1,0),0) -> Beverage | F58: =VLOOKUP($B58,Menu!$A$1:$F$20,MATCH(OrderLines!F$1,Menu!$A$1:$F$1,0),0) -> 8 | G58: =VLOOKUP($A58,Orders!$A$1:$H$361,MATCH($G$1,Orders!$A$1:$H$1,0),0) -> 45883 | H58: =VLOOKUP($A58,Orders!$A$1:$H$361,MATCH(OrderLines!$H$1,Orders!$A$1:$H$1,0),0) -> Plant 2 Canteen | I58: =VLOOKUP($A58,Orders!$A$1:$H$361,MATCH(OrderLines!$I$1,Orders!$A$1:$H$1,0),0) -> 0.09 | J58: =$C58*$D58*(1-$I58) -> 18.3001 | K58: =TEXT($G58,"mmmm") -> August | L58: =VLOOKUP(OrderLines!$A58,Orders!$A$1:$H$361,MATCH(OrderLines!$L$1,Orders!$A$1:$H$1,0),0) -> Lunch | M58: =VLOOKUP($A58,Orders!$A$1:$H$361,MATCH(OrderLines!$M$1,Orders!$A$1:$H$1,0),0) -> Cash | N58: =IF(AND(COUNTIFS(OrderID,$A58,Category,"hot meal")>=1,COUNTIFS(OrderID,$A58,Category,"beverage")>=1),"Combo","Single") -> Combo | O58: {=IF((SUMPRODUCT((OrderID=OrderLines!$A58)*Qty*UnitPrice*DiscountPct))>40,"HighDisc","OK")} -> OK | P58: =(orderlinesTABLE[[#This Row],[UnitCost]]*orderlinesTABLE[[#This Row],[Qty]]) -> 8 | Q58: =(orderlinesTABLE[[#This Row],[LineNetAmount]]-orderlinesTABLE[[#This Row],[totalCOST]]) -> 10.3001 | R58: =VLOOKUP($B58,Menu!$A$1:$F$20,MATCH(OrderLines!R$1,Menu!$A$1:$F$1,0),0) -> Nimbu Pani | S58: {=_xlfn.TEXTJOIN("+",TRUE,_xlfn._xlws.FILTER(orderlinesTABLE[ItemName],OrderID=orderlinesTABLE[[#This Row],[OrderID]]))} -> Nimbu Pani+Egg Curry + Rice | T58: =orderlinesTABLE[[#This Row],[Profit]]/orderlinesTABLE[[#This Row],[LineNetAmount]] -> 0.56284392 | U58: =(orderlinesTABLE[[#This Row],[Qty]]*orderlinesTABLE[[#This Row],[UnitCost]]) -> 8 | W58: SCKW5N
A59: O00023 | B59: HH1DNM | C59: 1 | D59: =VLOOKUP($B59,Menu!$A$1:$F$20,MATCH($D$1,Menu!$A$1:$F$1,0),0) -> 246.09 | E59: =VLOOKUP($B59,Menu!$A$1:$F$20,MATCH(OrderLines!E$1,Menu!$A$1:$F$1,0),0) -> Hot Meal | F59: =VLOOKUP($B59,Menu!$A$1:$F$20,MATCH(OrderLines!F$1,Menu!$A$1:$F$1,0),0) -> 112.08 | G59: =VLOOKUP($A59,Orders!$A$1:$H$361,MATCH($G$1,Orders!$A$1:$H$1,0),0) -> 45883 | H59: =VLOOKUP($A59,Orders!$A$1:$H$361,MATCH(OrderLines!$H$1,Orders!$A$1:$H$1,0),0) -> Plant 2 Canteen | I59: =VLOOKUP($A59,Orders!$A$1:$H$361,MATCH(OrderLines!$I$1,Orders!$A$1:$H$1,0),0) -> 0.09 | J59: =$C59*$D59*(1-$I59) -> 223.9419 | K59: =TEXT($G59,"mmmm") -> August | L59: =VLOOKUP(OrderLines!$A59,Orders!$A$1:$H$361,MATCH(OrderLines!$L$1,Orders!$A$1:$H$1,0),0) -> Lunch | M59: =VLOOKUP($A59,Orders!$A$1:$H$361,MATCH(OrderLines!$M$1,Orders!$A$1:$H$1,0),0) -> Cash | N59: =IF(AND(COUNTIFS(OrderID,$A59,Category,"hot meal")>=1,COUNTIFS(OrderID,$A59,Category,"beverage")>=1),"Combo","Single") -> Combo | O59: {=IF((SUMPRODUCT((OrderID=OrderLines!$A59)*Qty*UnitPrice*DiscountPct))>40,"HighDisc","OK")} -> OK | P59: =(orderlinesTABLE[[#This Row],[UnitCost]]*orderlinesTABLE[[#This Row],[Qty]]) -> 112.08 | Q59: =(orderlinesTABLE[[#This Row],[LineNetAmount]]-orderlinesTABLE[[#This Row],[totalCOST]]) -> 111.8619 | R59: =VLOOKUP($B59,Menu!$A$1:$F$20,MATCH(OrderLines!R$1,Menu!$A$1:$F$1,0),0) -> Egg Curry + Rice | S59: {=_xlfn.TEXTJOIN("+",TRUE,_xlfn._xlws.FILTER(orderlinesTABLE[ItemName],OrderID=orderlinesTABLE[[#This Row],[OrderID]]))} -> Nimbu Pani+Egg Curry + Rice | T59: =orderlinesTABLE[[#This Row],[Profit]]/orderlinesTABLE[[#This Row],[LineNetAmount]] -> 0.49951304 | U59: =(orderlinesTABLE[[#This Row],[Qty]]*orderlinesTABLE[[#This Row],[UnitCost]]) -> 112.08 | W59: B0T0PV
A60: O00024 | B60: HUZZPQ | C60: 3 | D60: =VLOOKUP($B60,Menu!$A$1:$F$20,MATCH($D$1,Menu!$A$1:$F$1,0),0) -> 146.4 | E60: =VLOOKUP($B60,Menu!$A$1:$F$20,MATCH(OrderLines!E$1,Menu!$A$1:$F$1,0),0) -> Hot Meal | F60: =VLOOKUP($B60,Menu!$A$1:$F$20,MATCH(OrderLines!F$1,Menu!$A$1:$F$1,0),0) -> 80.92 | G60: =VLOOKUP($A60,Orders!$A$1:$H$361,MATCH($G$1,Orders!$A$1:$H$1,0),0) -> 45893 | H60: =VLOOKUP($A60,Orders!$A$1:$H$361,MATCH(OrderLines!$H$1,Orders!$A$1:$H$1,0),0) -> Plant 1 Canteen | I60: =VLOOKUP($A60,Orders!$A$1:$H$361,MATCH(OrderLines!$I$1,Orders!$A$1:$H$1,0),0) -> 0.11 | J60: =$C60*$D60*(1-$I60) -> 390.888 | K60: =TEXT($G60,"mmmm") -> August | L60: =VLOOKUP(OrderLines!$A60,Orders!$A$1:$H$361,MATCH(OrderLines!$L$1,Orders!$A$1:$H$1,0),0) -> Dinner | M60: =VLOOKUP($A60,Orders!$A$1:$H$361,MATCH(OrderLines!$M$1,Orders!$A$1:$H$1,0),0) -> UPI | N60: =IF(AND(COUNTIFS(OrderID,$A60,Category,"hot meal")>=1,COUNTIFS(OrderID,$A60,Category,"beverage")>=1),"Combo","Single") -> Single | O60: {=IF((SUMPRODUCT((OrderID=OrderLines!$A60)*Qty*UnitPrice*DiscountPct))>40,"HighDisc","OK")} -> HighDisc | P60: =(orderlinesTABLE[[#This Row],[UnitCost]]*orderlinesTABLE[[#This Row],[Qty]]) -> 242.76 | Q60: =(orderlinesTABLE[[#This Row],[LineNetAmount]]-orderlinesTABLE[[#This Row],[totalCOST]]) -> 148.128 | R60: =VLOOKUP($B60,Menu!$A$1:$F$20,MATCH(OrderLines!R$1,Menu!$A$1:$F$1,0),0) -> Rajma Chawal | S60: {=_xlfn.TEXTJOIN("+",TRUE,_xlfn._xlws.FILTER(orderlinesTABLE[ItemName],OrderID=orderlinesTABLE[[#This Row],[OrderID]]))} -> Rajma Chawal | T60: =orderlinesTABLE[[#This Row],[Profit]]/orderlinesTABLE[[#This Row],[LineNetAmount]] -> 0.37895254 | U60: =(orderlinesTABLE[[#This Row],[Qty]]*orderlinesTABLE[[#This Row],[UnitCost]]) -> 242.76 | W60: BXO6QJ
A61: O00025 | B61: S5NQ4F | C61: 1 | D61: =VLOOKUP($B61,Menu!$A$1:$F$20,MATCH($D$1,Menu!$A$1:$F$1,0),0) -> 50.19 | E61: =VLOOKUP($B61,Menu!$A$1:$F$20,MATCH(OrderLines!E$1,Menu!$A$1:$F$1,0),0) -> Snack | F61: =VLOOKUP($B61,Menu!$A$1:$F$20,MATCH(OrderLines!F$1,Menu!$A$1:$F$1,0),0) -> 22.61 | G61: =VLOOKUP($A61,Orders!$A$1:$H$361,MATCH($G$1,Orders!$A$1:$H$1,0),0) -> 45888 | H61: =VLOOKUP($A61,Orders!$A$1:$H$361,MATCH(OrderLines!$H$1,Orders!$A$1:$H$1,0),0) -> Plant 2 Canteen | I61: =VLOOKUP($A61,Orders!$A$1:$H$361,MATCH(OrderLines!$I$1,Orders!$A$1:$H$1,0),0) -> 0.06 | J61: =$C61*$D61*(1-$I61) -> 47.1786 | K61: =TEXT($G61,"mmmm") -> August | L61: =VLOOKUP(OrderLines!$A61,Orders!$A$1:$H$361,MATCH(OrderLines!$L$1,Orders!$A$1:$H$1,0),0) -> Breakfast | M61: =VLOOKUP($A61,Orders!$A$1:$H$361,MATCH(OrderLines!$M$1,Orders!$A$1:$H$1,0),0) -> Card | N61: =IF(AND(COUNTIFS(OrderID,$A61,Category,"hot meal")>=1,COUNTIFS(OrderID,$A61,Category,"beverage")>=1),"Combo","Single") -> Single | O61: {=IF((SUMPRODUCT((OrderID=OrderLines!$A61)*Qty*UnitPrice*DiscountPct))>40,"HighDisc","OK")} -> OK | P61: =(orderlinesTABLE[[#This Row],[UnitCost]]*orderlinesTABLE[[#This Row],[Qty]]) -> 22.61 | Q61: =(orderlinesTABLE[[#This Row],[LineNetAmount]]-orderlinesTABLE[[#This Row],[totalCOST]]) -> 24.5686 | R61: =VLOOKUP($B61,Menu!$A$1:$F$20,MATCH(OrderLines!R$1,Menu!$A$1:$F$1,0),0) -> Masala Puff | S61: {=_xlfn.TEXTJOIN("+",TRUE,_xlfn._xlws.FILTER(orderlinesTABLE[ItemName],OrderID=orderlinesTABLE[[#This Row],[OrderID]]))} -> Masala Puff | T61: =orderlinesTABLE[[#This Row],[Profit]]/orderlinesTABLE[[#This Row],[LineNetAmount]] -> 0.52075729 | U61: =(orderlinesTABLE[[#This Row],[Qty]]*orderlinesTABLE[[#This Row],[UnitCost]]) -> 22.61 | W61: BHL1C3
A62: O00026 | B62: SHJ7XV | C62: 1 | D62: =VLOOKUP($B62,Menu!$A$1:$F$20,MATCH($D$1,Menu!$A$1:$F$1,0),0) -> 52.45 | E62: =VLOOKUP($B62,Menu!$A$1:$F$20,MATCH(OrderLines!E$1,Menu!$A$1:$F$1,0),0) -> Snack | F62: =VLOOKUP($B62,Menu!$A$1:$F$20,MATCH(OrderLines!F$1,Menu!$A$1:$F$1,0),0) -> 25.8 | G62: =VLOOKUP($A62,Orders!$A$1:$H$361,MATCH($G$1,Orders!$A$1:$H$1,0),0) -> 45862 | H62: =VLOOKUP($A62,Orders!$A$1:$H$361,MATCH(OrderLines!$H$1,Orders!$A$1:$H$1,0),0) -> Plant 2 Canteen | I62: =VLOOKUP($A62,Orders!$A$1:$H$361,MATCH(OrderLines!$I$1,Orders!$A$1:$H$1,0),0) -> 0.1 | J62: =$C62*$D62*(1-$I62) -> 47.205 | K62: =TEXT($G62,"mmmm") -> July | L62: =VLOOKUP(OrderLines!$A62,Orders!$A$1:$H$361,MATCH(OrderLines!$L$1,Orders!$A$1:$H$1,0),0) -> Dinner | M62: =VLOOKUP($A62,Orders!$A$1:$H$361,MATCH(OrderLines!$M$1,Orders!$A$1:$H$1,0),0) -> Cash | N62: =IF(AND(COUNTIFS(OrderID,$A62,Category,"hot meal")>=1,COUNTIFS(OrderID,$A62,Category,"beverage")>=1),"Combo","Single") -> Single | O62: {=IF((SUMPRODUCT((OrderID=OrderLines!$A62)*Qty*UnitPrice*DiscountPct))>40,"HighDisc","OK")} -> OK | P62: =(orderlinesTABLE[[#This Row],[UnitCost]]*orderlinesTABLE[[#This Row],[Qty]]) -> 25.8 | Q62: =(orderlinesTABLE[[#This Row],[LineNetAmount]]-orderlinesTABLE[[#This Row],[totalCOST]]) -> 21.405 | R62: =VLOOKUP($B62,Menu!$A$1:$F$20,MATCH(OrderLines!R$1,Menu!$A$1:$F$1,0),0) -> Poha | S62: {=_xlfn.TEXTJOIN("+",TRUE,_xlfn._xlws.FILTER(orderlinesTABLE[ItemName],OrderID=orderlinesTABLE[[#This Row],[OrderID]]))} -> Poha+Paneer Roll | T62: =orderlinesTABLE[[#This Row],[Profit]]/orderlinesTABLE[[#This Row],[LineNetAmount]] -> 0.45344773 | U62: =(orderlinesTABLE[[#This Row],[Qty]]*orderlinesTABLE[[#This Row],[UnitCost]]) -> 25.8 | W62: DYTJXE
A63: O00026 | B63: SZBIKC | C63: 1 | D63: =VLOOKUP($B63,Menu!$A$1:$F$20,MATCH($D$1,Menu!$A$1:$F$1,0),0) -> 38.06 | E63: =VLOOKUP($B63,Menu!$A$1:$F$20,MATCH(OrderLines!E$1,Menu!$A$1:$F$1,0),0) -> Snack | F63: =VLOOKUP($B63,Menu!$A$1:$F$20,MATCH(OrderLines!F$1,Menu!$A$1:$F$1,0),0) -> 19.55 | G63: =VLOOKUP($A63,Orders!$A$1:$H$361,MATCH($G$1,Orders!$A$1:$H$1,0),0) -> 45862 | H63: =VLOOKUP($A63,Orders!$A$1:$H$361,MATCH(OrderLines!$H$1,Orders!$A$1:$H$1,0),0) -> Plant 2 Canteen | I63: =VLOOKUP($A63,Orders!$A$1:$H$361,MATCH(OrderLines!$I$1,Orders!$A$1:$H$1,0),0) -> 0.1 | J63: =$C63*$D63*(1-$I63) -> 34.254 | K63: =TEXT($G63,"mmmm") -> July | L63: =VLOOKUP(OrderLines!$A63,Orders!$A$1:$H$361,MATCH(OrderLines!$L$1,Orders!$A$1:$H$1,0),0) -> Dinner | M63: =VLOOKUP($A63,Orders!$A$1:$H$361,MATCH(OrderLines!$M$1,Orders!$A$1:$H$1,0),0) -> Cash | N63: =IF(AND(COUNTIFS(OrderID,$A63,Category,"hot meal")>=1,COUNTIFS(OrderID,$A63,Category,"beverage")>=1),"Combo","Single") -> Single | O63: {=IF((SUMPRODUCT((OrderID=OrderLines!$A63)*Qty*UnitPrice*DiscountPct))>40,"HighDisc","OK")} -> OK | P63: =(orderlinesTABLE[[#This Row],[UnitCost]]*orderlinesTABLE[[#This Row],[Qty]]) -> 19.55 | Q63: =(orderlinesTABLE[[#This Row],[LineNetAmount]]-orderlinesTABLE[[#This Row],[totalCOST]]) -> 14.704 | R63: =VLOOKUP($B63,Menu!$A$1:$F$20,MATCH(OrderLines!R$1,Menu!$A$1:$F$1,0),0) -> Paneer Roll | S63: {=_xlfn.TEXTJOIN("+",TRUE,_xlfn._xlws.FILTER(orderlinesTABLE[ItemName],OrderID=orderlinesTABLE[[#This Row],[OrderID]]))} -> Poha+Paneer Roll | T63: =orderlinesTABLE[[#This Row],[Profit]]/orderlinesTABLE[[#This Row],[LineNetAmount]] -> 0.42926374 | U63: =(orderlinesTABLE[[#This Row],[Qty]]*orderlinesTABLE[[#This Row],[UnitCost]]) -> 19.55 | W63: DFFYVN
... A69: O00028 | B69: D9T84A | C69: 2 | D69: =VLOOKUP($B69,Menu!$A$1:$F$20,MATCH($D$1,Menu!$A$1:$F$1,0),0) -> 116.8 | E69: =VLOOKUP($B69,Menu!$A$1:$F$20,MATCH(OrderLines!E$1,Menu!$A$1:$F$1,0),0) -> Dessert | F69: =VLOOKUP($B69,Menu!$A$1:$F$20,MATCH(OrderLines!F$1,Menu!$A$1:$F$1,0),0) -> 48.97 | G69: =VLOOKUP($A69,Orders!$A$1:$H$361,MATCH($G$1,Orders!$A$1:$H$1,0),0) -> 45840 | H69: =VLOOKUP($A69,Orders!$A$1:$H$361,MATCH(OrderLines!$H$1,Orders!$A$1:$H$1,0),0) -> Head Office Café | I69: =VLOOKUP($A69,Orders!$A$1:$H$361,MATCH(OrderLines!$I$1,Orders!$A$1:$H$1,0),0) -> 0.03 | J69: =$C69*$D69*(1-$I69) -> 226.592 | K69: =TEXT($G69,"mmmm") -> July | L69: =VLOOKUP(OrderLines!$A69,Orders!$A$1:$H$361,MATCH(OrderLines!$L$1,Orders!$A$1:$H$1,0),0) -> Breakfast | M69: =VLOOKUP($A69,Orders!$A$1:$H$361,MATCH(OrderLines!$M$1,Orders!$A$1:$H$1,0),0) -> Card | N69: =IF(AND(COUNTIFS(OrderID,$A69,Category,"hot meal")>=1,COUNTIFS(OrderID,$A69,Category,"beverage")>=1),"Combo","Single") -> Single | O69: {=IF((SUMPRODUCT((OrderID=OrderLines!$A69)*Qty*UnitPrice*DiscountPct))>40,"HighDisc","OK")} -> OK | P69: =(orderlinesTABLE[[#This Row],[UnitCost]]*orderlinesTABLE[[#This Row],[Qty]]) -> 97.94 | Q69: =(orderlinesTABLE[[#This Row],[LineNetAmount]]-orderlinesTABLE[[#This Row],[totalCOST]]) -> 128.652 | R69: =VLOOKUP($B69,Menu!$A$1:$F$20,MATCH(OrderLines!R$1,Menu!$A$1:$F$1,0),0) -> Brownie | S69: {=_xlfn.TEXTJOIN("+",TRUE,_xlfn._xlws.FILTER(orderlinesTABLE[ItemName],OrderID=orderlinesTABLE[[#This Row],[OrderID]]))} -> Masala Puff+Brownie+Veg Sandwich+Nimbu Pani | T69: =orderlinesTABLE[[#This Row],[Profit]]/orderlinesTABLE[[#This Row],[LineNetAmount]] -> 0.56776938 | U69: =(orderlinesTABLE[[#This Row],[Qty]]*orderlinesTABLE[[#This Row],[UnitCost]]) -> 97.94 | W69: S5NQ4F
A70: O00028 | B70: SCKW5N | C70: 1 | D70: =VLOOKUP($B70,Menu!$A$1:$F$20,MATCH($D$1,Menu!$A$1:$F$1,0),0) -> 70.54 | E70: =VLOOKUP($B70,Menu!$A$1:$F$20,MATCH(OrderLines!E$1,Menu!$A$1:$F$1,0),0) -> Snack | F70: =VLOOKUP($B70,Menu!$A$1:$F$20,MATCH(OrderLines!F$1,Menu!$A$1:$F$1,0),0) -> 35.81 | G70: =VLOOKUP($A70,Orders!$A$1:$H$361,MATCH($G$1,Orders!$A$1:$H$1,0),0) -> 45840 | H70: =VLOOKUP($A70,Orders!$A$1:$H$361,MATCH(OrderLines!$H$1,Orders!$A$1:$H$1,0),0) -> Head Office Café | I70: =VLOOKUP($A70,Orders!$A$1:$H$361,MATCH(OrderLines!$I$1,Orders!$A$1:$H$1,0),0) -> 0.03 | J70: =$C70*$D70*(1-$I70) -> 68.4238 | K70: =TEXT($G70,"mmmm") -> July | L70: =VLOOKUP(OrderLines!$A70,Orders!$A$1:$H$361,MATCH(OrderLines!$L$1,Orders!$A$1:$H$1,0),0) -> Breakfast | M70: =VLOOKUP($A70,Orders!$A$1:$H$361,MATCH(OrderLines!$M$1,Orders!$A$1:$H$1,0),0) -> Card | N70: =IF(AND(COUNTIFS(OrderID,$A70,Category,"hot meal")>=1,COUNTIFS(OrderID,$A70,Category,"beverage")>=1),"Combo","Single") -> Single | O70: {=IF((SUMPRODUCT((OrderID=OrderLines!$A70)*Qty*UnitPrice*DiscountPct))>40,"HighDisc","OK")} -> OK | P70: =(orderlinesTABLE[[#This Row],[UnitCost]]*orderlinesTABLE[[#This Row],[Qty]]) -> 35.81 | Q70: =(orderlinesTABLE[[#This Row],[LineNetAmount]]-orderlinesTABLE[[#This Row],[totalCOST]]) -> 32.6138 | R70: =VLOOKUP($B70,Menu!$A$1:$F$20,MATCH(OrderLines!R$1,Menu!$A$1:$F$1,0),0) -> Veg Sandwich | S70: {=_xlfn.TEXTJOIN("+",TRUE,_xlfn._xlws.FILTER(orderlinesTABLE[ItemName],OrderID=orderlinesTABLE[[#This Row],[OrderID]]))} -> Masala Puff+Brownie+Veg Sandwich+Nimbu Pani | T70: =orderlinesTABLE[[#This Row],[Profit]]/orderlinesTABLE[[#This Row],[LineNetAmount]] -> 0.47664409 | U70: =(orderlinesTABLE[[#This Row],[Qty]]*orderlinesTABLE[[#This Row],[UnitCost]]) -> 35.81
A71: O00028 | B71: BXO6QJ | C71: 2 | D71: =VLOOKUP($B71,Menu!$A$1:$F$20,MATCH($D$1,Menu!$A$1:$F$1,0),0) -> 20.11 | E71: =VLOOKUP($B71,Menu!$A$1:$F$20,MATCH(OrderLines!E$1,Menu!$A$1:$F$1,0),0) -> Beverage | F71: =VLOOKUP($B71,Menu!$A$1:$F$20,MATCH(OrderLines!F$1,Menu!$A$1:$F$1,0),0) -> 8 | G71: =VLOOKUP($A71,Orders!$A$1:$H$361,MATCH($G$1,Orders!$A$1:$H$1,0),0) -> 45840 | H71: =VLOOKUP($A71,Orders!$A$1:$H$361,MATCH(OrderLines!$H$1,Orders!$A$1:$H$1,0),0) -> Head Office Café | I71: =VLOOKUP($A71,Orders!$A$1:$H$361,MATCH(OrderLines!$I$1,Orders!$A$1:$H$1,0),0) -> 0.03 | J71: =$C71*$D71*(1-$I71) -> 39.0134 | K71: =TEXT($G71,"mmmm") -> July | L71: =VLOOKUP(OrderLines!$A71,Orders!$A$1:$H$361,MATCH(OrderLines!$L$1,Orders!$A$1:$H$1,0),0) -> Breakfast | M71: =VLOOKUP($A71,Orders!$A$1:$H$361,MATCH(OrderLines!$M$1,Orders!$A$1:$H$1,0),0) -> Card | N71: =IF(AND(COUNTIFS(OrderID,$A71,Category,"hot meal")>=1,COUNTIFS(OrderID,$A71,Category,"beverage")>=1),"Combo","Single") -> Single | O71: {=IF((SUMPRODUCT((OrderID=OrderLines!$A71)*Qty*UnitPrice*DiscountPct))>40,"HighDisc","OK")} -> OK | P71: =(orderlinesTABLE[[#This Row],[UnitCost]]*orderlinesTABLE[[#This Row],[Qty]]) -> 16 | Q71: =(orderlinesTABLE[[#This Row],[LineNetAmount]]-orderlinesTABLE[[#This Row],[totalCOST]]) -> 23.0134 | R71: =VLOOKUP($B71,Menu!$A$1:$F$20,MATCH(OrderLines!R$1,Menu!$A$1:$F$1,0),0) -> Nimbu Pani | S71: {=_xlfn.TEXTJOIN("+",TRUE,_xlfn._xlws.FILTER(orderlinesTABLE[ItemName],OrderID=orderlinesTABLE[[#This Row],[OrderID]]))} -> Masala Puff+Brownie+Veg Sandwich+Nimbu Pani | T71: =orderlinesTABLE[[#This Row],[Profit]]/orderlinesTABLE[[#This Row],[LineNetAmount]] -> 0.5898845 | U71: =(orderlinesTABLE[[#This Row],[Qty]]*orderlinesTABLE[[#This Row],[UnitCost]]) -> 16
A72: O00029 | B72: S5NQ4F | C72: 3 | D72: =VLOOKUP($B72,Menu!$A$1:$F$20,MATCH($D$1,Menu!$A$1:$F$1,0),0) -> 50.19 | E72: =VLOOKUP($B72,Menu!$A$1:$F$20,MATCH(OrderLines!E$1,Menu!$A$1:$F$1,0),0) -> Snack | F72: =VLOOKUP($B72,Menu!$A$1:$F$20,MATCH(OrderLines!F$1,Menu!$A$1:$F$1,0),0) -> 22.61 | G72: =VLOOKUP($A72,Orders!$A$1:$H$361,MATCH($G$1,Orders!$A$1:$H$1,0),0) -> 45852 | H72: =VLOOKUP($A72,Orders!$A$1:$H$361,MATCH(OrderLines!$H$1,Orders!$A$1:$H$1,0),0) -> Plant 2 Canteen | I72: =VLOOKUP($A72,Orders!$A$1:$H$361,MATCH(OrderLines!$I$1,Orders!$A$1:$H$1,0),0) -> 0.07 | J72: =$C72*$D72*(1-$I72) -> 140.0301 | K72: =TEXT($G72,"mmmm") -> July | L72: =VLOOKUP(OrderLines!$A72,Orders!$A$1:$H$361,MATCH(OrderLines!$L$1,Orders!$A$1:$H$1,0),0) -> Breakfast | M72: =VLOOKUP($A72,Orders!$A$1:$H$361,MATCH(OrderLines!$M$1,Orders!$A$1:$H$1,0),0) -> Cash | N72: =IF(AND(COUNTIFS(OrderID,$A72,Category,"hot meal")>=1,COUNTIFS(OrderID,$A72,Category,"beverage")>=1),"Combo","Single") -> Single | O72: {=IF((SUMPRODUCT((OrderID=OrderLines!$A72)*Qty*UnitPrice*DiscountPct))>40,"HighDisc","OK")} -> OK | P72: =(orderlinesTABLE[[#This Row],[UnitCost]]*orderlinesTABLE[[#This Row],[Qty]]) -> 67.83 | Q72: =(orderlinesTABLE[[#This Row],[LineNetAmount]]-orderlinesTABLE[[#This Row],[totalCOST]]) -> 72.2001 | R72: =VLOOKUP($B72,Menu!$A$1:$F$20,MATCH(OrderLines!R$1,Menu!$A$1:$F$1,0),0) -> Masala Puff | S72: {=_xlfn.TEXTJOIN("+",TRUE,_xlfn._xlws.FILTER(orderlinesTABLE[ItemName],OrderID=orderlinesTABLE[[#This Row],[OrderID]]))} -> Masala Puff | T72: =orderlinesTABLE[[#This Row],[Profit]]/orderlinesTABLE[[#This Row],[LineNetAmount]] -> 0.51560415 | U72: =(orderlinesTABLE[[#This Row],[Qty]]*orderlinesTABLE[[#This Row],[UnitCost]]) -> 67.83
A73: O00030 | B73: B0T0PV | C73: 1 | D73: =VLOOKUP($B73,Menu!$A$1:$F$20,MATCH($D$1,Menu!$A$1:$F$1,0),0) -> 28.43 | E73: =VLOOKUP($B73,Menu!$A$1:$F$20,MATCH(OrderLines!E$1,Menu!$A$1:$F$1,0),0) -> Beverage | F73: =VLOOKUP($B73,Menu!$A$1:$F$20,MATCH(OrderLines!F$1,Menu!$A$1:$F$1,0),0) -> 13.89 | G73: =VLOOKUP($A73,Orders!$A$1:$H$361,MATCH($G$1,Orders!$A$1:$H$1,0),0) -> 45854 | H73: =VLOOKUP($A73,Orders!$A$1:$H$361,MATCH(OrderLines!$H$1,Orders!$A$1:$H$1,0),0) -> Plant 2 Canteen | I73: =VLOOKUP($A73,Orders!$A$1:$H$361,MATCH(OrderLines!$I$1,Orders!$A$1:$H$1,0),0) -> 0.12 | J73: =$C73*$D73*(1-$I73) -> 25.0184 | K73: =TEXT($G73,"mmmm") -> July | L73: =VLOOKUP(OrderLines!$A73,Orders!$A$1:$H$361,MATCH(OrderLines!$L$1,Orders!$A$1:$H$1,0),0) -> Breakfast | M73: =VLOOKUP($A73,Orders!$A$1:$H$361,MATCH(OrderLines!$M$1,Orders!$A$1:$H$1,0),0) -> UPI | N73: =IF(AND(COUNTIFS(OrderID,$A73,Category,"hot meal")>=1,COUNTIFS(OrderID,$A73,Category,"beverage")>=1),"Combo","Single") -> Combo | O73: {=IF((SUMPRODUCT((OrderID=OrderLines!$A73)*Qty*UnitPrice*DiscountPct))>40,"HighDisc","OK")} -> HighDisc | P73: =(orderlinesTABLE[[#This Row],[UnitCost]]*orderlinesTABLE[[#This Row],[Qty]]) -> 13.89 | Q73: =(orderlinesTABLE[[#This Row],[LineNetAmount]]-orderlinesTABLE[[#This Row],[totalCOST]]) -> 11.1284 | R73: =VLOOKUP($B73,Menu!$A$1:$F$20,MATCH(OrderLines!R$1,Menu!$A$1:$F$1,0),0) -> Bottled Water | S73: {=_xlfn.TEXTJOIN("+",TRUE,_xlfn._xlws.FILTER(orderlinesTABLE[ItemName],OrderID=orderlinesTABLE[[#This Row],[OrderID]]))} -> Bottled Water+Egg Curry + Rice+Veg Sandwich | T73: =orderlinesTABLE[[#This Row],[Profit]]/orderlinesTABLE[[#This Row],[LineNetAmount]] -> 0.44480862 | U73: =(orderlinesTABLE[[#This Row],[Qty]]*orderlinesTABLE[[#This Row],[UnitCost]]) -> 13.89
A74: O00030 | B74: HH1DNM | C74: 1 | D74: =VLOOKUP($B74,Menu!$A$1:$F$20,MATCH($D$1,Menu!$A$1:$F$1,0),0) -> 246.09 | E74: =VLOOKUP($B74,Menu!$A$1:$F$20,MATCH(OrderLines!E$1,Menu!$A$1:$F$1,0),0) -> Hot Meal | F74: =VLOOKUP($B74,Menu!$A$1:$F$20,MATCH(OrderLines!F$1,Menu!$A$1:$F$1,0),0) -> 112.08 | G74: =VLOOKUP($A74,Orders!$A$1:$H$361,MATCH($G$1,Orders!$A$1:$H$1,0),0) -> 45854 | H74: =VLOOKUP($A74,Orders!$A$1:$H$361,MATCH(OrderLines!$H$1,Orders!$A$1:$H$1,0),0) -> Plant 2 Canteen | I74: =VLOOKUP($A74,Orders!$A$1:$H$361,MATCH(OrderLines!$I$1,Orders!$A$1:$H$1,0),0) -> 0.12 | J74: =$C74*$D74*(1-$I74) -> 216.5592 | K74: =TEXT($G74,"mmmm") -> July | L74: =VLOOKUP(OrderLines!$A74,Orders!$A$1:$H$361,MATCH(OrderLines!$L$1,Orders!$A$1:$H$1,0),0) -> Breakfast | M74: =VLOOKUP($A74,Orders!$A$1:$H$361,MATCH(OrderLines!$M$1,Orders!$A$1:$H$1,0),0) -> UPI | N74: =IF(AND(COUNTIFS(OrderID,$A74,Category,"hot meal")>=1,COUNTIFS(OrderID,$A74,Category,"beverage")>=1),"Combo","Single") -> Combo | O74: {=IF((SUMPRODUCT((OrderID=OrderLines!$A74)*Qty*UnitPrice*DiscountPct))>40,"HighDisc","OK")} -> HighDisc | P74: =(orderlinesTABLE[[#This Row],[UnitCost]]*orderlinesTABLE[[#This Row],[Qty]]) -> 112.08 | Q74: =(orderlinesTABLE[[#This Row],[LineNetAmount]]-orderlinesTABLE[[#This Row],[totalCOST]]) -> 104.4792 | R74: =VLOOKUP($B74,Menu!$A$1:$F$20,MATCH(OrderLines!R$1,Menu!$A$1:$F$1,0),0) -> Egg Curry + Rice | S74: {=_xlfn.TEXTJOIN("+",TRUE,_xlfn._xlws.FILTER(orderlinesTABLE[ItemName],OrderID=orderlinesTABLE[[#This Row],[OrderID]]))} -> Bottled Water+Egg Curry + Rice+Veg Sandwich | T74: =orderlinesTABLE[[#This Row],[Profit]]/orderlinesTABLE[[#This Row],[LineNetAmount]] -> 0.48245099 | U74: =(orderlinesTABLE[[#This Row],[Qty]]*orderlinesTABLE[[#This Row],[UnitCost]]) -> 112.08
A75: O00030 | B75: SCKW5N | C75: 2 | D75: =VLOOKUP($B75,Menu!$A$1:$F$20,MATCH($D$1,Menu!$A$1:$F$1,0),0) -> 70.54 | E75: =VLOOKUP($B75,Menu!$A$1:$F$20,MATCH(OrderLines!E$1,Menu!$A$1:$F$1,0),0) -> Snack | F75: =VLOOKUP($B75,Menu!$A$1:$F$20,MATCH(OrderLines!F$1,Menu!$A$1:$F$1,0),0) -> 35.81 | G75: =VLOOKUP($A75,Orders!$A$1:$H$361,MATCH($G$1,Orders!$A$1:$H$1,0),0) -> 45854 | H75: =VLOOKUP($A75,Orders!$A$1:$H$361,MATCH(OrderLines!$H$1,Orders!$A$1:$H$1,0),0) -> Plant 2 Canteen | I75: =VLOOKUP($A75,Orders!$A$1:$H$361,MATCH(OrderLines!$I$1,Orders!$A$1:$H$1,0),0) -> 0.12 | J75: =$C75*$D75*(1-$I75) -> 124.1504 | K75: =TEXT($G75,"mmmm") -> July | L75: =VLOOKUP(OrderLines!$A75,Orders!$A$1:$H$361,MATCH(OrderLines!$L$1,Orders!$A$1:$H$1,0),0) -> Breakfast | M75: =VLOOKUP($A75,Orders!$A$1:$H$361,MATCH(OrderLines!$M$1,Orders!$A$1:$H$1,0),0) -> UPI | N75: =IF(AND(COUNTIFS(OrderID,$A75,Category,"hot meal")>=1,COUNTIFS(OrderID,$A75,Category,"beverage")>=1),"Combo","Single") -> Combo | O75: {=IF((SUMPRODUCT((OrderID=OrderLines!$A75)*Qty*UnitPrice*DiscountPct))>40,"HighDisc","OK")} -> HighDisc | P75: =(orderlinesTABLE[[#This Row],[UnitCost]]*orderlinesTABLE[[#This Row],[Qty]]) -> 71.62 | Q75: =(orderlinesTABLE[[#This Row],[LineNetAmount]]-orderlinesTABLE[[#This Row],[totalCOST]]) -> 52.5304 | R75: =VLOOKUP($B75,Menu!$A$1:$F$20,MATCH(OrderLines!R$1,Menu!$A$1:$F$1,0),0) -> Veg Sandwich | S75: {=_xlfn.TEXTJOIN("+",TRUE,_xlfn._xlws.FILTER(orderlinesTABLE[ItemName],OrderID=orderlinesTABLE[[#This Row],[OrderID]]))} -> Bottled Water+Egg Curry + Rice+Veg Sandwich | T75: =orderlinesTABLE[[#This Row],[Profit]]/orderlinesTABLE[[#This Row],[LineNetAmount]] -> 0.42311906 | U75: =(orderlinesTABLE[[#This Row],[Qty]]*orderlinesTABLE[[#This Row],[UnitCost]]) -> 71.62
A76: O00031 | B76: DFFYVN | C76: 1 | D76: =VLOOKUP($B76,Menu!$A$1:$F$20,MATCH($D$1,Menu!$A$1:$F$1,0),0) -> 54.2 | E76: =VLOOKUP($B76,Menu!$A$1:$F$20,MATCH(OrderLines!E$1,Menu!$A$1:$F$1,0),0) -> Dessert | F76: =VLOOKUP($B76,Menu!$A$1:$F$20,MATCH(OrderLines!F$1,Menu!$A$1:$F$1,0),0) -> 21.95 | G76: =VLOOKUP($A76,Orders!$A$1:$H$361,MATCH($G$1,Orders!$A$1:$H$1,0),0) -> 45872 | H76: =VLOOKUP($A76,Orders!$A$1:$H$361,MATCH(OrderLines!$H$1,Orders!$A$1:$H$1,0),0) -> Plant 1 Canteen | I76: =VLOOKUP($A76,Orders!$A$1:$H$361,MATCH(OrderLines!$I$1,Orders!$A$1:$H$1,0),0) -> 0.06 | J76: =$C76*$D76*(1-$I76) -> 50.948 | K76: =TEXT($G76,"mmmm") -> August | L76: =VLOOKUP(OrderLines!$A76,Orders!$A$1:$H$361,MATCH(OrderLines!$L$1,Orders!$A$1:$H$1,0),0) -> Lunch | M76: =VLOOKUP($A76,Orders!$A$1:$H$361,MATCH(OrderLines!$M$1,Orders!$A$1:$H$1,0),0) -> UPI | N76: =IF(AND(COUNTIFS(OrderID,$A76,Category,"hot meal")>=1,COUNTIFS(OrderID,$A76,Category,"beverage")>=1),"Combo","Single") -> Single | O76: {=IF((SUMPRODUCT((OrderID=OrderLines!$A76)*Qty*UnitPrice*DiscountPct))>40,"HighDisc","OK")} -> OK | P76: =(orderlinesTABLE[[#This Row],[UnitCost]]*orderlinesTABLE[[#This Row],[Qty]]) -> 21.95 | Q76: =(orderlinesTABLE[[#This Row],[LineNetAmount]]-orderlinesTABLE[[#This Row],[totalCOST]]) -> 28.998 | R76: =VLOOKUP($B76,Menu!$A$1:$F$20,MATCH(OrderLines!R$1,Menu!$A$1:$F$1,0),0) -> Kheer Cup | S76: {=_xlfn.TEXTJOIN("+",TRUE,_xlfn._xlws.FILTER(orderlinesTABLE[ItemName],OrderID=orderlinesTABLE[[#This Row],[OrderID]]))} -> Kheer Cup+Rajma Chawal+Brownie | T76: =orderlinesTABLE[[#This Row],[Profit]]/orderlinesTABLE[[#This Row],[LineNetAmount]] -> 0.56916856 | U76: =(orderlinesTABLE[[#This Row],[Qty]]*orderlinesTABLE[[#This Row],[UnitCost]]) -> 21.95 | Y76: {=_xlfn._xlws.SORT(_xlfn.UNIQUE(_xlfn._xlws.FILTER(Category,OrderID=A5)))} -> Beverage
A77: O00031 | B77: HUZZPQ | C77: 2 | D77: =VLOOKUP($B77,Menu!$A$1:$F$20,MATCH($D$1,Menu!$A$1:$F$1,0),0) -> 146.4 | E77: =VLOOKUP($B77,Menu!$A$1:$F$20,MATCH(OrderLines!E$1,Menu!$A$1:$F$1,0),0) -> Hot Meal | F77: =VLOOKUP($B77,Menu!$A$1:$F$20,MATCH(OrderLines!F$1,Menu!$A$1:$F$1,0),0) -> 80.92 | G77: =VLOOKUP($A77,Orders!$A$1:$H$361,MATCH($G$1,Orders!$A$1:$H$1,0),0) -> 45872 | H77: =VLOOKUP($A77,Orders!$A$1:$H$361,MATCH(OrderLines!$H$1,Orders!$A$1:$H$1,0),0) -> Plant 1 Canteen | I77: =VLOOKUP($A77,Orders!$A$1:$H$361,MATCH(OrderLines!$I$1,Orders!$A$1:$H$1,0),0) -> 0.06 | J77: =$C77*$D77*(1-$I77) -> 275.232 | K77: =TEXT($G77,"mmmm") -> August | L77: =VLOOKUP(OrderLines!$A77,Orders!$A$1:$H$361,MATCH(OrderLines!$L$1,Orders!$A$1:$H$1,0),0) -> Lunch | M77: =VLOOKUP($A77,Orders!$A$1:$H$361,MATCH(OrderLines!$M$1,Orders!$A$1:$H$1,0),0) -> UPI | N77: =IF(AND(COUNTIFS(OrderID,$A77,Category,"hot meal")>=1,COUNTIFS(OrderID,$A77,Category,"beverage")>=1),"Combo","Single") -> Single | O77: {=IF((SUMPRODUCT((OrderID=OrderLines!$A77)*Qty*UnitPrice*DiscountPct))>40,"HighDisc","OK")} -> OK | P77: =(orderlinesTABLE[[#This Row],[UnitCost]]*orderlinesTABLE[[#This Row],[Qty]]) -> 161.84 | Q77: =(orderlinesTABLE[[#This Row],[LineNetAmount]]-orderlinesTABLE[[#This Row],[totalCOST]]) -> 113.392 | R77: =VLOOKUP($B77,Menu!$A$1:$F$20,MATCH(OrderLines!R$1,Menu!$A$1:$F$1,0),0) -> Rajma Chawal | S77: {=_xlfn.TEXTJOIN("+",TRUE,_xlfn._xlws.FILTER(orderlinesTABLE[ItemName],OrderID=orderlinesTABLE[[#This Row],[OrderID]]))} -> Kheer Cup+Rajma Chawal+Brownie | T77: =orderlinesTABLE[[#This Row],[Profit]]/orderlinesTABLE[[#This Row],[LineNetAmount]] -> 0.41198698 | U77: =(orderlinesTABLE[[#This Row],[Qty]]*orderlinesTABLE[[#This Row],[UnitCost]]) -> 161.84 | Y77: Hot Meal
A78: O00031 | B78: D9T84A | C78: 1 | D78: =VLOOKUP($B78,Menu!$A$1:$F$20,MATCH($D$1,Menu!$A$1:$F$1,0),0) -> 116.8 | E78: =VLOOKUP($B78,Menu!$A$1:$F$20,MATCH(OrderLines!E$1,Menu!$A$1:$F$1,0),0) -> Dessert | F78: =VLOOKUP($B78,Menu!$A$1:$F$20,MATCH(OrderLines!F$1,Menu!$A$1:$F$1,0),0) -> 48.97 | G78: =VLOOKUP($A78,Orders!$A$1:$H$361,MATCH($G$1,Orders!$A$1:$H$1,0),0) -> 45872 | H78: =VLOOKUP($A78,Orders!$A$1:$H$361,MATCH(OrderLines!$H$1,Orders!$A$1:$H$1,0),0) -> Plant 1 Canteen | I78: =VLOOKUP($A78,Orders!$A$1:$H$361,MATCH(OrderLines!$I$1,Orders!$A$1:$H$1,0),0) -> 0.06 | J78: =$C78*$D78*(1-$I78) -> 109.792 | K78: =TEXT($G78,"mmmm") -> August | L78: =VLOOKUP(OrderLines!$A78,Orders!$A$1:$H$361,MATCH(OrderLines!$L$1,Orders!$A$1:$H$1,0),0) -> Lunch | M78: =VLOOKUP($A78,Orders!$A$1:$H$361,MATCH(OrderLines!$M$1,Orders!$A$1:$H$1,0),0) -> UPI | N78: =IF(AND(COUNTIFS(OrderID,$A78,Category,"hot meal")>=1,COUNTIFS(OrderID,$A78,Category,"beverage")>=1),"Combo","Single") -> Single | O78: {=IF((SUMPRODUCT((OrderID=OrderLines!$A78)*Qty*UnitPrice*DiscountPct))>40,"HighDisc","OK")} -> OK | P78: =(orderlinesTABLE[[#This Row],[UnitCost]]*orderlinesTABLE[[#This Row],[Qty]]) -> 48.97 | Q78: =(orderlinesTABLE[[#This Row],[LineNetAmount]]-orderlinesTABLE[[#This Row],[totalCOST]]) -> 60.822 | R78: =VLOOKUP($B78,Menu!$A$1:$F$20,MATCH(OrderLines!R$1,Menu!$A$1:$F$1,0),0) -> Brownie | S78: {=_xlfn.TEXTJOIN("+",TRUE,_xlfn._xlws.FILTER(orderlinesTABLE[ItemName],OrderID=orderlinesTABLE[[#This Row],[OrderID]]))} -> Kheer Cup+Rajma Chawal+Brownie | T78: =orderlinesTABLE[[#This Row],[Profit]]/orderlinesTABLE[[#This Row],[LineNetAmount]] -> 0.55397479 | U78: =(orderlinesTABLE[[#This Row],[Qty]]*orderlinesTABLE[[#This Row],[UnitCost]]) -> 48.97 | Y78: Snack
A79: O00032 | B79: DFFYVN | C79: 1 | D79: =VLOOKUP($B79,Menu!$A$1:$F$20,MATCH($D$1,Menu!$A$1:$F$1,0),0) -> 54.2 | E79: =VLOOKUP($B79,Menu!$A$1:$F$20,MATCH(OrderLines!E$1,Menu!$A$1:$F$1,0),0) -> Dessert | F79: =VLOOKUP($B79,Menu!$A$1:$F$20,MATCH(OrderLines!F$1,Menu!$A$1:$F$1,0),0) -> 21.95 | G79: =VLOOKUP($A79,Orders!$A$1:$H$361,MATCH($G$1,Orders!$A$1:$H$1,0),0) -> 45888 | H79: =VLOOKUP($A79,Orders!$A$1:$H$361,MATCH(OrderLines!$H$1,Orders!$A$1:$H$1,0),0) -> Plant 2 Canteen | I79: =VLOOKUP($A79,Orders!$A$1:$H$361,MATCH(OrderLines!$I$1,Orders!$A$1:$H$1,0),0) -> 0.12 | J79: =$C79*$D79*(1-$I79) -> 47.696 | K79: =TEXT($G79,"mmmm") -> August | L79: =VLOOKUP(OrderLines!$A79,Orders!$A$1:$H$361,MATCH(OrderLines!$L$1,Orders!$A$1:$H$1,0),0) -> Breakfast | M79: =VLOOKUP($A79,Orders!$A$1:$H$361,MATCH(OrderLines!$M$1,Orders!$A$1:$H$1,0),0) -> Cash | N79: =IF(AND(COUNTIFS(OrderID,$A79,Category,"hot meal")>=1,COUNTIFS(OrderID,$A79,Category,"beverage")>=1),"Combo","Single") -> Combo | O79: {=IF((SUMPRODUCT((OrderID=OrderLines!$A79)*Qty*UnitPrice*DiscountPct))>40,"HighDisc","OK")} -> HighDisc | P79: =(orderlinesTABLE[[#This Row],[UnitCost]]*orderlinesTABLE[[#This Row],[Qty]]) -> 21.95 | Q79: =(orderlinesTABLE[[#This Row],[LineNetAmount]]-orderlinesTABLE[[#This Row],[totalCOST]]) -> 25.746 | R79: =VLOOKUP($B79,Menu!$A$1:$F$20,MATCH(OrderLines!R$1,Menu!$A$1:$F$1,0),0) -> Kheer Cup | S79: {=_xlfn.TEXTJOIN("+",TRUE,_xlfn._xlws.FILTER(orderlinesTABLE[ItemName],OrderID=orderlinesTABLE[[#This Row],[OrderID]]))} -> Kheer Cup+Brownie+Masala Chaas+Rajma Chawal | T79: =orderlinesTABLE[[#This Row],[Profit]]/orderlinesTABLE[[#This Row],[LineNetAmount]] -> 0.53979369 | U79: =(orderlinesTABLE[[#This Row],[Qty]]*orderlinesTABLE[[#This Row],[UnitCost]]) -> 21.95
A80: O00032 | B80: D9T84A | C80: 1 | D80: =VLOOKUP($B80,Menu!$A$1:$F$20,MATCH($D$1,Menu!$A$1:$F$1,0),0) -> 116.8 | E80: =VLOOKUP($B80,Menu!$A$1:$F$20,MATCH(OrderLines!E$1,Menu!$A$1:$F$1,0),0) -> Dessert | F80: =VLOOKUP($B80,Menu!$A$1:$F$20,MATCH(OrderLines!F$1,Menu!$A$1:$F$1,0),0) -> 48.97 | G80: =VLOOKUP($A80,Orders!$A$1:$H$361,MATCH($G$1,Orders!$A$1:$H$1,0),0) -> 45888 | H80: =VLOOKUP($A80,Orders!$A$1:$H$361,MATCH(OrderLines!$H$1,Orders!$A$1:$H$1,0),0) -> Plant 2 Canteen | I80: =VLOOKUP($A80,Orders!$A$1:$H$361,MATCH(OrderLines!$I$1,Orders!$A$1:$H$1,0),0) -> 0.12 | J80: =$C80*$D80*(1-$I80) -> 102.784 | K80: =TEXT($G80,"mmmm") -> August | L80: =VLOOKUP(OrderLines!$A80,Orders!$A$1:$H$361,MATCH(OrderLines!$L$1,Orders!$A$1:$H$1,0),0) -> Breakfast | M80: =VLOOKUP($A80,Orders!$A$1:$H$361,MATCH(OrderLines!$M$1,Orders!$A$1:$H$1,0),0) -> Cash | N80: =IF(AND(COUNTIFS(OrderID,$A80,Category,"hot meal")>=1,COUNTIFS(OrderID,$A80,Category,"beverage")>=1),"Combo","Single") -> Combo | O80: {=IF((SUMPRODUCT((OrderID=OrderLines!$A80)*Qty*UnitPrice*DiscountPct))>40,"HighDisc","OK")} -> HighDisc | P80: =(orderlinesTABLE[[#This Row],[UnitCost]]*orderlinesTABLE[[#This Row],[Qty]]) -> 48.97 | Q80: =(orderlinesTABLE[[#This Row],[LineNetAmount]]-orderlinesTABLE[[#This Row],[totalCOST]]) -> 53.814 | R80: =VLOOKUP($B80,Menu!$A$1:$F$20,MATCH(OrderLines!R$1,Menu!$A$1:$F$1,0),0) -> Brownie | S80: {=_xlfn.TEXTJOIN("+",TRUE,_xlfn._xlws.FILTER(orderlinesTABLE[ItemName],OrderID=orderlinesTABLE[[#This Row],[OrderID]]))} -> Kheer Cup+Brownie+Masala Chaas+Rajma Chawal | T80: =orderlinesTABLE[[#This Row],[Profit]]/orderlinesTABLE[[#This Row],[LineNetAmount]] -> 0.52356398 | U80: =(orderlinesTABLE[[#This Row],[Qty]]*orderlinesTABLE[[#This Row],[UnitCost]]) -> 48.97
A81: O00032 | B81: BOC6UZ | C81: 2 | D81: =VLOOKUP($B81,Menu!$A$1:$F$20,MATCH($D$1,Menu!$A$1:$F$1,0),0) -> 32.98 | E81: =VLOOKUP($B81,Menu!$A$1:$F$20,MATCH(OrderLines!E$1,Menu!$A$1:$F$1,0),0) -> Beverage | F81: =VLOOKUP($B81,Menu!$A$1:$F$20,MATCH(OrderLines!F$1,Menu!$A$1:$F$1,0),0) -> 11.84 | G81: =VLOOKUP($A81,Orders!$A$1:$H$361,MATCH($G$1,Orders!$A$1:$H$1,0),0) -> 45888 | H81: =VLOOKUP($A81,Orders!$A$1:$H$361,MATCH(OrderLines!$H$1,Orders!$A$1:$H$1,0),0) -> Plant 2 Canteen | I81: =VLOOKUP($A81,Orders!$A$1:$H$361,MATCH(OrderLines!$I$1,Orders!$A$1:$H$1,0),0) -> 0.12 | J81: =$C81*$D81*(1-$I81) -> 58.0448 | K81: =TEXT($G81,"mmmm") -> August | L81: =VLOOKUP(OrderLines!$A81,Orders!$A$1:$H$361,MATCH(OrderLines!$L$1,Orders!$A$1:$H$1,0),0) -> Breakfast | M81: =VLOOKUP($A81,Orders!$A$1:$H$361,MATCH(OrderLines!$M$1,Orders!$A$1:$H$1,0),0) -> Cash | N81: =IF(AND(COUNTIFS(OrderID,$A81,Category,"hot meal")>=1,COUNTIFS(OrderID,$A81,Category,"beverage")>=1),"Combo","Single") -> Combo | O81: {=IF((SUMPRODUCT((OrderID=OrderLines!$A81)*Qty*UnitPrice*DiscountPct))>40,"HighDisc","OK")} -> HighDisc | P81: =(orderlinesTABLE[[#This Row],[UnitCost]]*orderlinesTABLE[[#This Row],[Qty]]) -> 23.68 | Q81: =(orderlinesTABLE[[#This Row],[LineNetAmount]]-orderlinesTABLE[[#This Row],[totalCOST]]) -> 34.3648 | R81: =VLOOKUP($B81,Menu!$A$1:$F$20,MATCH(OrderLines!R$1,Menu!$A$1:$F$1,0),0) -> Masala Chaas | S81: {=_xlfn.TEXTJOIN("+",TRUE,_xlfn._xlws.FILTER(orderlinesTABLE[ItemName],OrderID=orderlinesTABLE[[#This Row],[OrderID]]))} -> Kheer Cup+Brownie+Masala Chaas+Rajma Chawal | T81: =orderlinesTABLE[[#This Row],[Profit]]/orderlinesTABLE[[#This Row],[LineNetAmount]] -> 0.59203925 | U81: =(orderlinesTABLE[[#This Row],[Qty]]*orderlinesTABLE[[#This Row],[UnitCost]]) -> 23.68
A82: O00032 | B82: HUZZPQ | C82: 2 | D82: =VLOOKUP($B82,Menu!$A$1:$F$20,MATCH($D$1,Menu!$A$1:$F$1,0),0) -> 146.4 | E82: =VLOOKUP($B82,Menu!$A$1:$F$20,MATCH(OrderLines!E$1,Menu!$A$1:$F$1,0),0) -> Hot Meal | F82: =VLOOKUP($B82,Menu!$A$1:$F$20,MATCH(OrderLines!F$1,Menu!$A$1:$F$1,0),0) -> 80.92 | G82: =VLOOKUP($A82,Orders!$A$1:$H$361,MATCH($G$1,Orders!$A$1:$H$1,0),0) -> 45888 | H82: =VLOOKUP($A82,Orders!$A$1:$H$361,MATCH(OrderLines!$H$1,Orders!$A$1:$H$1,0),0) -> Plant 2 Canteen | I82: =VLOOKUP($A82,Orders!$A$1:$H$361,MATCH(OrderLines!$I$1,Orders!$A$1:$H$1,0),0) -> 0.12 | J82: =$C82*$D82*(1-$I82) -> 257.664 | K82: =TEXT($G82,"mmmm") -> August | L82: =VLOOKUP(OrderLines!$A82,Orders!$A$1:$H$361,MATCH(OrderLines!$L$1,Orders!$A$1:$H$1,0),0) -> Breakfast | M82: =VLOOKUP($A82,Orders!$A$1:$H$361,MATCH(OrderLines!$M$1,Orders!$A$1:$H$1,0),0) -> Cash | N82: =IF(AND(COUNTIFS(OrderID,$A82,Category,"hot meal")>=1,COUNTIFS(OrderID,$A82,Category,"beverage")>=1),"Combo","Single") -> Combo | O82: {=IF((SUMPRODUCT((OrderID=OrderLines!$A82)*Qty*UnitPrice*DiscountPct))>40,"HighDisc","OK")} -> HighDisc | P82: =(orderlinesTABLE[[#This Row],[UnitCost]]*orderlinesTABLE[[#This Row],[Qty]]) -> 161.84 | Q82: =(orderlinesTABLE[[#This Row],[LineNetAmount]]-orderlinesTABLE[[#This Row],[totalCOST]]) -> 95.824 | R82: =VLOOKUP($B82,Menu!$A$1:$F$20,MATCH(OrderLines!R$1,Menu!$A$1:$F$1,0),0) -> Rajma Chawal | S82: {=_xlfn.TEXTJOIN("+",TRUE,_xlfn._xlws.FILTER(orderlinesTABLE[ItemName],OrderID=orderlinesTABLE[[#This Row],[OrderID]]))} -> Kheer Cup+Brownie+Masala Chaas+Rajma Chawal | T82: =orderlinesTABLE[[#This Row],[Profit]]/orderlinesTABLE[[#This Row],[LineNetAmount]] -> 0.37189518 | U82: =(orderlinesTABLE[[#This Row],[Qty]]*orderlinesTABLE[[#This Row],[UnitCost]]) -> 161.84
A83: O00033 | B83: SV30T9 | C83: 1 | D83: =VLOOKUP($B83,Menu!$A$1:$F$20,MATCH($D$1,Menu!$A$1:$F$1,0),0) -> 39.95 | E83: =VLOOKUP($B83,Menu!$A$1:$F$20,MATCH(OrderLines!E$1,Menu!$A$1:$F$1,0),0) -> Snack | F83: =VLOOKUP($B83,Menu!$A$1:$F$20,MATCH(OrderLines!F$1,Menu!$A$1:$F$1,0),0) -> 15.51 | G83: =VLOOKUP($A83,Orders!$A$1:$H$361,MATCH($G$1,Orders!$A$1:$H$1,0),0) -> 45880 | H83: =VLOOKUP($A83,Orders!$A$1:$H$361,MATCH(OrderLines!$H$1,Orders!$A$1:$H$1,0),0) -> Plant 2 Canteen | I83: =VLOOKUP($A83,Orders!$A$1:$H$361,MATCH(OrderLines!$I$1,Orders!$A$1:$H$1,0),0) -> 0 | J83: =$C83*$D83*(1-$I83) -> 39.95 | K83: =TEXT($G83,"mmmm") -> August | L83: =VLOOKUP(OrderLines!$A83,Orders!$A$1:$H$361,MATCH(OrderLines!$L$1,Orders!$A$1:$H$1,0),0) -> Breakfast | M83: =VLOOKUP($A83,Orders!$A$1:$H$361,MATCH(OrderLines!$M$1,Orders!$A$1:$H$1,0),0) -> Cash | N83: =IF(AND(COUNTIFS(OrderID,$A83,Category,"hot meal")>=1,COUNTIFS(OrderID,$A83,Category,"beverage")>=1),"Combo","Single") -> Single | O83: {=IF((SUMPRODUCT((OrderID=OrderLines!$A83)*Qty*UnitPrice*DiscountPct))>40,"HighDisc","OK")} -> OK | P83: =(orderlinesTABLE[[#This Row],[UnitCost]]*orderlinesTABLE[[#This Row],[Qty]]) -> 15.51 | Q83: =(orderlinesTABLE[[#This Row],[LineNetAmount]]-orderlinesTABLE[[#This Row],[totalCOST]]) -> 24.44 | R83: =VLOOKUP($B83,Menu!$A$1:$F$20,MATCH(OrderLines!R$1,Menu!$A$1:$F$1,0),0) -> Samosa | S83: {=_xlfn.TEXTJOIN("+",TRUE,_xlfn._xlws.FILTER(orderlinesTABLE[ItemName],OrderID=orderlinesTABLE[[#This Row],[OrderID]]))} -> Samosa+Brownie | T83: =orderlinesTABLE[[#This Row],[Profit]]/orderlinesTABLE[[#This Row],[LineNetAmount]] -> 0.61176471 | U83: =(orderlinesTABLE[[#This Row],[Qty]]*orderlinesTABLE[[#This Row],[UnitCost]]) -> 15.51
A84: O00033 | B84: D9T84A | C84: 3 | D84: =VLOOKUP($B84,Menu!$A$1:$F$20,MATCH($D$1,Menu!$A$1:$F$1,0),0) -> 116.8 | E84: =VLOOKUP($B84,Menu!$A$1:$F$20,MATCH(OrderLines!E$1,Menu!$A$1:$F$1,0),0) -> Dessert | F84: =VLOOKUP($B84,Menu!$A$1:$F$20,MATCH(OrderLines!F$1,Menu!$A$1:$F$1,0),0) -> 48.97 | G84: =VLOOKUP($A84,Orders!$A$1:$H$361,MATCH($G$1,Orders!$A$1:$H$1,0),0) -> 45880 | H84: =VLOOKUP($A84,Orders!$A$1:$H$361,MATCH(OrderLines!$H$1,Orders!$A$1:$H$1,0),0) -> Plant 2 Canteen | I84: =VLOOKUP($A84,Orders!$A$1:$H$361,MATCH(OrderLines!$I$1,Orders!$A$1:$H$1,0),0) -> 0 | J84: =$C84*$D84*(1-$I84) -> 350.4 | K84: =TEXT($G84,"mmmm") -> August | L84: =VLOOKUP(OrderLines!$A84,Orders!$A$1:$H$361,MATCH(OrderLines!$L$1,Orders!$A$1:$H$1,0),0) -> Breakfast | M84: =VLOOKUP($A84,Orders!$A$1:$H$361,MATCH(OrderLines!$M$1,Orders!$A$1:$H$1,0),0) -> Cash | N84: =IF(AND(COUNTIFS(OrderID,$A84,Category,"hot meal")>=1,COUNTIFS(OrderID,$A84,Category,"beverage")>=1),"Combo","Single") -> Single | O84: {=IF((SUMPRODUCT((OrderID=OrderLines!$A84)*Qty*UnitPrice*DiscountPct))>40,"HighDisc","OK")} -> OK | P84: =(orderlinesTABLE[[#This Row],[UnitCost]]*orderlinesTABLE[[#This Row],[Qty]]) -> 146.91 | Q84: =(orderlinesTABLE[[#This Row],[LineNetAmount]]-orderlinesTABLE[[#This Row],[totalCOST]]) -> 203.49 | R84: =VLOOKUP($B84,Menu!$A$1:$F$20,MATCH(OrderLines!R$1,Menu!$A$1:$F$1,0),0) -> Brownie | S84: {=_xlfn.TEXTJOIN("+",TRUE,_xlfn._xlws.FILTER(orderlinesTABLE[ItemName],OrderID=orderlinesTABLE[[#This Row],[OrderID]]))} -> Samosa+Brownie | T84: =orderlinesTABLE[[#This Row],[Profit]]/orderlinesTABLE[[#This Row],[LineNetAmount]] -> 0.5807363 | U84: =(orderlinesTABLE[[#This Row],[Qty]]*orderlinesTABLE[[#This Row],[UnitCost]]) -> 146.91
A85: O00034 | B85: BOC6UZ | C85: 1 | D85: =VLOOKUP($B85,Menu!$A$1:$F$20,MATCH($D$1,Menu!$A$1:$F$1,0),0) -> 32.98 | E85: =VLOOKUP($B85,Menu!$A$1:$F$20,MATCH(OrderLines!E$1,Menu!$A$1:$F$1,0),0) -> Beverage | F85: =VLOOKUP($B85,Menu!$A$1:$F$20,MATCH(OrderLines!F$1,Menu!$A$1:$F$1,0),0) -> 11.84 | G85: =VLOOKUP($A85,Orders!$A$1:$H$361,MATCH($G$1,Orders!$A$1:$H$1,0),0) -> 45851 | H85: =VLOOKUP($A85,Orders!$A$1:$H$361,MATCH(OrderLines!$H$1,Orders!$A$1:$H$1,0),0) -> Head Office Café | I85: =VLOOKUP($A85,Orders!$A$1:$H$361,MATCH(OrderLines!$I$1,Orders!$A$1:$H$1,0),0) -> 0.09 | J85: =$C85*$D85*(1-$I85) -> 30.0118 | K85: =TEXT($G85,"mmmm") -> July | L85: =VLOOKUP(OrderLines!$A85,Orders!$A$1:$H$361,MATCH(OrderLines!$L$1,Orders!$A$1:$H$1,0),0) -> Dinner | M85: =VLOOKUP($A85,Orders!$A$1:$H$361,MATCH(OrderLines!$M$1,Orders!$A$1:$H$1,0),0) -> Cash | N85: =IF(AND(COUNTIFS(OrderID,$A85,Category,"hot meal")>=1,COUNTIFS(OrderID,$A85,Category,"beverage")>=1),"Combo","Single") -> Single | O85: {=IF((SUMPRODUCT((OrderID=OrderLines!$A85)*Qty*UnitPrice*DiscountPct))>40,"HighDisc","OK")} -> OK | P85: =(orderlinesTABLE[[#This Row],[UnitCost]]*orderlinesTABLE[[#This Row],[Qty]]) -> 11.84 | Q85: =(orderlinesTABLE[[#This Row],[LineNetAmount]]-orderlinesTABLE[[#This Row],[totalCOST]]) -> 18.1718 | R85: =VLOOKUP($B85,Menu!$A$1:$F$20,MATCH(OrderLines!R$1,Menu!$A$1:$F$1,0),0) -> Masala Chaas | S85: {=_xlfn.TEXTJOIN("+",TRUE,_xlfn._xlws.FILTER(orderlinesTABLE[ItemName],OrderID=orderlinesTABLE[[#This Row],[OrderID]]))} -> Masala Chaas+Samosa+Coffee | T85: =orderlinesTABLE[[#This Row],[Profit]]/orderlinesTABLE[[#This Row],[LineNetAmount]] -> 0.60548851 | U85: =(orderlinesTABLE[[#This Row],[Qty]]*orderlinesTABLE[[#This Row],[UnitCost]]) -> 11.84
A86: O00034 | B86: SV30T9 | C86: 1 | D86: =VLOOKUP($B86,Menu!$A$1:$F$20,MATCH($D$1,Menu!$A$1:$F$1,0),0) -> 39.95 | E86: =VLOOKUP($B86,Menu!$A$1:$F$20,MATCH(OrderLines!E$1,Menu!$A$1:$F$1,0),0) -> Snack | F86: =VLOOKUP($B86,Menu!$A$1:$F$20,MATCH(OrderLines!F$1,Menu!$A$1:$F$1,0),0) -> 15.51 | G86: =VLOOKUP($A86,Orders!$A$1:$H$361,MATCH($G$1,Orders!$A$1:$H$1,0),0) -> 45851 | H86: =VLOOKUP($A86,Orders!$A$1:$H$361,MATCH(OrderLines!$H$1,Orders!$A$1:$H$1,0),0) -> Head Office Café | I86: =VLOOKUP($A86,Orders!$A$1:$H$361,MATCH(OrderLines!$I$1,Orders!$A$1:$H$1,0),0) -> 0.09 | J86: =$C86*$D86*(1-$I86) -> 36.3545 | K86: =TEXT($G86,"mmmm") -> July | L86: =VLOOKUP(OrderLines!$A86,Orders!$A$1:$H$361,MATCH(OrderLines!$L$1,Orders!$A$1:$H$1,0),0) -> Dinner | M86: =VLOOKUP($A86,Orders!$A$1:$H$361,MATCH(OrderLines!$M$1,Orders!$A$1:$H$1,0),0) -> Cash | N86: =IF(AND(COUNTIFS(OrderID,$A86,Category,"hot meal")>=1,COUNTIFS(OrderID,$A86,Category,"beverage")>=1),"Combo","Single") -> Single | O86: {=IF((SUMPRODUCT((OrderID=OrderLines!$A86)*Qty*UnitPrice*DiscountPct))>40,"HighDisc","OK")} -> OK | P86: =(orderlinesTABLE[[#This Row],[UnitCost]]*orderlinesTABLE[[#This Row],[Qty]]) -> 15.51 | Q86: =(orderlinesTABLE[[#This Row],[LineNetAmount]]-orderlinesTABLE[[#This Row],[totalCOST]]) -> 20.8445 | R86: =VLOOKUP($B86,Menu!$A$1:$F$20,MATCH(OrderLines!R$1,Menu!$A$1:$F$1,0),0) -> Samosa | S86: {=_xlfn.TEXTJOIN("+",TRUE,_xlfn._xlws.FILTER(orderlinesTABLE[ItemName],OrderID=orderlinesTABLE[[#This Row],[OrderID]]))} -> Masala Chaas+Samosa+Coffee | T86: =orderlinesTABLE[[#This Row],[Profit]]/orderlinesTABLE[[#This Row],[LineNetAmount]] -> 0.57336781 | U86: =(orderlinesTABLE[[#This Row],[Qty]]*orderlinesTABLE[[#This Row],[UnitCost]]) -> 15.51
A87: O00034 | B87: BHL1C3 | C87: 1 | D87: =VLOOKUP($B87,Menu!$A$1:$F$20,MATCH($D$1,Menu!$A$1:$F$1,0),0) -> 22.2 | E87: =VLOOKUP($B87,Menu!$A$1:$F$20,MATCH(OrderLines!E$1,Menu!$A$1:$F$1,0),0) -> Beverage | F87: =VLOOKUP($B87,Menu!$A$1:$F$20,MATCH(OrderLines!F$1,Menu!$A$1:$F$1,0),0) -> 9.38 | G87: =VLOOKUP($A87,Orders!$A$1:$H$361,MATCH($G$1,Orders!$A$1:$H$1,0),0) -> 45851 | H87: =VLOOKUP($A87,Orders!$A$1:$H$361,MATCH(OrderLines!$H$1,Orders!$A$1:$H$1,0),0) -> Head Office Café | I87: =VLOOKUP($A87,Orders!$A$1:$H$361,MATCH(OrderLines!$I$1,Orders!$A$1:$H$1,0),0) -> 0.09 | J87: =$C87*$D87*(1-$I87) -> 20.202 | K87: =TEXT($G87,"mmmm") -> July | L87: =VLOOKUP(OrderLines!$A87,Orders!$A$1:$H$361,MATCH(OrderLines!$L$1,Orders!$A$1:$H$1,0),0) -> Dinner | M87: =VLOOKUP($A87,Orders!$A$1:$H$361,MATCH(OrderLines!$M$1,Orders!$A$1:$H$1,0),0) -> Cash | N87: =IF(AND(COUNTIFS(OrderID,$A87,Category,"hot meal")>=1,COUNTIFS(OrderID,$A87,Category,"beverage")>=1),"Combo","Single") -> Single | O87: {=IF((SUMPRODUCT((OrderID=OrderLines!$A87)*Qty*UnitPrice*DiscountPct))>40,"HighDisc","OK")} -> OK | P87: =(orderlinesTABLE[[#This Row],[UnitCost]]*orderlinesTABLE[[#This Row],[Qty]]) -> 9.38 | Q87: =(orderlinesTABLE[[#This Row],[LineNetAmount]]-orderlinesTABLE[[#This Row],[totalCOST]]) -> 10.822 | R87: =VLOOKUP($B87,Menu!$A$1:$F$20,MATCH(OrderLines!R$1,Menu!$A$1:$F$1,0),0) -> Coffee | S87: {=_xlfn.TEXTJOIN("+",TRUE,_xlfn._xlws.FILTER(orderlinesTABLE[ItemName],OrderID=orderlinesTABLE[[#This Row],[OrderID]]))} -> Masala Chaas+Samosa+Coffee | T87: =orderlinesTABLE[[#This Row],[Profit]]/orderlinesTABLE[[#This Row],[LineNetAmount]] -> 0.53568954 | U87: =(orderlinesTABLE[[#This Row],[Qty]]*orderlinesTABLE[[#This Row],[UnitCost]]) -> 9.38
A88: O00035 | B88: D9T84A | C88: 1 | D88: =VLOOKUP($B88,Menu!$A$1:$F$20,MATCH($D$1,Menu!$A$1:$F$1,0),0) -> 116.8 | E88: =VLOOKUP($B88,Menu!$A$1:$F$20,MATCH(OrderLines!E$1,Menu!$A$1:$F$1,0),0) -> Dessert | F88: =VLOOKUP($B88,Menu!$A$1:$F$20,MATCH(OrderLines!F$1,Menu!$A$1:$F$1,0),0) -> 48.97 | G88: =VLOOKUP($A88,Orders!$A$1:$H$361,MATCH($G$1,Orders!$A$1:$H$1,0),0) -> 45892 | H88: =VLOOKUP($A88,Orders!$A$1:$H$361,MATCH(OrderLines!$H$1,Orders!$A$1:$H$1,0),0) -> Head Office Café | I88: =VLOOKUP($A88,Orders!$A$1:$H$361,MATCH(OrderLines!$I$1,Orders!$A$1:$H$1,0),0) -> 0.06 | J88: =$C88*$D88*(1-$I88) -> 109.792 | K88: =TEXT($G88,"mmmm") -> August | L88: =VLOOKUP(OrderLines!$A88,Orders!$A$1:$H$361,MATCH(OrderLines!$L$1,Orders!$A$1:$H$1,0),0) -> Dinner | M88: =VLOOKUP($A88,Orders!$A$1:$H$361,MATCH(OrderLines!$M$1,Orders!$A$1:$H$1,0),0) -> UPI | N88: =IF(AND(COUNTIFS(OrderID,$A88,Category,"hot meal")>=1,COUNTIFS(OrderID,$A88,Category,"beverage")>=1),"Combo","Single") -> Combo | O88: {=IF((SUMPRODUCT((OrderID=OrderLines!$A88)*Qty*UnitPrice*DiscountPct))>40,"HighDisc","OK")} -> HighDisc | P88: =(orderlinesTABLE[[#This Row],[UnitCost]]*orderlinesTABLE[[#This Row],[Qty]]) -> 48.97 | Q88: =(orderlinesTABLE[[#This Row],[LineNetAmount]]-orderlinesTABLE[[#This Row],[totalCOST]]) -> 60.822 | R88: =VLOOKUP($B88,Menu!$A$1:$F$20,MATCH(OrderLines!R$1,Menu!$A$1:$F$1,0),0) -> Brownie | S88: {=_xlfn.TEXTJOIN("+",TRUE,_xlfn._xlws.FILTER(orderlinesTABLE[ItemName],OrderID=orderlinesTABLE[[#This Row],[OrderID]]))} -> Brownie+Veg Thali+Gulab Jamun (2 pc)+Bottled Water | T88: =orderlinesTABLE[[#This Row],[Profit]]/orderlinesTABLE[[#This Row],[LineNetAmount]] -> 0.55397479 | U88: =(orderlinesTABLE[[#This Row],[Qty]]*orderlinesTABLE[[#This Row],[UnitCost]]) -> 48.97
A89: O00035 | B89: HXAJI0 | C89: 2 | D89: =VLOOKUP($B89,Menu!$A$1:$F$20,MATCH($D$1,Menu!$A$1:$F$1,0),0) -> 227.61 | E89: =VLOOKUP($B89,Menu!$A$1:$F$20,MATCH(OrderLines!E$1,Menu!$A$1:$F$1,0),0) -> Hot Meal | F89: =VLOOKUP($B89,Menu!$A$1:$F$20,MATCH(OrderLines!F$1,Menu!$A$1:$F$1,0),0) -> 96.22 | G89: =VLOOKUP($A89,Orders!$A$1:$H$361,MATCH($G$1,Orders!$A$1:$H$1,0),0) -> 45892 | H89: =VLOOKUP($A89,Orders!$A$1:$H$361,MATCH(OrderLines!$H$1,Orders!$A$1:$H$1,0),0) -> Head Office Café | I89: =VLOOKUP($A89,Orders!$A$1:$H$361,MATCH(OrderLines!$I$1,Orders!$A$1:$H$1,0),0) -> 0.06 | J89: =$C89*$D89*(1-$I89) -> 427.9068 | K89: =TEXT($G89,"mmmm") -> August | L89: =VLOOKUP(OrderLines!$A89,Orders!$A$1:$H$361,MATCH(OrderLines!$L$1,Orders!$A$1:$H$1,0),0) -> Dinner | M89: =VLOOKUP($A89,Orders!$A$1:$H$361,MATCH(OrderLines!$M$1,Orders!$A$1:$H$1,0),0) -> UPI | N89: =IF(AND(COUNTIFS(OrderID,$A89,Category,"hot meal")>=1,COUNTIFS(OrderID,$A89,Category,"beverage")>=1),"Combo","Single") -> Combo | O89: {=IF((SUMPRODUCT((OrderID=OrderLines!$A89)*Qty*UnitPrice*DiscountPct))>40,"HighDisc","OK")} -> HighDisc | P89: =(orderlinesTABLE[[#This Row],[UnitCost]]*orderlinesTABLE[[#This Row],[Qty]]) -> 192.44 | Q89: =(orderlinesTABLE[[#This Row],[LineNetAmount]]-orderlinesTABLE[[#This Row],[totalCOST]]) -> 235.4668 | R89: =VLOOKUP($B89,Menu!$A$1:$F$20,MATCH(OrderLines!R$1,Menu!$A$1:$F$1,0),0) -> Veg Thali | S89: {=_xlfn.TEXTJOIN("+",TRUE,_xlfn._xlws.FILTER(orderlinesTABLE[ItemName],OrderID=orderlinesTABLE[[#This Row],[OrderID]]))} -> Brownie+Veg Thali+Gulab Jamun (2 pc)+Bottled Water | T89: =orderlinesTABLE[[#This Row],[Profit]]/orderlinesTABLE[[#This Row],[LineNetAmount]] -> 0.5502759 | U89: =(orderlinesTABLE[[#This Row],[Qty]]*orderlinesTABLE[[#This Row],[UnitCost]]) -> 192.44
A90: O00035 | B90: DH9SDB | C90: 1 | D90: =VLOOKUP($B90,Menu!$A$1:$F$20,MATCH($D$1,Menu!$A$1:$F$1,0),0) -> 76.55 | E90: =VLOOKUP($B90,Menu!$A$1:$F$20,MATCH(OrderLines!E$1,Menu!$A$1:$F$1,0),0) -> Dessert | F90: =VLOOKUP($B90,Menu!$A$1:$F$20,MATCH(OrderLines!F$1,Menu!$A$1:$F$1,0),0) -> 38.23 | G90: =VLOOKUP($A90,Orders!$A$1:$H$361,MATCH($G$1,Orders!$A$1:$H$1,0),0) -> 45892 | H90: =VLOOKUP($A90,Orders!$A$1:$H$361,MATCH(OrderLines!$H$1,Orders!$A$1:$H$1,0),0) -> Head Office Café | I90: =VLOOKUP($A90,Orders!$A$1:$H$361,MATCH(OrderLines!$I$1,Orders!$A$1:$H$1,0),0) -> 0.06 | J90: =$C90*$D90*(1-$I90) -> 71.957 | K90: =TEXT($G90,"mmmm") -> August | L90: =VLOOKUP(OrderLines!$A90,Orders!$A$1:$H$361,MATCH(OrderLines!$L$1,Orders!$A$1:$H$1,0),0) -> Dinner | M90: =VLOOKUP($A90,Orders!$A$1:$H$361,MATCH(OrderLines!$M$1,Orders!$A$1:$H$1,0),0) -> UPI | N90: =IF(AND(COUNTIFS(OrderID,$A90,Category,"hot meal")>=1,COUNTIFS(OrderID,$A90,Category,"beverage")>=1),"Combo","Single") -> Combo | O90: {=IF((SUMPRODUCT((OrderID=OrderLines!$A90)*Qty*UnitPrice*DiscountPct))>40,"HighDisc","OK")} -> HighDisc | P90: =(orderlinesTABLE[[#This Row],[UnitCost]]*orderlinesTABLE[[#This Row],[Qty]]) -> 38.23 | Q90: =(orderlinesTABLE[[#This Row],[LineNetAmount]]-orderlinesTABLE[[#This Row],[totalCOST]]) -> 33.727 | R90: =VLOOKUP($B90,Menu!$A$1:$F$20,MATCH(OrderLines!R$1,Menu!$A$1:$F$1,0),0) -> Gulab Jamun (2 pc) | S90: {=_xlfn.TEXTJOIN("+",TRUE,_xlfn._xlws.FILTER(orderlinesTABLE[ItemName],OrderID=orderlinesTABLE[[#This Row],[OrderID]]))} -> Brownie+Veg Thali+Gulab Jamun (2 pc)+Bottled Water | T90: =orderlinesTABLE[[#This Row],[Profit]]/orderlinesTABLE[[#This Row],[LineNetAmount]] -> 0.46871048 | U90: =(orderlinesTABLE[[#This Row],[Qty]]*orderlinesTABLE[[#This Row],[UnitCost]]) -> 38.23
... A925: O00360 | B925: BTIQJ7 | C925: 2 | D925: =VLOOKUP($B925,Menu!$A$1:$F$20,MATCH($D$1,Menu!$A$1:$F$1,0),0) -> 30.34 | E925: =VLOOKUP($B925,Menu!$A$1:$F$20,MATCH(OrderLines!E$1,Menu!$A$1:$F$1,0),0) -> Beverage | F925: =VLOOKUP($B925,Menu!$A$1:$F$20,MATCH(OrderLines!F$1,Menu!$A$1:$F$1,0),0) -> 14.18 | G925: =VLOOKUP($A925,Orders!$A$1:$H$361,MATCH($G$1,Orders!$A$1:$H$1,0),0) -> 45878 | H925: =VLOOKUP($A925,Orders!$A$1:$H$361,MATCH(OrderLines!$H$1,Orders!$A$1:$H$1,0),0) -> Plant 2 Canteen | I925: =VLOOKUP($A925,Orders!$A$1:$H$361,MATCH(OrderLines!$I$1,Orders!$A$1:$H$1,0),0) -> 0.04 | J925: =$C925*$D925*(1-$I925) -> 58.2528 | K925: =TEXT($G925,"mmmm") -> August | L925: =VLOOKUP(OrderLines!$A925,Orders!$A$1:$H$361,MATCH(OrderLines!$L$1,Orders!$A$1:$H$1,0),0) -> Dinner | M925: =VLOOKUP($A925,Orders!$A$1:$H$361,MATCH(OrderLines!$M$1,Orders!$A$1:$H$1,0),0) -> UPI | N925: =IF(AND(COUNTIFS(OrderID,$A925,Category,"hot meal")>=1,COUNTIFS(OrderID,$A925,Category,"beverage")>=1),"Combo","Single") -> Combo | O925: {=IF((SUMPRODUCT((OrderID=OrderLines!$A925)*Qty*UnitPrice*DiscountPct))>40,"HighDisc","OK")} -> HighDisc | P925: =(orderlinesTABLE[[#This Row],[UnitCost]]*orderlinesTABLE[[#This Row],[Qty]]) -> 28.36 | Q925: =(orderlinesTABLE[[#This Row],[LineNetAmount]]-orderlinesTABLE[[#This Row],[totalCOST]]) -> 29.8928 | R925: =VLOOKUP($B925,Menu!$A$1:$F$20,MATCH(OrderLines!R$1,Menu!$A$1:$F$1,0),0) -> Tea | S925: {=_xlfn.TEXTJOIN("+",TRUE,_xlfn._xlws.FILTER(orderlinesTABLE[ItemName],OrderID=orderlinesTABLE[[#This Row],[OrderID]]))} -> Paneer Butter Masala + Naan+Chicken Thali+Tea | T925: =orderlinesTABLE[[#This Row],[Profit]]/orderlinesTABLE[[#This Row],[LineNetAmount]] -> 0.51315645 | U925: =(orderlinesTABLE[[#This Row],[Qty]]*orderlinesTABLE[[#This Row],[UnitCost]]) -> 28.36

Sheet pivots
M1: 1. Make a summary of combo-order performance showing total combo orders, combo orders as a percentage of all orders,
A2: total combo orders | B2: {=ROWS(_xlfn.UNIQUE(_xlfn._xlws.FILTER([0]!OrderID,ComboFlag="combo")))} -> 86 | M2: average ticket size of combo orders, and average gross profit per combo order.
A3: t.o | B3: =ROWS(Orders!OrderID) -> 360
A4: % of combo orders | B4: =(B2/B3) -> 0.23888889
A6: average ticket size of combo orders | B6: {=AVERAGE(SUMIFS([0]!LineNetAmount,ComboFlag,"combo",OrderID,_xlfn.UNIQUE(_xlfn._xlws.FILTER(OrderID,ComboFlag="combo"))))} -> 544.19233
A7: average gross profit per combo orders | C7: {=AVERAGE(SUMIFS([0]!Profit,ComboFlag,"combo",OrderID,_xlfn.UNIQUE(_xlfn._xlws.FILTER(OrderID,ComboFlag="combo"))))} -> 278.79768
B11: combo | C11: single | D11: gap | M11: 2. Compare Combo and Single orders on average ticket size, average total cost, average gross profit, and gross margin. Show
A12: average ticket size | B12: {=AVERAGE(SUMIFS([0]!LineNetAmount,ComboFlag,"combo",OrderID,_xlfn.UNIQUE(_xlfn._xlws.FILTER(OrderID,ComboFlag="combo"))))} -> 544.19233 | C12: {=AVERAGE(SUMIFS([0]!LineNetAmount,ComboFlag,"single",OrderID,_xlfn.UNIQUE(_xlfn._xlws.FILTER(OrderID,ComboFlag="single"))))} -> 313.31055 | D12: =(B12-C12) -> 230.88179 | M12: the performance gap between the two groups.
A13: average total cost | B13: {=AVERAGE(SUMIFS([0]!totalCOST,ComboFlag,"combo",OrderID,_xlfn.UNIQUE(_xlfn._xlws.FILTER(OrderID,ComboFlag="combo"))))} -> 265.39465 | C13: {=AVERAGE(SUMIFS([0]!totalCOST,ComboFlag,"single",OrderID,_xlfn.UNIQUE(_xlfn._xlws.FILTER(OrderID,ComboFlag="single"))))} -> 154.47212 | D13: =B13-C13 -> 110.92253
A14: average gross profit | B14: {=AVERAGE(SUMIFS([0]!Profit,ComboFlag,"combo",OrderID,_xlfn.UNIQUE(_xlfn._xlws.FILTER(OrderID,ComboFlag="combo"))))} -> 278.79768 | C14: {=AVERAGE(SUMIFS([0]!Profit,ComboFlag,"single",OrderID,_xlfn.UNIQUE(_xlfn._xlws.FILTER(OrderID,ComboFlag="single"))))} -> 158.83843 | D14: =B14-C14 -> 119.95925
A15: gross margin | B15: =SUMIFS([0]!Profit,ComboFlag,"combo")/SUMIFS([0]!LineNetAmount,ComboFlag,"combo") -> 0.51231461 | C15: =SUMIFS([0]!Profit,ComboFlag,"single")/SUMIFS([0]!LineNetAmount,ComboFlag,"single") -> 0.50696803 | D15: =B15-C15 -> 0.0053465805
C20: % of combo orders
B21: Head Office Café | C21: {=ROWS(_xlfn.UNIQUE(_xlfn._xlws.FILTER([0]!OrderID,([0]!ComboFlag="combo")*([0]!Branch=$B21))))/ROWS(_xlfn.UNIQUE(_xlfn._xlws.FILTER([0]!OrderID,Branch=$B21)))} -> 0.2892562 | M21: 3. Show the percentage of Combo orders out of total orders across each branch so I can identify where combo adoption is
B22: Plant 1 Canteen | C22: {=ROWS(_xlfn.UNIQUE(_xlfn._xlws.FILTER([0]!OrderID,([0]!ComboFlag="combo")*([0]!Branch=$B22))))/ROWS(_xlfn.UNIQUE(_xlfn._xlws.FILTER([0]!OrderID,Branch=$B22)))} -> 0.13761468 | M22: strongest.
B23: Plant 2 Canteen | C23: {=ROWS(_xlfn.UNIQUE(_xlfn._xlws.FILTER([0]!OrderID,([0]!ComboFlag="combo")*([0]!Branch=$B23))))/ROWS(_xlfn.UNIQUE(_xlfn._xlws.FILTER([0]!OrderID,Branch=$B23)))} -> 0.27692308
C30: % of combo orders | M30: 4. Show the percentage of Combo orders out of total orders across each shift so I can identify which shift generates the highest
B31: Breakfast | C31: {=ROWS(_xlfn.UNIQUE(_xlfn._xlws.FILTER([0]!OrderID,([0]!ComboFlag="combo")*([0]!Shift=$B31))))/ROWS(_xlfn.UNIQUE(_xlfn._xlws.FILTER([0]!OrderID,Shift=$B31)))} -> 0.2259887 | M31: proportion of combo orders.
